Workbook

Sheet Template
A1: HYBRID OR INSTALLER PLUMBER COMMISSION TEMPLATE
B2: WEEKLY COMMISSION | F2: WEEK ENDING
K3: PHOTOS | N3: QUOTE | Q3: INVOICE
B4: BOOKED JOBS | C4: =C5+C6 -> 0 | E4: WEEKLY TARGET | K4: BEFORE | L4: AFTER | M4: RECEIPT | N4: DESCRIPTION | O4: SIGNED | P4: EMAILED | Q4: DESCRIPTION | R4: SIGNED | S4: EMAILED | T4: 5 Star Review
B5: SUCCESSFUL | C5: =P12 -> 0 | E5: Tier 1 | F5: 0.05 | J5: TAKEN | K5: =K46 -> 0 | L5: =L46 -> 0 | M5: =M46 -> 0 | N5: =N46 -> 0 | O5: =O46 -> 0 | P5: =P46 -> 0 | Q5: =Q46 -> 0 | R5: =R46 -> 0 | S5: =S46 -> 0 | T5: =T143 -> 0
B6: UNSUCCESSFUL | C6: =P13 -> 0 | J6: % | K6: =K46/K45 -> #DIV/0! | L6: =L46/L45 -> #DIV/0! | M6: =M46/M45 -> #DIV/0! | N6: =N46/N45 -> #DIV/0! | O6: =O46/O45 -> #DIV/0! | P6: =P46/P45 -> #DIV/0! | Q6: =Q46/Q45 -> #DIV/0! | R6: =R46/R45 -> #DIV/0! | S6: =S46/S45 -> #DIV/0! | U6: M8 Notes
B7: SUCESSFUL (%) | C7: =P14 -> #DIV/0!
F8: ACTUAL | G8: POTENTIAL | H8: Exc. SUPER
B9: AVERAGE SALE | C9: =P15 -> #DIV/0! | E9: NET PROFIT | F9: =P11 -> 0 | G9: =I45+I79+I101 -> 0 | K9: DAILY NET PROFIT | R9: WEEKDAY | S9: WEEKEND
E10: UNLOCKED | F10: =F5 -> 0.05 | K10: MON | L10: TUE | M10: WED | N10: THU | O10: FRI | P10: Total | Q10: SAT | R10: Awaiting Payment | S10: Awaiting Payment
E11: COMMISSION - PAY OUT | F11: =F9*F10 -> 0 | G11: $- | H11: =F11/1.12 -> 0 | P11: =SUM(K11:O11) -> 0 | Q11: 0 | R11: =I79+I101 -> 0 | S11: =I90+I112 -> 0
E12: EMERGENCY | F12: =Q11 -> 0 | G12: $- | J12: Successful | P12: =SUM(K12:O12) -> 0
E13: EMERGENCY - PAY OUT | F13: =F12*0.25 -> 0 | G13: $- | H13: =F13/1.12 -> 0 | J13: Unsuccessful | P13: =SUM(K13:O13) -> 0
E14: PREV. WEEK | G14: $- | J14: Success rate | K14: =K12/(K12+K13) -> #DIV/0! | L14: =L12/(L12+L13) -> #DIV/0! | M14: =M12/(M12+M13) -> #DIV/0! | N14: =N12/(N12+N13) -> #DIV/0! | O14: =O12/(O12+O13) -> #DIV/0! | P14: =P12/(P12+P13) -> #DIV/0! | Q14: =Q12/(Q12+Q13) -> #DIV/0!
E15: PREV. WEEK - PAY OUT | F15: =F14*0.05 -> 0 | G15: $- | H15: =F15/1.12 -> 0 | J15: Avg sale | K15: =K11/K12 -> #DIV/0! | L15: =L11/L12 -> #DIV/0! | M15: =M11/M12 -> #DIV/0! | N15: =N11/N12 -> #DIV/0! | O15: =O11/O12 -> #DIV/0! | P15: =P11/P12 -> #DIV/0! | Q15: =Q11/Q12 -> #DIV/0!
E16: 5 Star Review | H16: =F16/1.12 -> 0
E17: 5 Star Notes | F17: =T6 -> 0 | K17: Managment Summary - SALES ONLY - COLUMN F | R17: WEEKDAY | S17: WEEKEND
K18: MON | L18: TUE | M18: WED | N18: THU | O18: FRI | P18: Total | Q18: SAT | R18: Awaiting Payment | S18: Awaiting Payment
Q19: 0 | R19: =F79+F101 -> 0 | S19: =F90+F112 -> 0
J20: Successful | K20: =K12 -> 0 | L20: =L12 -> 0 | M20: =M12 -> 0 | N20: =N12 -> 0 | O20: =O12 -> 0 | P20: =P12 -> 0 | Q20: =Q12 -> 0
J21: Unsuccessful | K21: =K13 -> 0 | L21: =L13 -> 0 | M21: =M13 -> 0 | N21: =N13 -> 0 | O21: =O13 -> 0 | P21: =P13 -> 0 | Q21: =Q13 -> 0
J22: Success rate | K22: =K20/(K20+K21) -> #DIV/0! | L22: =L20/(L20+L21) -> #DIV/0! | M22: =M20/(M20+M21) -> #DIV/0! | N22: =N20/(N20+N21) -> #DIV/0! | O22: =O20/(O20+O21) -> #DIV/0! | P22: =P20/(P20+P21) -> #DIV/0! | Q22: =Q20/(Q20+Q21) -> #DIV/0!
J23: Avg sale | K23: =K19/K20 -> #DIV/0! | L23: =L19/L20 -> #DIV/0! | M23: =M19/M20 -> #DIV/0! | N23: =N19/N20 -> #DIV/0! | O23: =O19/O20 -> #DIV/0! | P23: =P19/P20 -> #DIV/0! | Q23: =Q19/Q20 -> #DIV/0!
B26: JOB DETAILS | F26: JOB AMOUNT | K26: PHOTOS | N26: QUOTE | Q26: INVOICE | U26: NOTES
B27: JOB STATUS | C27: DATE | D27: JOB # | E27: SUBURB | F27: AMOUNT EXC. GST | G27: MATERIALS | H27: Merchant Fees | I27: NET PROFIT | J27: PAID | K27: BEFORE | L27: AFTER | M27: RECEIPT | N27: DESCRIPTION | O27: SIGNED | P27: EMAILED | Q27: DESCRIPTION | R27: SIGNED | S27: EMAILED | T27: 5 Star Review | V27: EFTPOS | W27: CASH | X27: Payment Plan
B28: COMPLETED & PAID JOBS
B29: 1 | I29: =F29-G29-H29 -> 0
B30: =B29+1 -> 2 | I30: =F30-G30-H30 -> 0
B31: =B30+1 -> 3 | I31: =F31-G31-H31 -> 0
B32: =B31+1 -> 4 | I32: =F32-G32-H32 -> 0
B33: =B32+1 -> 5 | I33: =F33-G33-H33 -> 0
B34: =B33+1 -> 6 | I34: =F34-G34-H34 -> 0
B35: =B34+1 -> 7 | I35: =F35-G35-H35 -> 0
B36: =B35+1 -> 8 | I36: =F36-G36-H36 -> 0
B37: =B36+1 -> 9 | I37: =F37-G37-H37 -> 0
B38: =B37+1 -> 10 | I38: =F38-G38-H38 -> 0
B39: =B38+1 -> 11 | I39: =F39-G39-H39 -> 0
B40: =B39+1 -> 12 | I40: =F40-G40-H40 -> 0
B41: =B40+1 -> 13 | I41: =F41-G41-H41 -> 0
... B44: =B43+1 -> 16 | I44: =F44-G44-H44 -> 0
F45: =SUM(F29:F44) -> 0 | G45: =SUM(G29:G44) -> 0 | H45: =SUM(H29:H44) -> 0 | I45: =SUM(I29:I44) -> 0 | K45: =COUNT(K29:K44) -> 0 | L45: =COUNT(L29:L44) -> 0 | M45: =COUNT(M29:M44) -> 0 | N45: =COUNT(N29:N44) -> 0 | O45: =COUNT(O29:O44) -> 0 | P45: =COUNT(P29:P44) -> 0 | Q45: =COUNT(Q29:Q44) -> 0 | R45: =COUNT(R29:R44) -> 0 | S45: =COUNT(S29:S44) -> 0
K46: =SUM(K29:K44) -> 0 | L46: =SUM(L29:L44) -> 0 | M46: =SUM(M29:M44) -> 0 | N46: =SUM(N29:N44) -> 0 | O46: =SUM(O29:O44) -> 0 | P46: =SUM(P29:P44) -> 0 | Q46: =SUM(Q29:Q44) -> 0 | R46: =SUM(R29:R44) -> 0 | S46: =SUM(S29:S44) -> 0
B48: WEEKEND COMPLETED & PAID JOBS
B49: 1 | I49: =F49-G49-H49 -> 0
B50: =B49+1 -> 2 | I50: =F50-G50-H50 -> 0
B51: =B50+1 -> 3 | I51: =F51-G51-H51 -> 0
B52: =B51+1 -> 4 | I52: =F52-G52-H52 -> 0
B53: =B52+1 -> 5 | I53: =F53-G53-H53 -> 0
B54: =B53+1 -> 6 | I54: =F54-G54-H54 -> 0
B55: =B54+1 -> 7 | I55: =F55-G55-H55 -> 0
B56: =B55+1 -> 8 | I56: =F56-G56-H56 -> 0
F57: =SUM(F49:F56) -> 0 | G57: =SUM(G49:G56) -> 0 | H57: =SUM(H49:H56) -> 0 | I57: =SUM(I49:I56) -> 0
B59: PREVIOUS JOBS COMPLETED & PAID (COMMISSION) - Modoras Team Please do ADD to THIS SECTION or AMEND/TOUCH
B60: 1 | I60: =F60-G60-H60 -> 0
B61: =B60+1 -> 2 | I61: =F61-G61-H61 -> 0
B62: =B61+1 -> 3 | I62: =F62-G62-H62 -> 0
B63: =B62+1 -> 4 | I63: =F63-G63-H63 -> 0
B64: =B63+1 -> 5 | I64: =F64-G64-H64 -> 0
B65: =B64+1 -> 6 | I65: =F65-G65-H65 -> 0
B66: =B65+1 -> 7 | I66: =F66-G66-H66 -> 0
B67: =B66+1 -> 8 | I67: =F67-G67-H67 -> 0
F68: =SUM(F60:F67) -> 0 | G68: =SUM(G60:G67) -> 0 | H68: =SUM(H60:H67) -> 0 | I68: =SUM(I60:I67) -> 0
B70: CURRENT JOBS COMPLETED (AWAITING PAYMENT)
B71: 1 | I71: =F71-G71-H71 -> 0
B72: =B71+1 -> 2 | I72: =F72-G72-H72 -> 0
B73: =B72+1 -> 3 | I73: =F73-G73-H73 -> 0
B74: =B73+1 -> 4 | I74: =F74-G74-H74 -> 0
B75: =B74+1 -> 5 | I75: =F75-G75-H75 -> 0
B76: =B75+1 -> 6 | I76: =F76-G76-H76 -> 0
B77: =B76+1 -> 7 | I77: =F77-G77-H77 -> 0
B78: =B77+1 -> 8 | I78: =F78-G78-H78 -> 0
F79: =SUM(F71:F78) -> 0 | G79: =SUM(G71:G78) -> 0 | H79: =SUM(H71:H78) -> 0 | I79: =SUM(I71:I78) -> 0
B81: WEEKEND CURRENT JOBS COMPLETED (AWAITING PAYMENT)
B82: 1 | I82: =F82-G82-H82 -> 0
B83: =B82+1 -> 2 | I83: =F83-G83-H83 -> 0
B84: =B83+1 -> 3 | I84: =F84-G84-H84 -> 0
B85: =B84+1 -> 4 | I85: =F85-G85-H85 -> 0
B86: =B85+1 -> 5 | I86: =F86-G86-H86 -> 0
B87: =B86+1 -> 6 | I87: =F87-G87-H87 -> 0
B88: =B87+1 -> 7 | I88: =F88-G88-H88 -> 0
B89: =B88+1 -> 8 | I89: =F89-G89-H89 -> 0
F90: =SUM(F82:F89) -> 0 | G90: =SUM(G82:G89) -> 0 | H90: =SUM(H82:H89) -> 0 | I90: =SUM(I82:I89) -> 0
B92: CURRENT WORK ORDERS (AWAITING PAYMENT)
B93: 1 | I93: =F93-G93-H93 -> 0
B94: =B93+1 -> 2 | I94: =F94-G94-H94 -> 0
B95: =B94+1 -> 3 | I95: =F95-G95-H95 -> 0
B96: =B95+1 -> 4 | I96: =F96-G96-H96 -> 0
B97: =B96+1 -> 5 | I97: =F97-G97-H97 -> 0
B98: =B97+1 -> 6 | I98: =F98-G98-H98 -> 0
B99: =B98+1 -> 7 | I99: =F99-G99-H99 -> 0
B100: =B99+1 -> 8 | I100: =F100-G100-H100 -> 0
F101: =SUM(F93:F100) -> 0 | G101: =SUM(G93:G100) -> 0 | H101: =SUM(H93:H100) -> 0 | I101: =SUM(I93:I100) -> 0
B103: WEEKEND WORK ORDERS (AWAITING PAYMENT)
B104: 1 | I104: =F104-G104-H104 -> 0
B105: =B104+1 -> 2 | I105: =F105-G105-H105 -> 0
B106: =B105+1 -> 3 | I106: =F106-G106-H106 -> 0
B107: =B106+1 -> 4 | I107: =F107-G107-H107 -> 0
B108: =B107+1 -> 5 | I108: =F108-G108-H108 -> 0
B109: =B108+1 -> 6 | I109: =F109-G109-H109 -> 0
B110: =B109+1 -> 7 | I110: =F110-G110-H110 -> 0
...

Sheet Mgmt Summary
B3: WEEKLY TOTALS - 6th July 2025 | I3: WEEKLY | N3: COMMISSION | O3: WEEKEND
C4: MONDAY | D4: TUESDAY | E4: WEDNESDAY | F4: THURSDAY | G4: FRIDAY | H4: ACTUAL TOTAL | I4: TARGETS[S] | J4: RUNNING BAL | K4: WEEKEND | L4: COMMISSION | M4: AWAITING PAYMENT | N4: COMPLETED & PAID | O4: AWAITING PAYMENT
B5: Mathew B | C5: ='Mathew B'!K135 -> 12985 | D5: ='Mathew B'!L135 -> 6408 | E5: ='Mathew B'!M135 -> 5090 | F5: ='Mathew B'!N135 -> 6476.5 | G5: ='Mathew B'!O135 -> 21827 | H5: ='Mathew B'!P135 -> 52786.5 | I5: 50000 | J5: =-I5+H5 -> 2786.5 | K5: ='Mathew B'!Q135 -> 0 | L5: =H5 -> 52786.5 | M5: ='Mathew B'!R135 -> 17953 | N5: =L5-M5 -> 34833.5 | O5: ='Mathew B'!S135 -> 0 | P5: ='Mathew B'!F166+'Mathew B'!F177+'Mathew B'!F181 -> 52786.5 | Q5: =H5-P5 -> 0
B6: Success rate | C6: {='Mathew B'!K138:K139} -> 0.57142857 | D6: {='Mathew B'!L138:L139} -> 0.38461538 | E6: {='Mathew B'!M138:M139} -> 0.42857143 | F6: {='Mathew B'!N138:N139} -> 0.625 | G6: {='Mathew B'!O138:O139} -> 0.6 | H6: {='Mathew B'!P138:P139} -> 0.51111111 | K6: {='Mathew B'!Q138:Q139} -> #DIV/0!
B7: Avg sale | C7: 3246.25 | D7: 1281.6 | E7: 1696.6667 | F7: 1295.3 | G7: 3637.8333 | H7: 2295.0652 | K7: #DIV/0!
B8: Ben | C8: ='Ben - No OT'!K101 -> 8233 | D8: ='Ben - No OT'!L101 -> 4080 | E8: ='Ben - No OT'!M101 -> 16035 | F8: ='Ben - No OT'!N101 -> 1138 | G8: ='Ben - No OT'!O101 -> 2457.05 | H8: ='Ben - No OT'!P101 -> 31943.05 | I8: 25000 | J8: =-I8+H8 -> 6943.05 | K8: ='Ben - No OT'!Q101 -> 3206 | L8: =H8 -> 31943.05 | M8: ='Ben - No OT'!R101 -> 18484 | N8: =L8-M8 -> 13459.05 | O8: ='Ben - No OT'!S101 -> 0 | P8: ='Ben - No OT'!F122+'Ben - No OT'!F142+'Ben - No OT'!F147 -> 31943.05 | Q8: =H8-P8 -> 0
B9: Success rate | C9: {='Ben - No OT'!K104:K105} -> 0.71428571 | D9: {='Ben - No OT'!L104:L105} -> 0.5 | E9: {='Ben - No OT'!M104:M105} -> 0.6 | F9: {='Ben - No OT'!N104:N105} -> 0.33333333 | G9: {='Ben - No OT'!O104:O105} -> 0.5 | H9: {='Ben - No OT'!P104:P105} -> 0.55555556 | K9: {='Ben - No OT'!Q104:Q105} -> 0.6
B10: Avg sale | C10: 1646.6 | D10: 1360 | E10: 5345 | F10: 1138 | G10: 819.01667 | H10: 2129.5367 | K10: 1068.6667
B11: Shaun | C11: ='Shaun - No OT'!K97 -> 14401.8 | D11: ='Shaun - No OT'!L97 -> 5240.7 | E11: ='Shaun - No OT'!M97 -> 4785 | F11: ='Shaun - No OT'!N97 -> 16173 | G11: ='Shaun - No OT'!O97 -> 5060 | H11: ='Shaun - No OT'!P97 -> 45660.5 | I11: 25000 | J11: =-I11+H11 -> 20660.5 | K11: ='Shaun - No OT'!Q97 -> 0 | L11: =H11 -> 45660.5 | M11: ='Shaun - No OT'!R97 -> 12814 | N11: =L11-M11 -> 32846.5 | O11: ='Shaun - No OT'!S97 -> 0 | P11: ='Shaun - No OT'!F124+'Shaun - No OT'!F133 -> 45660.5 | Q11: =H11-P11 -> 0
B12: Success rate | C12: {='Shaun - No OT'!K100:K101} -> 0.57142857 | D12: {='Shaun - No OT'!L100:L101} -> 0.22222222 | E12: {='Shaun - No OT'!M100:M101} -> 0.625 | F12: {='Shaun - No OT'!N100:N101} -> 0.5 | G12: {='Shaun - No OT'!O100:O101} -> 0.42857143 | H12: {='Shaun - No OT'!P100:P101} -> 0.46153846 | K12: {='Shaun - No OT'!Q100:Q101} -> #DIV/0!
B13: Avg sale | C13: 3600.45 | D13: 2620.35 | E13: 957 | F13: 4043.25 | G13: 1686.6667 | H13: 2536.6944 | K13: #DIV/0!
B14: Jack M | C14: ='Jack M'!K113 -> 4952 | E14: ='Jack M'!M113 -> 18356 | F14: ='Jack M'!N113 -> 0 | G14: ='Jack M'!O113 -> 23016 | H14: ='Jack M'!P113 -> 46324 | I14: 25000 | J14: =-I14+H14 -> 21324 | K14: ='Jack M'!Q113 -> 0 | L14: =H14 -> 46324 | M14: ='Jack M'!R113 -> 35171 | N14: =L14-M14 -> 11153 | O14: ='Jack M'!S113 -> 0 | P14: ='Jack M'!F130+'Jack M'!F142+'Jack M'!F147 -> 46324 | Q14: =H14-P14 -> 0
B15: Success rate | C15: {='Jack M'!K116:K117} -> 0.5 | E15: {='Jack M'!M116:M117} -> 0.42857143 | F15: {='Jack M'!N116:N117} -> 0 | G15: {='Jack M'!O116:O117} -> 0.85714286 | H15: {='Jack M'!P116:P117} -> 0.46153846 | K15: {='Jack M'!Q116:Q117} -> #DIV/0!
B16: Avg sale | C16: 1650.6667 | E16: 6118.6667 | F16: #DIV/0! | G16: 3836 | H16: 3860.3333 | K16: #DIV/0!
B17: Liam | C17: =Liam!K103 -> 4285 | D17: =Liam!L103 -> 5475 | E17: =Liam!M103 -> 21959 | F17: =Liam!N103 -> 1025 | G17: =Liam!O103 -> 6238 | H17: =Liam!P103 -> 38982 | I17: 25000 | J17: =-I17+H17 -> 13982 | K17: =Liam!Q103 -> 0 | L17: =H17 -> 38982 | M17: =Liam!R103 -> 17756 | N17: =L17-M17 -> 21226 | O17: =Liam!S103 -> 0 | P17: =Liam!F124+Liam!F134+Liam!F138 -> 38982 | Q17: =H17-P17 -> 0
B18: Success rate | C18: {=Liam!K106:K107} -> 0.33333333 | D18: {=Liam!L106:L107} -> 0.33333333 | E18: {=Liam!M106:M107} -> 0.75 | F18: {=Liam!N106:N107} -> 0.25 | G18: {=Liam!O106:O107} -> 0.27272727 | H18: {=Liam!P106:P107} -> 0.4 | K18: {=Liam!Q106:Q107} -> #DIV/0!
B19: Avg sale | C19: 2142.5 | D19: 2737.5 | E19: 3659.8333 | F19: 1025 | G19: 2079.3333 | H19: 2784.4286 | K19: #DIV/0!
B20: Rhys C | E20: =+'Rhys C'!M19 -> 2935 | H20: =+'Rhys C'!P19 -> 2935 | I20: 25000 | J20: =-I20+H20 -> -22065 | K20: =+'Rhys C'!Q19 -> 0 | L20: =H20 -> 2935 | M20: =+'Rhys C'!R19 -> 0 | N20: =L20-M20 -> 2935 | O20: =+'Rhys C'!S19 -> 0 | P20: =+'Rhys C'!P19 -> 2935 | Q20: =H20-P20 -> 0
B21: Success rate | E21: =+'Rhys C'!M22 -> 1 | H21: =+'Rhys C'!P22 -> 1 | K21: =+'Rhys C'!Q14 -> #DIV/0!
B22: Avg sale | E22: =+'Rhys C'!M23 -> 2935 | H22: =+'Rhys C'!P23 -> 2935 | K22: =+'Rhys C'!Q15 -> #DIV/0!
B23: TOTAL | C23: =C5+C8+C20+C11+C14+C17 -> 44856.8 | D23: =D5+D8+D20+D11+D14+D17 -> 21203.7 | E23: =E5+E8+E20+E11+E14+E17 -> 69160 | F23: =F5+F8+F20+F11+F14+F17 -> 24812.5 | G23: =G5+G8+G20+G11+G14+G17 -> 58598.05 | H23: =H5+H8+H20+H11+H14+H17 -> 218631.05 | I23: =I5+I8+I20+I11+I14+I17 -> 175000 | J23: =J5+J8+J20+J11+J14+J17 -> 43631.05 | ... O23: =O5+O8+O20+O11+O14+O17 -> 0
B24: *Pending Materials Costs & Merchant Fees | H24: =H23+K23 -> 221837.05 | I24: =I23+J23 -> 218631.05 | M24: =L23-N23 -> 102178 | P24: ='Ben - No OT'!P101+'Jack M'!P113+Liam!P103+'Mathew B'!P135+'Shaun - No OT'!P97+'Rhys C'!P19 -> 218631.05 | Q24: ='Ben - No OT'!Q101+'Jack M'!Q113+Liam!Q103+'Mathew B'!Q135+'Shaun - No OT'!Q97 -> 3206 | R24: ='Ben - No OT'!R101+'Jack M'!R113+Liam!R103+'Mathew B'!R135+'Shaun - No OT'!R97 -> 102178
P25: =P24+Q24 -> 221837.05
B27: WEEKLY TOTALS - 13th July 2025 | I27: WEEKLY | N27: COMMISSION | O27: WEEKEND
C28: MONDAY | D28: TUESDAY | E28: WEDNESDAY | F28: THURSDAY | G28: FRIDAY | H28: ACTUAL TOTAL | I28: TARGETS[S] | J28: RUNNING BAL | K28: WEEKEND | L28: COMMISSION | M28: AWAITING PAYMENT | N28: COMPLETED & PAID | O28: AWAITING PAYMENT
B29: Mathew B | C29: ='Mathew B'!K244 -> 2035 | D29: ='Mathew B'!L244 -> 1734 | E29: ='Mathew B'!M244 -> 12121 | F29: ='Mathew B'!N244 -> 11723 | G29: ='Mathew B'!O244 -> 11872 | H29: ='Mathew B'!P244 -> 39485 | I29: 50000 | J29: =-I29+H29 -> -10515 | L29: =H29 -> 39485 | M29: ='Mathew B'!R244 -> 17223 | N29: =L29-M29 -> 22262 | O29: ='Mathew B'!S244 -> 0 | P29: ='Mathew B'!F271+'Mathew B'!F283+'Mathew B'!F288 -> 39485 | Q29: =H29-P29 -> 0
B30: Success rate | C30: {='Mathew B'!K247:K248} -> 0.1 | D30: {='Mathew B'!L247:L248} -> 0.4 | E30: {='Mathew B'!M247:M248} -> 0.5 | F30: {='Mathew B'!N247:N248} -> 0.5 | G30: {='Mathew B'!O247:O248} -> 0.54545455 | H30: {='Mathew B'!P247:P248} -> 0.41666667
B31: Avg sale | C31: 2035 | D31: 867 | E31: 2020.1667 | F31: 2344.6 | G31: 1978.6667 | H31: 1974.25
B32: Ben | C32: ='Ben - No OT'!K203 -> 3003 | D32: ='Ben - No OT'!L203 -> 481 | E32: ='Ben - No OT'!M203 -> 8094 | F32: ='Ben - No OT'!N203 -> 2399 | G32: ='Ben - No OT'!O203 -> 15264 | H32: ='Ben - No OT'!P203 -> 29241 | I32: 25000 | J32: =-I32+H32 -> 4241 | K32: ='Ben - No OT'!Q203 -> 3786 | L32: =H32 -> 29241 | M32: ='Ben - No OT'!R203 -> 9043 | N32: =L32-M32 -> 20198 | O32: ='Ben - No OT'!S203 -> 0 | P32: ='Ben - No OT'!F226+'Ben - No OT'!F243+'Ben - No OT'!F247 -> 29241 | Q32: =H32-P32 -> 0
B33: Success rate | C33: {='Ben - No OT'!K206:K207} -> 0.75 | D33: {='Ben - No OT'!L206:L207} -> 0.25 | E33: {='Ben - No OT'!M206:M207} -> 0.36363636 | F33: {='Ben - No OT'!N206:N207} -> 0.28571429 | G33: {='Ben - No OT'!O206:O207} -> 0.55555556 | H33: {='Ben - No OT'!P206:P207} -> 0.42857143 | K33: {='Ben - No OT'!Q206:Q207} -> 0.6
B34: Avg sale | C34: 1001 | D34: 481 | E34: 2023.5 | F34: 1199.5 | G34: 3052.8 | H34: 1949.4 | K34: 1262
B35: Shaun | C35: ='Shaun - No OT'!K191 -> 8656 | D35: ='Shaun - No OT'!L191 -> 8938 | H35: ='Shaun - No OT'!P191 -> 17594 | I35: 25000 | J35: =-I35+H35 -> -7406 | L35: =H35 -> 17594 | M35: ='Shaun - No OT'!R191 -> 0 | N35: =L35-M35 -> 17594 | O35: ='Shaun - No OT'!S191 -> 0 | P35: ='Shaun - No OT'!F207 -> 17594 | Q35: =H35-P35 -> 0
B36: Success rate | C36: {='Shaun - No OT'!K194:K195} -> 0.5 | D36: {='Shaun - No OT'!L194:L195} -> 0.75 | H36: {='Shaun - No OT'!P194:P195} -> 0.6
B37: Avg sale | C37: 2885.3333 | D37: 2979.3333 | H37: 2932.3333
B38: Jack M | C38: ='Jack M'!K192 -> 3672 | D38: ='Jack M'!L192 -> 1138 | H38: ='Jack M'!P192 -> 4810 | I38: 25000 | J38: =-I38+H38 -> -20190 | L38: =H38 -> 4810 | M38: ='Jack M'!R192 -> 0 | N38: =L38-M38 -> 4810 | O38: ='Jack M'!S192 -> 0 | P38: ='Jack M'!F206 -> 4810 | Q38: =H38-P38 -> 0
B39: Success rate | C39: {='Jack M'!K195:K196} -> 0.375 | D39: {='Jack M'!L195:L196} -> 0.14285714 | H39: {='Jack M'!P195:P196} -> 0.26666667
B40: Avg sale | C40: 1224 | D40: 1138 | H40: 1202.5
B41: Liam | C41: =Liam!K188 -> 4152 | E41: =Liam!M188 -> 7759 | F41: =Liam!N188 -> 8192 | G41: =Liam!O188 -> 3970 | H41: =Liam!P188 -> 24073 | I41: 25000 | J41: =-I41+H41 -> -927 | L41: =H41 -> 24073 | M41: =Liam!R188 -> 10131 | N41: =L41-M41 -> 13942 | O41: =Liam!S188 -> 0 | P41: =Liam!F208+Liam!F218+Liam!F224 -> 24073 | Q41: =H41-P41 -> 0
B42: Success rate | C42: {=Liam!K191:K192} -> 1 | E42: {=Liam!M191:M192} -> 0.6 | F42: {=Liam!N191:N192} -> 0.45454545 | G42: {=Liam!O191:O192} -> 0.33333333 | H42: {=Liam!P191:P192} -> 0.44117647
B43: Avg sale | C43: 1038 | E43: 2586.3333 | F43: 1638.4 | G43: 1323.3333 | H43: 1604.8667
B44: Jarrod | E44: ='Jarrod - No OT'!M58 -> 17023 | F44: ='Jarrod - No OT'!N58 -> 18411.6 | G44: ='Jarrod - No OT'!O58 -> 24484 | H44: ='Jarrod - No OT'!P58 -> 59918.6 | I44: 25000 | J44: =-I44+H44 -> 34918.6 | L44: =H44 -> 59918.6 | M44: ='Jarrod - No OT'!R58 -> 58780.6 | N44: =L44-M44 -> 1138 | O44: ='Jarrod - No OT'!S58 -> 0 | P44: ='Jarrod - No OT'!F70+'Jarrod - No OT'!F82+'Jarrod - No OT'!F88 -> 59918.6 | Q44: =H44-P44 -> 0
B45: Success rate | E45: {='Jarrod - No OT'!M61:M62} -> 0.28571429 | F45: {='Jarrod - No OT'!N61:N62} -> 0.375 | G45: {='Jarrod - No OT'!O61:O62} -> 0.57142857 | H45: {='Jarrod - No OT'!P61:P62} -> 0.40909091
B46: Avg sale | E46: 8511.5 | F46: 6137.2 | G46: 6121 | H46: 6657.6222
B47: TOTAL | C47: =C29+C32+C35+C38+C41+C44 -> 21518 | D47: =D29+D32+D35+D38+D41+D44 -> 12291 | E47: =E29+E32+E35+E38+E41+E44 -> 44997 | F47: =F29+F32+F35+F38+F41+F44 -> 40725.6 | G47: =G29+G32+G35+G38+G41+G44 -> 55590 | H47: =H29+H32+H35+H38+H41+H44 -> 175121.6 | I47: =I29+I32+I35+I38+I41+I44 -> 175000 | J47: =J29+J32+J35+J38+J41+J44 -> 121.6 | ... O47: =O29+O32+O35+O38+O41+O44 -> 0 | P47: ='Ben - No OT'!P203+'Jack M'!P192+Liam!P188+'Mathew B'!P244+'Shaun - No OT'!P191 -> 115203 | Q47: ='Ben - No OT'!Q203+'Jack M'!Q192+Liam!Q188+'Mathew B'!Q244+'Shaun - No OT'!Q191 -> 3786 | R47: ='Ben - No OT'!R203+'Jack M'!R192+Liam!R188+'Mathew B'!R244+'Shaun - No OT'!R191 -> 36397
B48: *Pending Materials Costs & Merchant Fees | H48: =H47+K47 -> 178907.6 | I48: =I47+J47 -> 175121.6 | M48: =L47-N47 -> 95177.6 | P48: =P47+Q47 -> 118989
B52: WEEKLY TOTALS - 13th July 2025 | C52: 45858 | I52: WEEKLY | N52: COMMISSION | O52: WEEKEND
C53: MONDAY | D53: TUESDAY | E53: WEDNESDAY | F53: THURSDAY | G53: FRIDAY | H53: ACTUAL TOTAL | I53: TARGETS[S] | J53: RUNNING BAL | K53: WEEKEND | L53: COMMISSION | M53: AWAITING PAYMENT | N53: COMPLETED & PAID | O53: AWAITING PAYMENT
B54: Ben | C54: ='Ben - No OT'!K311 -> 11698 | D54: ='Ben - No OT'!L311 -> 3035 | E54: ='Ben - No OT'!M311 -> 34038.6 | F54: ='Ben - No OT'!N311 -> 1134 | G54: ='Ben - No OT'!O311 -> 1162 | H54: ='Ben - No OT'!P311 -> 51067.6 | I54: 50000 | J54: =-I54+H54 -> 1067.6 | K54: ='Ben - No OT'!Q311 -> 0 | L54: =H54 -> 51067.6 | M54: ='Ben - No OT'!R311 -> 29233 | N54: =L54-M54 -> 21834.6 | O54: ='Ben - No OT'!S311 -> 0 | P54: ='Ben - No OT'!F335+'Ben - No OT'!F344 -> 51067.6 | Q54: =H54-P54 -> 0
B55: Success rate | C55: {='Ben - No OT'!K314:K315} -> 0.8 | D55: {='Ben - No OT'!L314:L315} -> 0.5 | E55: {='Ben - No OT'!M314:M315} -> 0.55555556 | F55: {='Ben - No OT'!N314:N315} -> 0.16666667 | G55: {='Ben - No OT'!O314:O315} -> 0.66666667 | H55: {='Ben - No OT'!P314:P315} -> 0.51724138 | K55: {='Ben - No OT'!Q314:Q315} -> #DIV/0!
B56: Avg sale | C56: 2924.5 | D56: 1011.6667 | E56: 6807.72 | F56: 1134 | G56: 581 | H56: 3404.5067 | K56: #DIV/0!
B57: Heath | D57: =Heath!L108 -> 5917 | E57: =Heath!M108 -> 20224.95 | F57: =Heath!N108 -> 4080 | G57: =Heath!O108 -> 7911 | H57: =Heath!P108 -> 38132.95 | I57: 50000 | J57: =-I57+H57 -> -11867.05 | K57: =Heath!Q108 -> 0 | L57: =H57 -> 38132.95 | M57: =Heath!R108 -> 20912 | N57: =L57-M57 -> 17220.95 | O57: =Heath!S108 -> 0 | P57: =Heath!F129+Heath!F134+Heath!F140 -> 38132.95 | Q57: =H57-P57 -> 0
B58: Success rate | D58: {=Heath!L111:L112} -> 0.66666667 | E58: {=Heath!M111:M112} -> 0.625 | F58: {=Heath!N111:N112} -> 0.6 | G58: {=Heath!O111:O112} -> 0.36363636 | H58: {=Heath!P111:P112} -> 0.51851852 | K58: {=Heath!Q111:Q112} -> #DIV/0!
B59: Avg sale | D59: 2958.5 | E59: 4044.99 | F59: 1360 | G59: 1977.75 | H59: 2723.7821 | K59: #DIV/0!
B60: Jarrod | C60: ='Jarrod - No OT'!K126 -> 27894.4 | D60: ='Jarrod - No OT'!L126 -> 4022 | E60: ='Jarrod - No OT'!M126 -> 8712.17 | F60: ='Jarrod - No OT'!N126 -> 3715.9 | G60: ='Jarrod - No OT'!O126 -> 1462 | H60: ='Jarrod - No OT'!P126 -> 45806.47 | I60: 25000 | J60: =-I60+H60 -> 20806.47 | K60: ='Jarrod - No OT'!Q126 -> 0 | L60: =H60 -> 45806.47 | M60: ='Jarrod - No OT'!R126 -> 2034.9 | N60: =L60-M60 -> 43771.57 | O60: ='Jarrod - No OT'!S126 -> 0 | P60: ='Jarrod - No OT'!F153+'Jarrod - No OT'!F165 -> 45806.47 | Q60: =H60-P60 -> 0
B61: Success rate | C61: {='Jarrod - No OT'!K129:K130} -> 0.75 | D61: {='Jarrod - No OT'!L129:L130} -> 0.66666667 | E61: {='Jarrod - No OT'!M129:M130} -> 0.66666667 | F61: {='Jarrod - No OT'!N129:N130} -> 0.18181818 | G61: {='Jarrod - No OT'!O129:O130} -> 0.4 | H61: {='Jarrod - No OT'!P129:P130} -> 0.5 | K61: {='Jarrod - No OT'!Q129:Q130} -> 0
B62: Avg sale | C62: 4649.0667 | D62: 1005.5 | E62: 2178.0425 | F62: 1857.95 | G62: 731 | H62: 2544.8039 | K62: #DIV/0!
B63: Liam | E63: =Liam!M278 -> 10060 | F63: =Liam!N278 -> 6284 | G63: =Liam!O278 -> 23556.6 | H63: =Liam!P278 -> 39900.6 | I63: 25000 | J63: =-I63+H63 -> 14900.6 | K63: =Liam!Q278 -> 0 | L63: =H63 -> 39900.6 | M63: =Liam!R278 -> 23598.6 | N63: =L63-M63 -> 16302 | O63: =Liam!S278 -> 0 | P63: =Liam!F298+Liam!F311 -> 39900.6 | Q63: =H63-P63 -> 0
B64: Success rate | E64: {=Liam!M281:M282} -> 0.625 | F64: {=Liam!N281:N282} -> 0.44444444 | G64: {=Liam!O281:O282} -> 0.42857143 | H64: {=Liam!P281:P282} -> 0.48387097 | K64: {=Liam!Q281:Q282} -> #DIV/0!
B65: Avg sale | E65: 2012 | F65: 1571 | G65: 3926.1 | H65: 2660.04 | K65: #DIV/0!
B66: Mathew B | C66: ='Mathew B'!K361 -> 25523 | D66: ='Mathew B'!L361 -> 16091 | E66: ='Mathew B'!M361 -> 7461.2 | F66: ='Mathew B'!N361 -> 5191 | G66: ='Mathew B'!O361 -> 5920 | H66: ='Mathew B'!P361 -> 60186.2 | I66: 25000 | J66: =-I66+H66 -> 35186.2 | K66: ='Mathew B'!Q361 -> 0 | L66: =H66 -> 60186.2 | M66: ='Mathew B'!R361 -> 14278 | N66: =L66-M66 -> 45908.2 | O66: ='Mathew B'!S361 -> 0 | P66: ='Mathew B'!F392+'Mathew B'!F398+'Mathew B'!F402 -> 60186.2 | Q66: =H66-P66 -> 0
B67: Success rate | C67: {='Mathew B'!K364:K365} -> 0.75 | D67: {='Mathew B'!L364:L365} -> 0.44444444 | E67: {='Mathew B'!M364:M365} -> 0.66666667 | F67: {='Mathew B'!N364:N365} -> 0.5 | G67: {='Mathew B'!O364:O365} -> 0.625 | H67: {='Mathew B'!P364:P365} -> 0.58974359 | K67: {='Mathew B'!Q364:Q365} -> #DIV/0!
B68: Avg sale | C68: 4253.8333 | D68: 4022.75 | E68: 1865.3 | F68: 1297.75 | G68: 1184 | H68: 2616.7913 | K68: #DIV/0!
B69: Mathew H | F69: ='Matthew H - No OT'!N58 -> 11352.6 | H69: ='Matthew H - No OT'!P58 -> 11352.6 | J69: =-I69+H69 -> 11352.6 | K69: ='Matthew H - No OT'!Q58 -> 0 | L69: =H69 -> 11352.6 | M69: ='Matthew H - No OT'!R58 -> 11352.6 | N69: =L69-M69 -> 0 | O69: ='Matthew H - No OT'!S58 -> 0 | P69: ='Matthew H - No OT'!F69+'Matthew H - No OT'!F74 -> 11352.6 | Q69: =H69-P69 -> 0
B70: Success rate | F70: {='Matthew H - No OT'!N61:N62} -> 0.5 | H70: {='Matthew H - No OT'!P61:P62} -> 0.5 | K70: {='Matthew H - No OT'!Q61:Q62} -> #DIV/0!
B71: Avg sale | F71: 11352.6 | H71: 11352.6 | K71: #DIV/0!
B72: Elliot | F72: =Elliot!N19 -> 1461 | G72: =Elliot!O19 -> 481 | H72: =Elliot!P19 -> 1942 | J72: =-I72+H72 -> 1942 | K72: =Elliot!Q19 -> 0 | L72: =H72 -> 1942 | M72: =Elliot!R19 -> 0 | N72: =L72-M72 -> 1942 | O72: =Elliot!S19 -> 0 | P72: =Elliot!F30 -> 1461 | Q72: =H72-P72 -> 481
B73: Success rate | F73: {=Elliot!N22:N23} -> 1 | G73: {=Elliot!O22:O23} -> #DIV/0! | H73: {=Elliot!P22:P23} -> 1 | K73: {=Elliot!Q22:Q23} -> #DIV/0!
B74: Avg sale | F74: 1461 | G74: #DIV/0! | H74: 1942 | K74: #DIV/0!
B75: TOTAL | C75: =C54+C57+C60+C63+C66+C69+C72 -> 65115.4 | D75: =D54+D57+D60+D63+D66+D69+D72 -> 29065 | E75: =E54+E57+E60+E63+E66+E69+E72 -> 80496.92 | F75: =F54+F57+F60+F63+F66+F69+F72 -> 33218.5 | G75: =G54+G57+G60+G63+G66+G69+G72 -> 40492.6 | H75: =H54+H57+H60+H63+H66+H69+H72 -> 248388.42 | I75: =I54+I57+I60+I63+I66+I69+I72 -> 175000 | J75: =J54+J57+J60+J63+J66+J69+J72 -> 73388.42 | ... O75: =O54+O57+O60+O63+O66+O69+O72 -> 0 | P75: ='Ben - No OT'!P311+Heath!P108+'Jack M'!P256+'Jarrod - No OT'!P126+Liam!P278+'Mathew B'!P361+'Matthew H - No OT'!P58+Elliot!P19 -> 248388.42 | Q75: ='Ben - No OT'!Q311+'Jack M'!Q256+'Jarrod - No OT'!Q126+Liam!Q278+'Mathew B'!Q361+'Matthew H - No OT'!Q58+Elliot!Q19 -> 0 | R75: ='Ben - No OT'!R311+'Jack M'!R256+'Jarrod - No OT'!R126+Liam!R278+'Mathew B'!R361+'Matthew H - No OT'!R58+Elliot!R19 -> 80497.1
B76: *Pending Materials Costs & Merchant Fees | H76: =H75+K75 -> 248388.42 | I76: =I75+J75 -> 248388.42 | M76: =L75-N75 -> 101409.1 | P76: =P75+Q75 -> 248388.42
B80: WEEKLY TOTALS - 13th July 2025 | C80: 45865 | I80: WEEKLY | N80: COMMISSION | O80: WEEKEND
C81: MONDAY | D81: TUESDAY | E81: WEDNESDAY | F81: THURSDAY | G81: FRIDAY | H81: ACTUAL TOTAL | I81: TARGETS[S] | J81: RUNNING BAL | K81: WEEKEND | L81: COMMISSION | M81: AWAITING PAYMENT | N81: COMPLETED & PAID | O81: AWAITING PAYMENT
B82: Ben | D82: ='Ben - No OT'!L398 -> 563 | E82: ='Ben - No OT'!M398 -> 616 | F82: ='Ben - No OT'!N398 -> 3938 | G82: ='Ben - No OT'!O398 -> 3517.9 | H82: ='Ben - No OT'!P398 -> 8634.9 | I82: 50000 | J82: =-I82+H82 -> -41365.1 | K82: ='Ben - No OT'!Q398 -> 0 | L82: =H82 -> 8634.9 | M82: ='Ben - No OT'!R398 -> 0 | N82: =L82-M82 -> 8634.9 | O82: ='Ben - No OT'!S398 -> 0 | P82: ='Ben - No OT'!F416 -> 8634.9 | Q82: =H82-P82 -> 0
B83: Success rate | D83: {='Ben - No OT'!L401:L402} -> 0.25 | E83: {='Ben - No OT'!M401:M402} -> 0.16666667 | F83: {='Ben - No OT'!N401:N402} -> 0.6 | G83: {='Ben - No OT'!O401:O402} -> 0.6 | H83: {='Ben - No OT'!P401:P402} -> 0.4 | K83: {='Ben - No OT'!Q401:Q402} -> #DIV/0!
B84: Avg sale | D84: 563 | E84: 616 | F84: 1312.6667 | G84: 1172.6333 | H84: 1079.3625 | K84: #DIV/0!
B85: Heath | C85: =Heath!K192 -> 14058.1 | E85: =Heath!M192 -> 1719 | F85: =Heath!N192 -> 15858.5 | G85: =Heath!O192 -> 11383 | H85: =Heath!P192 -> 43018.6 | I85: 50000 | J85: =-I85+H85 -> -6981.4 | K85: =Heath!Q192 -> 0 | L85: =H85 -> 43018.6 | M85: =Heath!R192 -> 26570.5 | N85: =L85-M85 -> 16448.1 | O85: =Heath!S192 -> 0 | P85: =Heath!F213+Heath!F229 -> 43018.6 | Q85: =H85-P85 -> 0
B86: Success rate | C86: {=Heath!K195:K196} -> 0.55555556 | E86: {=Heath!M195:M196} -> 0.33333333 | F86: {=Heath!N195:N196} -> 0.71428571 | G86: {=Heath!O195:O196} -> 0.57142857 | H86: {=Heath!P195:P196} -> 0.51612903 | K86: {=Heath!Q195:Q196} -> #DIV/0!
B87: Avg sale | C87: 2811.62 | E87: 859.5 | F87: 3171.7 | G87: 2845.75 | H87: 2688.6625 | K87: #DIV/0!
B88: Jarrod | C88: ='Jarrod - No OT'!K219 -> 3083 | D88: ='Jarrod - No OT'!L219 -> 19235 | E88: ='Jarrod - No OT'!M219 -> 681 | F88: ='Jarrod - No OT'!N219 -> 1661 | G88: ='Jarrod - No OT'!O219 -> 13099.6 | H88: ='Jarrod - No OT'!P219 -> 37759.6 | I88: 25000 | J88: =-I88+H88 -> 12759.6 | K88: ='Jarrod - No OT'!Q219 -> 0 | L88: =H88 -> 37759.6 | M88: ='Jarrod - No OT'!R219 -> 22927.6 | N88: =L88-M88 -> 14832 | O88: ='Jarrod - No OT'!S219 -> 0 | P88: ='Jarrod - No OT'!F239+'Jarrod - No OT'!F244+'Jarrod - No OT'!F249 -> 37759.6 | Q88: =H88-P88 -> 0
B89: Success rate | C89: {='Jarrod - No OT'!K222:K223} -> 0.33333333 | D89: {='Jarrod - No OT'!L222:L223} -> 0.5 | E89: {='Jarrod - No OT'!M222:M223} -> 0.125 | F89: {='Jarrod - No OT'!N222:N223} -> 0.14285714 | G89: {='Jarrod - No OT'!O222:O223} -> 0.57142857 | H89: {='Jarrod - No OT'!P222:P223} -> 0.32432432 | K89: {='Jarrod - No OT'!Q222:Q223} -> #DIV/0!
B90: Avg sale | C90: 1027.6667 | D90: 6411.6667 | E90: 681 | F90: 1661 | G90: 3274.9 | H90: 3146.6333 | K90: #DIV/0!
B91: Liam | C91: =Liam!K364 -> 11283.95 | D91: =Liam!L364 -> 2276 | E91: =Liam!M364 -> 21651.2 | F91: =Liam!N364 -> 2542 | G91: =Liam!O364 -> 6364 | H91: =Liam!P364 -> 44117.15 | I91: 25000 | J91: =-I91+H91 -> 19117.15 | K91: =Liam!Q364 -> 0 | L91: =H91 -> 44117.15 | M91: =Liam!R364 -> 27041 | N91: =L91-M91 -> 17076.15 | O91: =Liam!S364 -> 0 | P91: =Liam!F388+Liam!F401+Liam!F407 -> 44117.15 | Q91: =H91-P91 -> 0
B92: Success rate | C92: {=Liam!K367:K368} -> 0.75 | D92: {=Liam!L367:L368} -> 0.5 | E92: {=Liam!M367:M368} -> 0.75 | F92: {=Liam!N367:N368} -> 0.4 | G92: {=Liam!O367:O368} -> 0.5 | H92: {=Liam!P367:P368} -> 0.61290323 | K92: {=Liam!Q367:Q368} -> #DIV/0!
B93: Avg sale | C93: 1880.6583 | D93: 1138 | E93: 3608.5333 | F93: 1271 | G93: 2121.3333 | H93: 2321.9553 | K93: #DIV/0!
B94: Mathew B | C94: ='Mathew B'!K460 -> 12442 | D94: ='Mathew B'!L460 -> 2510 | E94: ='Mathew B'!M460 -> 25373 | F94: ='Mathew B'!N460 -> 27608 | G94: ='Mathew B'!O460 -> 97272 | H94: ='Mathew B'!P460 -> 165205 | I94: 25000 | J94: =-I94+H94 -> 140205 | K94: ='Mathew B'!Q460 -> 0 | L94: =H94 -> 165205 | M94: ='Mathew B'!R460 -> 0 | N94: =L94-M94 -> 165205 | O94: ='Mathew B'!S460 -> 0 | P94: ='Mathew B'!F489+'Mathew B'!F501+'Mathew B'!F509 -> 165205 | Q94: =H94-P94 -> 0
B95: Success rate | C95: {='Mathew B'!K463:K464} -> 0.5 | D95: {='Mathew B'!L463:L464} -> 0.5 | E95: {='Mathew B'!M463:M464} -> 0.8 | F95: {='Mathew B'!N463:N464} -> 0.85714286 | G95: {='Mathew B'!O463:O464} -> 0.71428571 | H95: {='Mathew B'!P463:P464} -> 0.68421053 | K95: {='Mathew B'!Q463:Q464} -> #DIV/0!
B96: Avg sale | C96: 2488.4 | D96: 1255 | E96: 3171.625 | F96: 4601.3333 | G96: 19454.4 | H96: 6354.0385 | K96: #DIV/0!
B97: Shaun | D97: ='Shaun - No OT'!L253 -> 7695 | E97: ='Shaun - No OT'!M253 -> 6384 | F97: ='Shaun - No OT'!N253 -> 5644 | G97: ='Shaun - No OT'!O253 -> 14899 | H97: ='Shaun - No OT'!P253 -> 34622 | I97: 25000 | J97: =-I97+H97 -> 9622 | K97: ='Shaun - No OT'!Q253 -> 0 | L97: =H97 -> 34622 | M97: ='Shaun - No OT'!R253 -> 16479 | N97: =L97-M97 -> 18143 | O97: ='Shaun - No OT'!S253 -> 0 | P97: ='Shaun - No OT'!F273+'Shaun - No OT'!F283 -> 34622 | Q97: =H97-P97 -> 0
B98: Success rate | D98: {='Shaun - No OT'!L256:L257} -> 0.33333333 | E98: {='Shaun - No OT'!M256:M257} -> 0.5 | F98: {='Shaun - No OT'!N256:N257} -> 0.625 | G98: {='Shaun - No OT'!O256:O257} -> 0.5 | H98: {='Shaun - No OT'!P256:P257} -> 0.5 | K98: {='Shaun - No OT'!Q256:Q257} -> #DIV/0!
B99: Avg sale | D99: 3847.5 | E99: 2128 | F99: 1128.8 | G99: 7449.5 | H99: 2885.1667 | K99: #DIV/0!
B100: Elliot | C100: =Elliot!K52 -> 814 | H100: =Elliot!P52 -> 814 | J100: =-I100+H100 -> 814 | K100: =Elliot!Q52 -> 3679 | L100: =H100 -> 814 | M100: =Elliot!R52 -> 0 | N100: =L100-M100 -> 814 | O100: =Elliot!S52 -> 0 | P100: =Elliot!F63 -> 814 | Q100: =H100-P100 -> 0
B101: Success rate | C101: {=Elliot!K55:K56} -> 1 | H101: {=Elliot!P55:P56} -> 1 | K101: {=Elliot!Q55:Q56} -> 0.36363636
B102: Avg sale | C102: 814 | H102: 814 | K102: 919.75
B103: TOTAL | C103: =C82+C85+C88+C91+C94+C97+C100 -> 41681.05 | D103: =D82+D85+D88+D91+D94+D97+D100 -> 32279 | E103: =E82+E85+E88+E91+E94+E97+E100 -> 56424.2 | F103: =F82+F85+F88+F91+F94+F97+F100 -> 57251.5 | G103: =G82+G85+G88+G91+G94+G97+G100 -> 146535.5 | H103: =H82+H85+H88+H91+H94+H97+H100 -> 334171.25 | I103: =I82+I85+I88+I91+I94+I97+I100 -> 200000 | J103: =J82+J85+J88+J91+J94+J97+J100 -> 134171.25 | ... O103: =O82+O85+O88+O91+O94+O97+O100 -> 0 | P103: ='Ben - No OT'!P398+Elliot!P52+Heath!P192+'Jarrod - No OT'!P219+Liam!P364+'Mathew B'!P460+'Shaun - No OT'!P253 -> 334171.25 | Q103: ='Ben - No OT'!Q398+Elliot!Q52+Heath!Q192+'Jarrod - No OT'!Q219+Liam!Q364+'Mathew B'!Q460+'Shaun - No OT'!Q253 -> 3679 | R103: ='Ben - No OT'!R398+Elliot!R52+Heath!R192+'Jarrod - No OT'!R219+Liam!R364+'Mathew B'!R460+'Shaun - No OT'!R253 -> 93018.1
B104: *Pending Materials Costs & Merchant Fees | H104: =H103+K103 -> 337850.25 | I104: =I103+J103 -> 334171.25 | M104: =L103-N103 -> 93018.1 | P104: =P103+Q103 -> 337850.25
B108: WEEKLY TOTALS - 13th July 2025 | C108: 45872 | I108: WEEKLY | N108: COMMISSION | O108: WEEKEND
C109: MONDAY | D109: TUESDAY | E109: WEDNESDAY | F109: THURSDAY | G109: FRIDAY | H109: ACTUAL TOTAL | I109: TARGETS[S] | J109: RUNNING BAL | K109: WEEKEND | L109: COMMISSION | M109: AWAITING PAYMENT | N109: COMPLETED & PAID | O109: AWAITING PAYMENT
B110: Ben | D110: ='Ben - No OT'!L473 -> 15913.2 | E110: ='Ben - No OT'!M473 -> 1396 | F110: ='Ben - No OT'!N473 -> 2759 | H110: ='Ben - No OT'!P473 -> 20068.2 | I110: 50000 | J110: =-I110+H110 -> -29931.8 | L110: =H110 -> 20068.2 | M110: ='Ben - No OT'!R473 -> 6133 | N110: =L110-M110 -> 13935.2 | O110: ='Ben - No OT'!S473 -> 0 | P110: ='Ben - No OT'!F491+'Ben - No OT'!F501 -> 20068.2 | Q110: =H110-P110 -> 0
B111: Success rate | D111: {='Ben - No OT'!L476:L477} -> 0.83333333 | E111: {='Ben - No OT'!M476:M477} -> 0.2 | F111: {='Ben - No OT'!N476:N477} -> 0.42857143 | H111: {='Ben - No OT'!P476:P477} -> 0.5
B112: Avg sale | D112: 3182.64 | E112: 1396 | F112: 919.66667 | H112: 2229.8
...

Sheet Weekly Summary
H1: VIC Total | I1: No of Weeks | J1: Average
H2: =I28+I52+I79+I106+I140+I168+I199+I227+I258+I285+I313+I341+I373+I407+I443+I474+I499 -> 3906652.1 | I2: =17 -> 17 | J2: =H2/I2 -> 229803.07
C7: WEEKLY TOTALS | D7: 6th Jul 2025 | J7: WEEKLY | O7: COMMISSION | P7: WEEKEND
A8: No. of 5 Star Reviews | B8: M8 Notes | D8: MONDAY | E8: TUESDAY | F8: WEDNESDAY | G8: THURSDAY | H8: FRIDAY | I8: ACTUAL TOTAL | J8: TARGETS[S] | K8: RUNNING BAL | L8: WEEKEND | M8: COMMISSION | N8: AWAITING PAYMENT | O8: COMPLETED & PAID | P8: AWAITING PAYMENT
A9: ='Ben - No OT'!T87 -> 0 | B9: ='Ben - No OT'!T88 -> 0 | C9: Ben | D9: ='Ben - No OT'!K93 -> 7859.14 | E9: ='Ben - No OT'!L93 -> 4000.6 | F9: ='Ben - No OT'!M93 -> 14266.04 | G9: ='Ben - No OT'!N93 -> 898.3 | H9: ='Ben - No OT'!O93 -> 2369.65 | I9: ='Ben - No OT'!P93 -> 29393.73 | J9: 50000 | K9: =-J9+I9 -> -20606.27 | L9: ='Ben - No OT'!Q93 -> 2903.17 | M9: =I9 -> 29393.73 | N9: ='Ben - No OT'!R93 -> 16875.34 | O9: =M9-N9 -> 12518.39 | P9: ='Ben - No OT'!S93 -> 0
C10: Success rate | D10: {='Ben - No OT'!K96:K97} -> 0.71428571 | E10: {='Ben - No OT'!L96:L97} -> 0.5 | F10: {='Ben - No OT'!M96:M97} -> 0.6 | G10: {='Ben - No OT'!N96:N97} -> 0.33333333 | H10: {='Ben - No OT'!O96:O97} -> 0.5 | I10: {='Ben - No OT'!P96:P97} -> 0.55555556 | L10: {='Ben - No OT'!Q96:Q97} -> 0.6
C11: Avg sale | D11: 1571.828 | E11: 1333.5333 | F11: 4755.3467 | G11: 898.3 | H11: 789.88333 | I11: 1959.582 | L11: 967.72333
A12: ='Jack M'!T99 -> 0 | B12: ='Jack M'!T100 -> 0 | C12: Jack M | D12: ='Jack M'!K105 -> 4069.55 | F12: ='Jack M'!M105 -> 15872.99 | G12: ='Jack M'!N105 -> 0 | H12: ='Jack M'!O105 -> 21295.65 | I12: ='Jack M'!P105 -> 41238.19 | J12: 50000 | K12: =-J12+I12 -> -8761.81 | M12: =I12 -> 41238.19 | N12: ='Jack M'!R105 -> 31148.29 | O12: =M12-N12 -> 10089.9 | P12: ='Jack M'!S105 -> 0
C13: Success rate | D13: {='Jack M'!K108:K109} -> 0.5 | F13: {='Jack M'!M108:M109} -> 0.42857143 | G13: {='Jack M'!N108:N109} -> 0 | H13: {='Jack M'!O108:O109} -> 0.85714286 | I13: {='Jack M'!P108:P109} -> 0.46153846
C14: Avg sale | D14: 1356.5167 | F14: 5290.9967 | G14: #DIV/0! | H14: 3549.275 | I14: 3436.5158
A15: =Liam!T89 -> 0 | B15: =Liam!T90 -> 1 | C15: Liam | D15: =Liam!K95 -> 3754.66 | E15: =Liam!L95 -> 5126.75 | F15: =Liam!M95 -> 20237.1 | G15: =Liam!N95 -> 985.3 | H15: =Liam!O95 -> 6198.3 | I15: =Liam!P95 -> 36302.11 | J15: 50000 | K15: =-J15+I15 -> -13697.89 | M15: =I15 -> 36302.11 | N15: =Liam!R95 -> 16113.5 | O15: =M15-N15 -> 20188.61 | P15: =Liam!S95 -> 0
C16: Success rate | D16: {=Liam!K98:K99} -> 0.33333333 | E16: {=Liam!L98:L99} -> 0.33333333 | F16: {=Liam!M98:M99} -> 0.75 | G16: {=Liam!N98:N99} -> 0.25 | H16: {=Liam!O98:O99} -> 0.27272727 | I16: {=Liam!P98:P99} -> 0.4
C17: Avg sale | D17: 1877.33 | E17: 2563.375 | F17: 3372.85 | G17: 985.3 | H17: 2066.1 | I17: 2593.0079
A18: ='Mathew B'!T121 -> 0 | B18: ='Mathew B'!T122 -> 0 | C18: Mathew B | D18: ='Mathew B'!K127 -> 9501.91 | E18: ='Mathew B'!L127 -> 5627.31 | F18: ='Mathew B'!M127 -> 4350.21 | G18: ='Mathew B'!N127 -> 6232 | H18: ='Mathew B'!O127 -> 19495.03 | I18: ='Mathew B'!P127 -> 45206.46 | J18: 50000 | K18: =-J18+I18 -> -4793.54 | M18: =I18 -> 45206.46 | N18: ='Mathew B'!R127 -> 15883.65 | O18: =M18-N18 -> 29322.81 | P18: ='Mathew B'!S127 -> 0
C19: Success rate | D19: {='Mathew B'!K130:K131} -> 0.57142857 | E19: {='Mathew B'!L130:L131} -> 0.38461538 | F19: {='Mathew B'!M130:M131} -> 0.42857143 | G19: {='Mathew B'!N130:N131} -> 0.625 | H19: {='Mathew B'!O130:O131} -> 0.6 | I19: {='Mathew B'!P130:P131} -> 0.51111111
C20: Avg sale | D20: 2375.4775 | E20: 1125.462 | F20: 1450.07 | G20: 1246.4 | H20: 3249.1717 | I20: 1965.4983
A21: ='Shaun - No OT'!T83 -> 0 | B21: ='Shaun - No OT'!T84 -> 0 | C21: Shaun | D21: ='Shaun - No OT'!K89 -> 11178.03 | E21: ='Shaun - No OT'!L89 -> 4307.26 | F21: ='Shaun - No OT'!M89 -> 4665.9 | G21: ='Shaun - No OT'!N89 -> 14856.52 | H21: ='Shaun - No OT'!O89 -> 4965.57 | I21: ='Shaun - No OT'!P89 -> 39973.28 | J21: 50000 | K21: =-J21+I21 -> -10026.72 | M21: =I21 -> 39973.28 | N21: ='Shaun - No OT'!R89 -> 11576.92 | O21: =M21-N21 -> 28396.36 | P21: ='Shaun - No OT'!S89 -> 0
C22: Success rate | D22: {='Shaun - No OT'!K92:K93} -> 0.57142857 | E22: {='Shaun - No OT'!L92:L93} -> 0.22222222 | F22: {='Shaun - No OT'!M92:M93} -> 0.625 | G22: {='Shaun - No OT'!N92:N93} -> 0.5 | H22: {='Shaun - No OT'!O92:O93} -> 0.42857143 | I22: {='Shaun - No OT'!P92:P93} -> 0.46153846
C23: Avg sale | D23: 2794.5075 | E23: 2153.63 | F23: 933.18 | G23: 3714.13 | H23: 1655.19 | I23: 2220.7378
A24: =+'Rhys C'!T5 -> 0 | B24: =+'Rhys C'!T6 -> 0 | C24: Rhys C | F24: =+'Rhys C'!M11 -> 2202.59 | I24: =+'Rhys C'!P11 -> 2202.59 | J24: 50000 | K24: =-J24+I24 -> -47797.41 | M24: =I24 -> 2202.59 | N24: =+'Rhys C'!R11 -> 0 | O24: =M24-N24 -> 2202.59 | P24: =+'Rhys C'!S11 -> 0
C25: Success rate | F25: =+'Rhys C'!M14 -> 1 | I25: =+'Rhys C'!P14 -> 1
C26: Avg sale | F26: =+'Rhys C'!M15 -> 2202.59 | I26: =+'Rhys C'!P15 -> 2202.59
A27: =SUM(A12:A26) -> 0 | B27: =SUM(B12:B26) -> 1 | C27: TOTAL | D27: =D12+D18++D9+D21+D15+D24 -> 36363.29 | E27: =E12+E18++E9+E21+E15+E24 -> 19061.92 | F27: =F12+F18++F9+F21+F15+F24 -> 61594.83 | G27: =G12+G18++G9+G21+G15+G24 -> 22972.12 | H27: =H12+H18++H9+H21+H15+H24 -> 54324.2 | I27: =I12+I18++I9+I21+I15+I24 -> 194316.36 | J27: =J12+J18++J9+J21+J15+J24 -> 300000 | K27: =K12+K18++K9+K21+K15+K24 -> -105683.64 | ... P27: =P12+P18++P9+P21+P15+P24 -> 0
I28: =I27+L27 -> 197219.53 | J28: =J27+K27 -> 194316.36 | N28: =M27-O27 -> 91597.7 | R28: ='Ben - No OT'!P93+'Jack M'!P105+Liam!P95+'Mathew B'!P127+'Shaun - No OT'!P89+'Rhys C'!P11 -> 194316.36 | S28: ='Ben - No OT'!Q93+'Jack M'!Q105+Liam!Q95+'Mathew B'!Q127+'Shaun - No OT'!Q89 -> 2903.17 | T28: ='Ben - No OT'!R93+'Jack M'!R105+Liam!R95+'Mathew B'!R127+'Shaun - No OT'!R89 -> 91597.7
R29: =R28+S28 -> 197219.53
C31: WEEKLY TOTALS | D31: 13th Jul 2025 | J31: WEEKLY | O31: COMMISSION | P31: WEEKEND
A32: No. of 5 Star Reviews | B32: M8 Notes | D32: MONDAY | E32: TUESDAY | F32: WEDNESDAY | G32: THURSDAY | H32: FRIDAY | I32: ACTUAL TOTAL | J32: TARGETS[S] | K32: RUNNING BAL | L32: WEEKEND | M32: COMMISSION | N32: AWAITING PAYMENT | O32: COMPLETED & PAID | P32: AWAITING PAYMENT
A33: ='Ben - No OT'!T189 -> 0 | B33: ='Ben - No OT'!T190 -> 0 | C33: Ben | D33: ='Ben - No OT'!K195 -> 2719.58 | E33: ='Ben - No OT'!L195 -> 474.48 | F33: ='Ben - No OT'!M195 -> 7489.47 | G33: ='Ben - No OT'!N195 -> 2319.6 | H33: ='Ben - No OT'!O195 -> 13838.92 | I33: ='Ben - No OT'!P195 -> 26842.05 | J33: 50000 | K33: =-J33+I33 -> -23157.95 | L33: ='Ben - No OT'!Q195 -> 3666.9 | M33: =I33 -> 26842.05 | N33: ='Ben - No OT'!R195 -> 8057.79 | O33: =M33-N33 -> 18784.26 | P33: ='Ben - No OT'!S195 -> 0
C34: Success rate | D34: {='Ben - No OT'!K198:K199} -> 0.75 | E34: {='Ben - No OT'!L198:L199} -> 0.25 | F34: {='Ben - No OT'!M198:M199} -> 0.36363636 | G34: {='Ben - No OT'!N198:N199} -> 0.28571429 | H34: {='Ben - No OT'!O198:O199} -> 0.55555556 | I34: {='Ben - No OT'!P198:P199} -> 0.42857143 | L34: {='Ben - No OT'!Q198:Q199} -> 0.6
C35: Avg sale | D35: 906.52667 | E35: 474.48 | F35: 1872.3675 | G35: 1159.8 | H35: 2767.784 | I35: 1789.47 | L35: 1222.3
A36: ='Jack M'!T178 -> 0 | B36: ='Jack M'!T179 -> 0 | C36: Jack M | D36: ='Jack M'!K184 -> 3632.3 | E36: ='Jack M'!L184 -> 1098.3 | I36: ='Jack M'!P184 -> 4730.6 | J36: 50000 | K36: =-J36+I36 -> -45269.4 | M36: =I36 -> 4730.6 | N36: ='Jack M'!R184 -> 0 | O36: =M36-N36 -> 4730.6 | P36: ='Jack M'!S184 -> 0
C37: Success rate | D37: {='Jack M'!K187:K188} -> 0.375 | E37: {='Jack M'!L187:L188} -> 0.14285714 | I37: {='Jack M'!P187:P188} -> 0.26666667
C38: Avg sale | D38: 1210.7667 | E38: 1098.3 | I38: 1182.65
A39: =Liam!T174 -> 0 | B39: =Liam!T175 -> 0 | C39: Liam | D39: =Liam!K180 -> 4032.9 | F39: =Liam!M180 -> 5662.66 | G39: =Liam!N180 -> 7286.51 | H39: =Liam!O180 -> 3809.61 | I39: =Liam!P180 -> 20791.68 | J39: 50000 | K39: =-J39+I39 -> -29208.32 | M39: =I39 -> 20791.68 | N39: =Liam!R180 -> 7755.26 | O39: =M39-N39 -> 13036.42 | P39: =Liam!S180 -> 0
C40: Success rate | D40: {=Liam!K183:K184} -> 1 | F40: {=Liam!M183:M184} -> 0.6 | G40: {=Liam!N183:N184} -> 0.45454545 | H40: {=Liam!O183:O184} -> 0.33333333 | I40: {=Liam!P183:P184} -> 0.44117647
C41: Avg sale | D41: 1008.225 | F41: 1887.5533 | G41: 1457.302 | H41: 1269.87 | I41: 1386.112
A42: ='Mathew B'!T230 -> 1 | B42: ='Mathew B'!T231 -> 0 | C42: Mathew B | D42: ='Mathew B'!K236 -> 1588.3 | E42: ='Mathew B'!L236 -> 1656.2 | F42: ='Mathew B'!M236 -> 9922.5 | G42: ='Mathew B'!N236 -> 9507.85 | H42: ='Mathew B'!O236 -> 11337.74 | I42: ='Mathew B'!P236 -> 34012.59 | J42: 50000 | K42: =-J42+I42 -> -15987.41 | M42: =I42 -> 34012.59 | N42: ='Mathew B'!R236 -> 14469.71 | O42: =M42-N42 -> 19542.88 | P42: ='Mathew B'!S236 -> 0
C43: Success rate | D43: {='Mathew B'!K239:K240} -> 0.1 | E43: {='Mathew B'!L239:L240} -> 0.4 | F43: {='Mathew B'!M239:M240} -> 0.5 | G43: {='Mathew B'!N239:N240} -> 0.5 | H43: {='Mathew B'!O239:O240} -> 0.54545455 | I43: {='Mathew B'!P239:P240} -> 0.41666667
C44: Avg sale | D44: 1588.3 | E44: 828.1 | F44: 1653.75 | G44: 1901.57 | H44: 1889.6233 | I44: 1700.6295
A45: ='Shaun - No OT'!T177 -> 0 | B45: ='Shaun - No OT'!T178 -> 0 | C45: Shaun | D45: ='Shaun - No OT'!K183 -> 7299.83 | E45: ='Shaun - No OT'!L183 -> 7415.25 | I45: ='Shaun - No OT'!P183 -> 14715.08 | J45: 50000 | K45: =-J45+I45 -> -35284.92 | M45: =I45 -> 14715.08 | N45: ='Shaun - No OT'!R183 -> 0 | O45: =M45-N45 -> 14715.08 | P45: ='Shaun - No OT'!S183 -> 0
C46: Success rate | D46: {='Shaun - No OT'!K186:K187} -> 0.5 | E46: {='Shaun - No OT'!L186:L187} -> 0.75 | I46: {='Shaun - No OT'!P186:P187} -> 0.6
C47: Avg sale | D47: 2433.2767 | E47: 2471.75 | I47: 2452.5133
A48: ='Jarrod - No OT'!T44 -> 0 | B48: ='Jarrod - No OT'!T45 -> 0 | C48: Jarrod | F48: ='Jarrod - No OT'!M50 -> 11118.99 | G48: ='Jarrod - No OT'!N50 -> 15994.33 | H48: ='Jarrod - No OT'!O50 -> 22825.2 | I48: ='Jarrod - No OT'!P50 -> 49938.52 | J48: 50000 | K48: =-J48+I48 -> -61.48 | M48: =I48 -> 49938.52 | N48: ='Jarrod - No OT'!R50 -> 48840.22 | O48: =M48-N48 -> 1098.3 | P48: ='Jarrod - No OT'!S50 -> 0
C49: Success rate | F49: {='Jarrod - No OT'!M53:M54} -> 0.28571429 | G49: {='Jarrod - No OT'!N53:N54} -> 0.375 | H49: {='Jarrod - No OT'!O53:O54} -> 0.57142857 | I49: {='Jarrod - No OT'!P53:P54} -> 0.40909091
C50: Avg sale | F50: 5559.495 | G50: 5331.4433 | H50: 5706.3 | I50: 5548.7244
A51: =SUM(A33:A47) -> 0 | B51: =SUM(B33:B47) -> 0 | C51: TOTAL | D51: =D33+D36+D39+D42+D45+D48 -> 19272.91 | E51: =E33+E36+E39+E42+E45+E48 -> 10644.23 | F51: =F33+F36+F39+F42+F45+F48 -> 34193.62 | G51: =G33+G36+G39+G42+G45+G48 -> 35108.29 | H51: =H33+H36+H39+H42+H45+H48 -> 51811.47 | I51: =I33+I36+I39+I42+I45+I48 -> 151030.52 | J51: =J33+J36+J39+J42+J45+J48 -> 300000 | K51: =K33+K36+K39+K42+K45+K48 -> -148969.48 | ... P51: =P33+P36+P39+P42+P45+P48 -> 0
I52: =I51+L51 -> 154697.42 | J52: =J51+K51 -> 151030.52 | N52: =M51-O51 -> 79122.98 | R52: ='Ben - No OT'!P195+'Jack M'!P184+Liam!P180+'Mathew B'!P236+'Shaun - No OT'!P183+'Jarrod - No OT'!P50+'Matthew H - No OT'!P12 -> 151030.52 | S52: ='Ben - No OT'!Q195+'Jack M'!Q184+Liam!Q180+'Mathew B'!Q236+'Shaun - No OT'!Q183+'Jarrod - No OT'!Q50+'Matthew H - No OT'!Q12 -> 3666.9 | T52: ='Ben - No OT'!R195+'Jack M'!R184+Liam!R180+'Mathew B'!R236+'Shaun - No OT'!R183+'Jarrod - No OT'!R50+'Matthew H - No OT'!R12 -> 79122.98
R53: =R52+S52 -> 154697.42
C55: WEEKLY TOTALS | D55: 20th Jul 2025 | J55: WEEKLY | O55: COMMISSION | P55: WEEKEND
A56: No. of 5 Star Reviews | B56: M8 Notes | D56: MONDAY | E56: TUESDAY | F56: WEDNESDAY | G56: THURSDAY | H56: FRIDAY | I56: ACTUAL TOTAL | J56: TARGETS[S] | K56: RUNNING BAL | L56: WEEKEND | M56: COMMISSION | N56: AWAITING PAYMENT | O56: COMPLETED & PAID | P56: AWAITING PAYMENT
A57: ='Ben - No OT'!T297 -> 0 | B57: ='Ben - No OT'!T298 -> 0 | C57: Ben | D57: ='Ben - No OT'!K303 -> 9210.56 | E57: ='Ben - No OT'!L303 -> 2955.6 | F57: ='Ben - No OT'!M303 -> 23749.02 | G57: ='Ben - No OT'!N303 -> 1094.3 | H57: ='Ben - No OT'!O303 -> 1162 | I57: ='Ben - No OT'!P303 -> 38171.48 | J57: 50000 | K57: =-J57+I57 -> -11828.52 | M57: =I57 -> 38171.48 | N57: ='Ben - No OT'!R303 -> 19047.21 | O57: =M57-N57 -> 19124.27 | P57: ='Ben - No OT'!S303 -> 0
C58: Success rate | D58: {='Ben - No OT'!K306:K307} -> 0.8 | E58: {='Ben - No OT'!L306:L307} -> 0.5 | F58: {='Ben - No OT'!M306:M307} -> 0.55555556 | G58: {='Ben - No OT'!N306:N307} -> 0.16666667 | H58: {='Ben - No OT'!O306:O307} -> 0.66666667 | I58: {='Ben - No OT'!P306:P307} -> 0.51724138
C59: Avg sale | D59: 2302.64 | E59: 985.2 | F59: 4749.804 | G59: 1094.3 | H59: 581 | I59: 2544.7653
A60: =Heath!T94 -> 4 | B60: =Heath!T95 -> 0 | C60: Heath | E60: =Heath!L100 -> 5585.35 | F60: =Heath!M100 -> 17230.15 | G60: =Heath!N100 -> 3859.56 | H60: =Heath!O100 -> 6236.01 | I60: =Heath!P100 -> 32911.07 | J60: 50000 | K60: =-J60+I60 -> -17088.93 | M60: =I60 -> 32911.07 | N60: =Heath!R100 -> 16914.87 | O60: =M60-N60 -> 15996.2 | P60: =Heath!S100 -> 0
C61: Success rate | E61: {=Heath!L103:L104} -> 0.66666667 | F61: {=Heath!M103:M104} -> 0.625 | G61: {=Heath!N103:N104} -> 0.6 | H61: {=Heath!O103:O104} -> 0.36363636 | I61: {=Heath!P103:P104} -> 0.51851852
C62: Avg sale | E62: 2792.675 | F62: 3446.03 | G62: 1286.52 | H62: 1559.0025 | I62: 2350.7907
A63: ='Jarrod - No OT'!T112 -> 0 | B63: ='Jarrod - No OT'!T113 -> 0 | C63: Jarrod | D63: ='Jarrod - No OT'!K118 -> 21224.95 | E63: ='Jarrod - No OT'!L118 -> 3861.61 | F63: ='Jarrod - No OT'!M118 -> 6842.56 | G63: ='Jarrod - No OT'!N118 -> 3224.23 | H63: ='Jarrod - No OT'!O118 -> 1422.3 | I63: ='Jarrod - No OT'!P118 -> 36575.65 | J63: 50000 | K63: =-J63+I63 -> -13424.35 | M63: =I63 -> 36575.65 | N63: ='Jarrod - No OT'!R118 -> 1582.93 | O63: =M63-N63 -> 34992.72 | P63: ='Jarrod - No OT'!S118 -> 0
C64: Success rate | D64: {='Jarrod - No OT'!K121:K122} -> 0.75 | E64: {='Jarrod - No OT'!L121:L122} -> 0.66666667 | F64: {='Jarrod - No OT'!M121:M122} -> 0.66666667 | G64: {='Jarrod - No OT'!N121:N122} -> 0.18181818 | H64: {='Jarrod - No OT'!O121:O122} -> 0.4 | I64: {='Jarrod - No OT'!P121:P122} -> 0.5
C65: Avg sale | D65: 3537.4917 | E65: 965.4025 | F65: 1710.64 | G65: 1612.115 | H65: 711.15 | I65: 2031.9806
A66: =Liam!T264 -> 0 | B66: =Liam!T265 -> 0 | C66: Liam | F66: =Liam!M270 -> 8307.98 | G66: =Liam!N270 -> 5399.39 | H66: =Liam!O270 -> 22358.1 | I66: =Liam!P270 -> 36065.47 | J66: 50000 | K66: =-J66+I66 -> -13934.53 | M66: =I66 -> 36065.47 | N66: =Liam!R270 -> 21855.6 | O66: =M66-N66 -> 14209.87 | P66: =Liam!S270 -> 0
C67: Success rate | F67: {=Liam!M273:M274} -> 0.625 | G67: {=Liam!N273:N274} -> 0.44444444 | H67: {=Liam!O273:O274} -> 0.42857143 | I67: {=Liam!P273:P274} -> 0.48387097
C68: Avg sale | F68: 1661.596 | G68: 1349.8475 | H68: 3726.35 | I68: 2404.3647
A69: ='Mathew B'!T347 -> 0 | B69: ='Mathew B'!T348 -> 0 | C69: Mathew B | D69: ='Mathew B'!K353 -> 20981.85 | E69: ='Mathew B'!L353 -> 13337.88 | F69: ='Mathew B'!M353 -> 7114.63 | G69: ='Mathew B'!N353 -> 3980.9 | H69: ='Mathew B'!O353 -> 5424.4 | I69: ='Mathew B'!P353 -> 50839.66 | J69: 50000 | K69: =-J69+I69 -> 839.66 | M69: =I69 -> 50839.66 | N69: ='Mathew B'!R353 -> 11311.78 | O69: =M69-N69 -> 39527.88 | P69: ='Mathew B'!S353 -> 0
C70: Success rate | D70: {='Mathew B'!K356:K357} -> 0.75 | E70: {='Mathew B'!L356:L357} -> 0.44444444 | F70: {='Mathew B'!M356:M357} -> 0.66666667 | G70: {='Mathew B'!N356:N357} -> 0.5 | H70: {='Mathew B'!O356:O357} -> 0.625 | I70: {='Mathew B'!P356:P357} -> 0.58974359
C71: Avg sale | D71: 3496.975 | E71: 3334.47 | F71: 1778.6575 | G71: 995.225 | H71: 1084.88 | I71: 2210.42
A72: ='Matthew H - No OT'!T44 -> 0 | B72: ='Matthew H - No OT'!T45 -> 0 | C72: Mathew H | G72: ='Matthew H - No OT'!N50 -> 9462.16 | I72: ='Matthew H - No OT'!P50 -> 9462.16 | K72: =-J72+I72 -> 9462.16 | M72: =I72 -> 9462.16 | N72: ='Matthew H - No OT'!R50 -> 9462.16 | O72: =M72-N72 -> 0 | P72: ='Matthew H - No OT'!S50 -> 0
C73: Success rate | G73: {='Matthew H - No OT'!N53:N54} -> 0.5 | I73: {='Matthew H - No OT'!P53:P54} -> 0.5
C74: Avg sale | G74: 9462.16 | I74: 9462.16
A75: =Elliot!T5-1 -> 0 | B75: =Elliot!T6 -> 0 | C75: Elliot | G75: =Elliot!N11 -> 1221.3 | I75: =Elliot!P11 -> 1221.3 | K75: =-J75+I75 -> 1221.3 | M75: =I75 -> 1221.3 | N75: =Elliot!R11 -> 0 | O75: =M75-N75 -> 1221.3 | P75: =Elliot!S11 -> 0
C76: Success rate | G76: {=Elliot!N14:N15} -> 1 | I76: {=Elliot!P14:P15} -> 1
C77: Avg sale | G77: 1221.3 | I77: 1221.3
A78: =SUM(A57:A77) -> 4 | B78: =SUM(B57:B77) -> 0 | C78: TOTAL | D78: =D57+D60+D63+D66+D69+D72+D75 -> 51417.36 | E78: =E57+E60+E63+E66+E69+E72+E75 -> 25740.44 | F78: =F57+F60+F63+F66+F69+F72+F75 -> 63244.34 | G78: =G57+G60+G63+G66+G69+G72+G75 -> 28241.84 | H78: =H57+H60+H63+H66+H69+H72+H75 -> 36602.81 | I78: =I57+I60+I63+I66+I69+I72+I75 -> 205246.79 | J78: =J57+J60+J63+J66+J69+J72+J75 -> 250000 | K78: =K57+K60+K63+K66+K69+K72+K75 -> -44753.21 | ... P78: =P57+P60+P63+P66+P69+P72+P75 -> 0
I79: =I78+L78 -> 205246.79 | J79: =J78+K78 -> 205246.79 | N79: =M78-O78 -> 80174.55 | Q79: ='Ben - No OT'!P303+Heath!P100+'Jack M'!P248+'Jarrod - No OT'!P118+Liam!P270+'Mathew B'!P353+'Matthew H - No OT'!P50+Elliot!P11 -> 205246.79 | R79: ='Ben - No OT'!Q303+Heath!Q100+'Jack M'!Q248+'Jarrod - No OT'!Q118+Liam!Q270+'Mathew B'!Q353+'Matthew H - No OT'!Q50+Elliot!Q11 -> 0 | S79: ='Ben - No OT'!R303+Heath!R100+'Jack M'!R248+'Jarrod - No OT'!R118+Liam!R270+'Mathew B'!R353+'Matthew H - No OT'!R50+Elliot!R11 -> 80174.55
Q80: =Q79+R79 -> 205246.79
C82: WEEKLY TOTALS | D82: 27th Jul 2025 | J82: WEEKLY | O82: COMMISSION | P82: WEEKEND
A83: No. of 5 Star Reviews | B83: M8 Notes | D83: MONDAY | E83: TUESDAY | F83: WEDNESDAY | G83: THURSDAY | H83: FRIDAY | I83: ACTUAL TOTAL | J83: TARGETS[S] | K83: RUNNING BAL | L83: WEEKEND | M83: COMMISSION | N83: AWAITING PAYMENT | O83: COMPLETED & PAID | P83: AWAITING PAYMENT
A84: ='Ben - No OT'!T384 -> 1 | B84: ='Ben - No OT'!T385 -> 0 | C84: Ben | E84: ='Ben - No OT'!L390 -> 563 | F84: ='Ben - No OT'!M390 -> 616 | G84: ='Ben - No OT'!N390 -> 3619.26 | H84: ='Ben - No OT'!O390 -> 3136.33 | I84: ='Ben - No OT'!P390 -> 7934.59 | J84: 50000 | K84: =-J84+I84 -> -42065.41 | M84: =I84 -> 7934.59 | N84: ='Ben - No OT'!R390 -> 0 | O84: =M84-N84 -> 7934.59 | P84: ='Ben - No OT'!S390 -> 0
C85: Success rate | E85: {='Ben - No OT'!L393:L394} -> 0.25 | F85: {='Ben - No OT'!M393:M394} -> 0.16666667 | G85: {='Ben - No OT'!N393:N394} -> 0.6 | H85: {='Ben - No OT'!O393:O394} -> 0.6 | I85: {='Ben - No OT'!P393:P394} -> 0.4
C86: Avg sale | E86: 563 | F86: 616 | G86: 1206.42 | H86: 1045.4433 | I86: 991.82375
A87: =Heath!T178-0.5 -> 4.5 | B87: =Heath!T179 -> 0 | C87: Heath | D87: =Heath!K184 -> 12330.09 | F87: =Heath!M184 -> 1679.3 | G87: =Heath!N184 -> 14491.58 | H87: =Heath!O184 -> 10638.23 | I87: =Heath!P184 -> 39139.2 | J87: 50000 | K87: =-J87+I87 -> -10860.8 | M87: =I87 -> 39139.2 | N87: =Heath!R184 -> 23634.37 | O87: =M87-N87 -> 15504.83 | P87: =Heath!S184 -> 0
C88: Success rate | D88: {=Heath!K187:K188} -> 0.55555556 | F88: {=Heath!M187:M188} -> 0.33333333 | G88: {=Heath!N187:N188} -> 0.71428571 | H88: {=Heath!O187:O188} -> 0.57142857 | I88: {=Heath!P187:P188} -> 0.51612903
C89: Avg sale | D89: 2466.018 | F89: 839.65 | G89: 2898.316 | H89: 2659.5575 | I89: 2446.2
A90: ='Jarrod - No OT'!T205 -> 0 | B90: ='Jarrod - No OT'!T206 -> 0 | C90: Jarrod | D90: ='Jarrod - No OT'!K211 -> 2953.6 | E90: ='Jarrod - No OT'!L211 -> 17343.09 | F90: ='Jarrod - No OT'!M211 -> 681 | G90: ='Jarrod - No OT'!N211 -> 1621.3 | H90: ='Jarrod - No OT'!O211 -> 11990.8 | I90: ='Jarrod - No OT'!P211 -> 34589.79 | J90: 50000 | K90: =-J90+I90 -> -15410.21 | M90: =I90 -> 34589.79 | N90: ='Jarrod - No OT'!R211 -> 20735.2 | O90: =M90-N90 -> 13854.59 | P90: ='Jarrod - No OT'!S211 -> 0
C91: Success rate | D91: {='Jarrod - No OT'!K214:K215} -> 0.33333333 | E91: {='Jarrod - No OT'!L214:L215} -> 0.5 | F91: {='Jarrod - No OT'!M214:M215} -> 0.125 | G91: {='Jarrod - No OT'!N214:N215} -> 0.14285714 | H91: {='Jarrod - No OT'!O214:O215} -> 0.57142857 | I91: {='Jarrod - No OT'!P214:P215} -> 0.32432432
C92: Avg sale | D92: 984.53333 | E92: 5781.03 | F92: 681 | G92: 1621.3 | H92: 2997.7 | I92: 2882.4825
A93: =Liam!T350 -> 0 | B93: =Liam!T351 -> 0 | C93: Liam | D93: =Liam!K356 -> 10730.99 | E93: =Liam!L356 -> 2196.6 | F93: =Liam!M356 -> 14804.33 | G93: =Liam!N356 -> 2502.3 | H93: =Liam!O356 -> 5982.79 | I93: =Liam!P356 -> 36217.01 | J93: 50000 | K93: =-J93+I93 -> -13782.99 | M93: =I93 -> 36217.01 | N93: =Liam!R356 -> 19988.11 | O93: =M93-N93 -> 16228.9 | P93: =Liam!S356 -> 0
C94: Success rate | D94: {=Liam!K359:K360} -> 0.75 | E94: {=Liam!L359:L360} -> 0.5 | F94: {=Liam!M359:M360} -> 0.75 | G94: {=Liam!N359:N360} -> 0.4 | H94: {=Liam!O359:O360} -> 0.5 | I94: {=Liam!P359:P360} -> 0.61290323
C95: Avg sale | D95: 1788.4983 | E95: 1098.3 | F95: 2467.3883 | G95: 1251.15 | H95: 1994.2633 | I95: 1906.1584
A96: ='Mathew B'!T446 -> 0 | B96: ='Mathew B'!T447 -> 0 | C96: Mathew B | D96: ='Mathew B'!K452 -> 9641.86 | E96: ='Mathew B'!L452 -> 2430.6 | F96: ='Mathew B'!M452 -> 18604.79 | G96: ='Mathew B'!N452 -> 20839.72 | H96: ='Mathew B'!O452 -> 73334.23 | I96: ='Mathew B'!P452 -> 124851.2 | J96: 50000 | K96: =-J96+I96 -> 74851.2 | M96: =I96 -> 124851.2 | N96: ='Mathew B'!R452 -> 100236.52 | O96: =M96-N96 -> 24614.68 | P96: ='Mathew B'!S452 -> 0
C97: Success rate | D97: {='Mathew B'!K455:K456} -> 0.5 | E97: {='Mathew B'!L455:L456} -> 0.5 | F97: {='Mathew B'!M455:M456} -> 0.8 | G97: {='Mathew B'!N455:N456} -> 0.85714286 | H97: {='Mathew B'!O455:O456} -> 0.71428571 | I97: {='Mathew B'!P455:P456} -> 0.68421053
C98: Avg sale | D98: 1928.372 | E98: 1215.3 | F98: 2325.5988 | G98: 3473.2867 | H98: 14666.846 | I98: 4801.9692
A99: ='Shaun - No OT'!T239 -> 1 | B99: ='Shaun - No OT'!T240 -> 0 | C99: Shaun | E99: ='Shaun - No OT'!L245 -> 4682.9 | F99: ='Shaun - No OT'!M245 -> 5377.4 | G99: ='Shaun - No OT'!N245 -> 4951.82 | H99: ='Shaun - No OT'!O245 -> 13638.25 | I99: ='Shaun - No OT'!P245 -> 28650.37 | J99: 50000 | K99: =-J99+I99 -> -21349.63 | M99: =I99 -> 28650.37 | N99: ='Shaun - No OT'!R245 -> 14491.05 | O99: =M99-N99 -> 14159.32 | P99: ='Shaun - No OT'!S245 -> 0
C100: Success rate | E100: {='Shaun - No OT'!L248:L249} -> 0.33333333 | F100: {='Shaun - No OT'!M248:M249} -> 0.5 | G100: {='Shaun - No OT'!N248:N249} -> 0.625 | H100: {='Shaun - No OT'!O248:O249} -> 0.5 | I100: {='Shaun - No OT'!P248:P249} -> 0.5
C101: Avg sale | E101: 2341.45 | F101: 1792.4667 | G101: 990.364 | H101: 6819.125 | I101: 2387.5308
A102: =Elliot!T38 -> 0 | B102: =Elliot!T39 -> 0 | C102: Elliot | D102: =Elliot!K44 -> 774.3 | I102: =Elliot!P44 -> 774.3 | J102: 50000 | K102: =-J102+I102 -> -49225.7 | L102: =Elliot!Q44 -> 3599.6 | M102: =I102 -> 774.3 | N102: =Elliot!R44 -> 0 | O102: =M102-N102 -> 774.3 | P102: =Elliot!S44 -> 0
C103: Success rate | D103: {=Elliot!K47:K48} -> 1 | I103: {=Elliot!P47:P48} -> 1 | L103: {=Elliot!Q47:Q48} -> 0.36363636
C104: Avg sale | D104: 774.3 | I104: 774.3 | L104: 899.9
A105: =SUM(A84:A104) -> 6.5 | B105: =SUM(B84:B104) -> 0 | C105: TOTAL | D105: =D84+D87+D90+D93+D96+D99+D102 -> 36430.84 | E105: =E84+E87+E90+E93+E96+E99+E102 -> 27216.19 | F105: =F84+F87+F90+F93+F96+F99+F102 -> 41762.82 | G105: =G84+G87+G90+G93+G96+G99+G102 -> 48025.98 | H105: =H84+H87+H90+H93+H96+H99+H102 -> 118720.63 | I105: =I84+I87+I90+I93+I96+I99+I102 -> 272156.46 | J105: =J84+J87+J90+J93+J96+J99+J102 -> 350000 | K105: =K84+K87+K90+K93+K96+K99+K102 -> -77843.54 | ... P105: =P84+P87+P90+P93+P96+P99+P102 -> 0
I106: =I105+L105 -> 275756.06 | J106: =J105+K105 -> 272156.46 | N106: =M105-O105 -> 179085.25 | Q106: ='Ben - No OT'!P390+Elliot!P44+Heath!P184+'Jarrod - No OT'!P211+Liam!P356+'Mathew B'!P452+'Matthew H - No OT'!P91+'Shaun - No OT'!P245 -> 272156.46 | R106: ='Ben - No OT'!Q390+Elliot!Q44+Heath!Q184+'Jarrod - No OT'!Q211+Liam!Q356+'Mathew B'!Q452+'Matthew H - No OT'!Q91+'Shaun - No OT'!Q245 -> 3599.6 | S106: ='Ben - No OT'!R390+Elliot!R44+Heath!R184+'Jarrod - No OT'!R211+Liam!R356+'Mathew B'!R452+'Matthew H - No OT'!R91+'Shaun - No OT'!R245 -> 179085.25
Q107: =Q106+R106 -> 275756.06
...

Sheet Aden
B3: WEEKLY COMMISSION | F3: WEEK ENDING | G3: 45886
K4: PHOTOS | N4: QUOTE | Q4: INVOICE
B5: BOOKED JOBS | C5: =C6+C7 -> 1 | E5: WEEKLY TARGET | K5: BEFORE | L5: AFTER | M5: RECEIPT | N5: DESCRIPTION | O5: SIGNED | P5: EMAILED | Q5: DESCRIPTION | R5: SIGNED | S5: EMAILED | T5: 5 Star Review
B6: SUCCESSFUL | C6: =P13 -> 1 | E6: Tier 1 | F6: 0.05 | J6: TAKEN | K6: =K32 -> 0 | L6: =L32 -> 0 | M6: =M32 -> 0 | N6: =N32 -> 0 | O6: =O32 -> 0 | P6: =P32 -> 0 | Q6: =Q32 -> 0 | R6: =R32 -> 0 | S6: =S32 -> 0 | T6: =T37 -> 0
B7: UNSUCCESSFUL | C7: =P14 -> 0 | J7: % | K7: =K32/K31 -> #DIV/0! | L7: =L32/L31 -> #DIV/0! | M7: =M32/M31 -> #DIV/0! | N7: =N32/N31 -> #DIV/0! | O7: =O32/O31 -> #DIV/0! | P7: =P32/P31 -> #DIV/0! | Q7: =Q32/Q31 -> #DIV/0! | R7: =R32/R31 -> #DIV/0! | S7: =S32/S31 -> #DIV/0! | U7: M8 Notes
B8: SUCESSFUL (%) | C8: =P15 -> 1
F9: ACTUAL | G9: POTENTIAL | H9: Exc. SUPER
B10: AVERAGE SALE | C10: =P16 -> 990 | E10: NET PROFIT | F10: =P12 -> 990 | G10: =I31+I36 -> 990 | K10: DAILY NET PROFIT | R10: WEEKDAY | S10: WEEKEND
E11: UNLOCKED | F11: =F6 -> 0.05 | K11: MON | L11: TUE | M11: WED | N11: THU | O11: FRI | P11: Total | Q11: SAT | R11: Awaiting Payment | S11: Awaiting Payment
E12: COMMISSION - PAY OUT | F12: =(F10-I35)*F11 -> 0 | G12: $- | H12: =F12/1.12 -> 0 | O12: =I35 -> 990 | P12: =SUM(K12:O12) -> 990 | Q12: 0 | R12: =I36 -> 990 | S12: 0
E13: EMERGENCY | F13: =Q12 -> 0 | G13: $- | J13: Successful | O13: 1 | P13: =SUM(K13:O13) -> 1
E14: EMERGENCY - PAY OUT | F14: =F13*0.25 -> 0 | G14: $- | H14: =F14/1.12 -> 0 | J14: Unsuccessful | O14: 0 | P14: =SUM(K14:O14) -> 0
E15: PREV. WEEK | G15: $- | J15: Success rate | K15: =K13/(K13+K14) -> #DIV/0! | L15: =L13/(L13+L14) -> #DIV/0! | M15: =M13/(M13+M14) -> #DIV/0! | N15: =N13/(N13+N14) -> #DIV/0! | O15: =O13/(O13+O14) -> 1 | P15: =P13/(P13+P14) -> 1 | Q15: =Q13/(Q13+Q14) -> #DIV/0!
E16: PREV. WEEK - PAY OUT | F16: =F15*0.05 -> 0 | G16: $- | H16: =F16/1.12 -> 0 | J16: Avg sale | K16: =K12/K13 -> #DIV/0! | L16: =L12/L13 -> #DIV/0! | M16: =M12/M13 -> #DIV/0! | N16: =N12/N13 -> #DIV/0! | O16: =O12/O13 -> 990 | P16: =P12/P13 -> 990 | Q16: =Q12/Q13 -> #DIV/0!
E17: 5 Star Review | H17: =F17/1.12 -> 0
E18: 5 Star Notes | F18: =T7 -> 0 | K18: Managment Summary - SALES ONLY - COLUMN F | R18: WEEKDAY | S18: WEEKEND
K19: MON | L19: TUE | M19: WED | N19: THU | O19: FRI | P19: Total | Q19: SAT | R19: Awaiting Payment | S19: Awaiting Payment
O20: =F35 -> 1675 | P20: =SUM(K20:O20) -> 1675 | Q20: 0 | R20: =+F36 -> 1675 | S20: 0
J21: Successful | K21: =K13 -> 0 | L21: =L13 -> 0 | M21: =M13 -> 0 | N21: =N13 -> 0 | O21: =O13 -> 1 | P21: =P13 -> 1 | Q21: =Q13 -> 0
J22: Unsuccessful | K22: =K14 -> 0 | L22: =L14 -> 0 | M22: =M14 -> 0 | N22: =N14 -> 0 | O22: =O14 -> 0 | P22: =P14 -> 0 | Q22: =Q14 -> 0
J23: Success rate | K23: =K21/(K21+K22) -> #DIV/0! | L23: =L21/(L21+L22) -> #DIV/0! | M23: =M21/(M21+M22) -> #DIV/0! | N23: =N21/(N21+N22) -> #DIV/0! | O23: =O21/(O21+O22) -> 1 | P23: =P21/(P21+P22) -> 1 | Q23: =Q21/(Q21+Q22) -> #DIV/0!
J24: Avg sale | K24: =K20/K21 -> #DIV/0! | L24: =L20/L21 -> #DIV/0! | M24: =M20/M21 -> #DIV/0! | N24: =N20/N21 -> #DIV/0! | O24: =O20/O21 -> 1675 | P24: =P20/P21 -> 1675 | Q24: =Q20/Q21 -> #DIV/0!
B27: JOB DETAILS | F27: JOB AMOUNT | K27: PHOTOS | N27: QUOTE | Q27: INVOICE | U27: NOTES
B28: JOB STATUS | C28: DATE | D28: JOB # | E28: SUBURB | F28: AMOUNT EXC. GST | G28: MATERIALS | H28: Merchant Fees | I28: NET PROFIT | J28: PAID | K28: BEFORE | L28: AFTER | M28: RECEIPT | N28: DESCRIPTION | O28: SIGNED | P28: EMAILED | Q28: DESCRIPTION | R28: SIGNED | S28: EMAILED | T28: 5 Star Review | V28: EFTPOS | W28: CASH | X28: Payment Plan
B29: COMPLETED & PAID JOBS
B30: 1 | I30: =F30-G30-H30 -> 0
F31: =SUM(F30:F30) -> 0 | G31: =SUM(G30:G30) -> 0 | H31: =SUM(H30:H30) -> 0 | I31: =SUM(I30:I30) -> 0 | K31: =COUNT(K30:K30) -> 0 | L31: =COUNT(L30:L30) -> 0 | M31: =COUNT(M30:M30) -> 0 | N31: =COUNT(N30:N30) -> 0 | O31: =COUNT(O30:O30) -> 0 | P31: =COUNT(P30:P30) -> 0 | Q31: =COUNT(Q30:Q30) -> 0 | R31: =COUNT(R30:R30) -> 0 | S31: =COUNT(S30:S30) -> 0
K32: =SUM(K30:K30) -> 0 | L32: =SUM(L30:L30) -> 0 | M32: =SUM(M30:M30) -> 0 | N32: =SUM(N30:N30) -> 0 | O32: =SUM(O30:O30) -> 0 | P32: =SUM(P30:P30) -> 0 | Q32: =SUM(Q30:Q30) -> 0 | R32: =SUM(R30:R30) -> 0 | S32: =SUM(S30:S30) -> 0
B34: CURRENT WORK ORDERS (AWAITING PAYMENT)
A35: 45887 | B35: 1 | C35: 45884 | D35: 72353 | E35: Dandenong North | F35: 1675 | G35: =485+200 -> 685 | I35: =F35-G35-H35 -> 990 | J35: Cash | K35: 1 | L35: 1 | M35: 1 | N35: 1 | O35: 1 | P35: 0 | Q35: 1 | R35: 1 | S35: 0 | U35: 18/8-WIP by Rhys | W35: =200+1457 -> 1657
F36: =SUM(F35:F35) -> 1675 | G36: =SUM(G35:G35) -> 685 | H36: =SUM(H35:H35) -> 0 | I36: =SUM(I35:I35) -> 990
T37: =SUM(T30:T36) -> 0 | V37: =SUM(V30:V36) -> 0 | W37: =SUM(W30:W36) -> 1657 | X37: =SUM(X30:X36) -> 0
B40: WEEKLY COMMISSION | F40: WEEK ENDING | G40: 45893
K41: PHOTOS | N41: QUOTE | Q41: INVOICE
B42: BOOKED JOBS | C42: =C43+C44 -> 0 | E42: WEEKLY TARGET | K42: BEFORE | L42: AFTER | M42: RECEIPT | N42: DESCRIPTION | O42: SIGNED | P42: EMAILED | Q42: DESCRIPTION | R42: SIGNED | S42: EMAILED | T42: 5 Star Review
B43: SUCCESSFUL | C43: =P50 -> 0 | E43: Tier 1 | F43: 0.05 | J43: TAKEN | K43: =K69 -> 0 | L43: =L69 -> 0 | M43: =M69 -> 0 | N43: =N69 -> 0 | O43: =O69 -> 0 | P43: =P69 -> 0 | Q43: =Q69 -> 0 | R43: =R69 -> 0 | S43: =S69 -> 0 | T43: =T73 -> 0
B44: UNSUCCESSFUL | C44: =P51 -> 0 | J44: % | K44: =K69/K68 -> #DIV/0! | L44: =L69/L68 -> #DIV/0! | M44: =M69/M68 -> #DIV/0! | N44: =N69/N68 -> #DIV/0! | O44: =O69/O68 -> #DIV/0! | P44: =P69/P68 -> #DIV/0! | Q44: =Q69/Q68 -> #DIV/0! | R44: =R69/R68 -> #DIV/0! | S44: =S69/S68 -> #DIV/0! | U44: M8 Notes
B45: SUCESSFUL (%) | C45: =P52 -> #DIV/0!
F46: ACTUAL | G46: POTENTIAL | H46: Exc. SUPER
B47: AVERAGE SALE | C47: =P53 -> #DIV/0! | E47: NET PROFIT | F47: =P49 -> 0 | G47: =I68 -> 0 | K47: DAILY NET PROFIT | R47: WEEKDAY | S47: WEEKEND
E48: UNLOCKED | F48: =F43 -> 0.05 | K48: MON | L48: TUE | M48: WED | N48: THU | O48: FRI | P48: Total | Q48: SAT | R48: Awaiting Payment | S48: Awaiting Payment
E49: COMMISSION - PAY OUT | F49: =F47*F48 -> 0 | G49: $- | H49: =F49/1.12 -> 0 | P49: =SUM(K49:O49) -> 0 | Q49: 0 | R49: =0 -> 0 | S49: =0 -> 0
E50: EMERGENCY | F50: =Q49 -> 0 | G50: $- | J50: Successful | P50: =SUM(K50:O50) -> 0
E51: EMERGENCY - PAY OUT | F51: =F50*0.25 -> 0 | G51: $- | H51: =F51/1.12 -> 0 | J51: Unsuccessful | P51: =SUM(K51:O51) -> 0
E52: PREV. WEEK | G52: $- | J52: Success rate | K52: =K50/(K50+K51) -> #DIV/0! | L52: =L50/(L50+L51) -> #DIV/0! | M52: =M50/(M50+M51) -> #DIV/0! | N52: =N50/(N50+N51) -> #DIV/0! | O52: =O50/(O50+O51) -> #DIV/0! | P52: =P50/(P50+P51) -> #DIV/0! | Q52: =Q50/(Q50+Q51) -> #DIV/0!
E53: PREV. WEEK - PAY OUT | F53: =F52*0.05 -> 0 | G53: $- | H53: =F53/1.12 -> 0 | J53: Avg sale | K53: =K49/K50 -> #DIV/0! | L53: =L49/L50 -> #DIV/0! | M53: =M49/M50 -> #DIV/0! | N53: =N49/N50 -> #DIV/0! | O53: =O49/O50 -> #DIV/0! | P53: =P49/P50 -> #DIV/0! | Q53: =Q49/Q50 -> #DIV/0!
E54: 5 Star Review | H54: =F54/1.12 -> 0
E55: 5 Star Notes | F55: =T44 -> 0 | K55: Managment Summary - SALES ONLY - COLUMN F | R55: WEEKDAY | S55: WEEKEND
K56: MON | L56: TUE | M56: WED | N56: THU | O56: FRI | P56: Total | Q56: SAT | R56: Awaiting Payment | S56: Awaiting Payment
P57: =SUM(K57:O57) -> 0 | Q57: 0 | R57: =0 -> 0 | S57: =0 -> 0
J58: Successful | K58: =K50 -> 0 | L58: =L50 -> 0 | M58: =M50 -> 0 | N58: =N50 -> 0 | O58: =O50 -> 0 | P58: =P50 -> 0 | Q58: =Q50 -> 0
J59: Unsuccessful | K59: =K51 -> 0 | L59: =L51 -> 0 | M59: =M51 -> 0 | N59: =N51 -> 0 | O59: =O51 -> 0 | P59: =P51 -> 0 | Q59: =Q51 -> 0
J60: Success rate | K60: =K58/(K58+K59) -> #DIV/0! | L60: =L58/(L58+L59) -> #DIV/0! | M60: =M58/(M58+M59) -> #DIV/0! | N60: =N58/(N58+N59) -> #DIV/0! | O60: =O58/(O58+O59) -> #DIV/0! | P60: =P58/(P58+P59) -> #DIV/0! | Q60: =Q58/(Q58+Q59) -> #DIV/0!
J61: Avg sale | K61: =K57/K58 -> #DIV/0! | L61: =L57/L58 -> #DIV/0! | M61: =M57/M58 -> #DIV/0! | N61: =N57/N58 -> #DIV/0! | O61: =O57/O58 -> #DIV/0! | P61: =P57/P58 -> #DIV/0! | Q61: =Q57/Q58 -> #DIV/0!
B64: JOB DETAILS | F64: JOB AMOUNT | K64: PHOTOS | N64: QUOTE | Q64: INVOICE | U64: NOTES
B65: JOB STATUS | C65: DATE | D65: JOB # | E65: SUBURB | F65: AMOUNT EXC. GST | G65: MATERIALS | H65: Merchant Fees | I65: NET PROFIT | J65: PAID | K65: BEFORE | L65: AFTER | M65: RECEIPT | N65: DESCRIPTION | O65: SIGNED | P65: EMAILED | Q65: DESCRIPTION | R65: SIGNED | S65: EMAILED | T65: 5 Star Review | V65: EFTPOS | W65: CASH | X65: Payment Plan
B66: COMPLETED & PAID JOBS
B67: 1 | I67: =F67-G67-H67 -> 0
F68: =SUM(F67:F67) -> 0 | G68: =SUM(G67:G67) -> 0 | H68: =SUM(H67:H67) -> 0 | I68: =SUM(I67:I67) -> 0 | K68: =COUNT(K67:K67) -> 0 | L68: =COUNT(L67:L67) -> 0 | M68: =COUNT(M67:M67) -> 0 | N68: =COUNT(N67:N67) -> 0 | O68: =COUNT(O67:O67) -> 0 | P68: =COUNT(P67:P67) -> 0 | Q68: =COUNT(Q67:Q67) -> 0 | R68: =COUNT(R67:R67) -> 0 | S68: =COUNT(S67:S67) -> 0
K69: =SUM(K67:K67) -> 0 | L69: =SUM(L67:L67) -> 0 | M69: =SUM(M67:M67) -> 0 | N69: =SUM(N67:N67) -> 0 | O69: =SUM(O67:O67) -> 0 | P69: =SUM(P67:P67) -> 0 | Q69: =SUM(Q67:Q67) -> 0 | R69: =SUM(R67:R67) -> 0 | S69: =SUM(S67:S67) -> 0
B70: PREVIOUS JOBS COMPLETED (AWAITING PAYMENT) - Modoras Team Please do ADD to THIS SECTION or AMEND/TOUCH
A71: 45887 | B71: 1 | C71: 45884 | D71: 72353 | E71: Dandenong North | F71: 1675 | G71: =450+(126.6)+200 -> 776.6 | I71: =F71-G71-H71 -> 898.4 | J71: Cash | K71: 1 | L71: 1 | M71: 1 | N71: 1 | O71: 1 | P71: 0 | Q71: 1 | R71: 1 | S71: 0 | U71: 18/8-WIP by Rhys | W71: =1457 -> 1457
F72: =SUM(F71:F71) -> 1675 | G72: =SUM(G71:G71) -> 776.6 | H72: =SUM(H71:H71) -> 0 | I72: =SUM(I71:I71) -> 898.4
T73: =SUM(T67:T72) -> 0 | V73: =SUM(V67:V72) -> 0 | W73: =SUM(W67:W72) -> 1457 | X73: =SUM(X67:X72) -> 0
B76: WEEKLY COMMISSION | F76: WEEK ENDING | G76: 45900
K77: PHOTOS | N77: QUOTE | Q77: INVOICE
B78: BOOKED JOBS | C78: =C79+C80 -> 0 | E78: WEEKLY TARGET | K78: BEFORE | L78: AFTER | M78: RECEIPT | N78: DESCRIPTION | O78: SIGNED | P78: EMAILED | Q78: DESCRIPTION | R78: SIGNED | S78: EMAILED | T78: 5 Star Review
B79: SUCCESSFUL | C79: =P86 -> 0 | E79: Tier 1 | F79: 0.05 | J79: TAKEN | K79: =K105 -> 0 | L79: =L105 -> 0 | M79: =M105 -> 0 | N79: =N105 -> 0 | O79: =O105 -> 0 | P79: =P105 -> 0 | Q79: =Q105 -> 0 | R79: =R105 -> 0 | S79: =S105 -> 0 | T79: =T110 -> 0
B80: UNSUCCESSFUL | C80: =P87 -> 0 | J80: % | K80: =K105/K104 -> #DIV/0! | L80: =L105/L104 -> #DIV/0! | M80: =M105/M104 -> #DIV/0! | N80: =N105/N104 -> #DIV/0! | O80: =O105/O104 -> #DIV/0! | P80: =P105/P104 -> #DIV/0! | Q80: =Q105/Q104 -> #DIV/0! | R80: =R105/R104 -> #DIV/0! | S80: =S105/S104 -> #DIV/0! | U80: M8 Notes
B81: SUCESSFUL (%) | C81: =P88 -> #DIV/0!
F82: ACTUAL | G82: POTENTIAL | H82: Exc. SUPER
B83: AVERAGE SALE | C83: =P89 -> #DIV/0! | E83: NET PROFIT | F83: =P85 -> 0 | G83: =I104 -> 0 | K83: DAILY NET PROFIT | R83: WEEKDAY | S83: WEEKEND
E84: UNLOCKED | F84: =F79 -> 0.05 | K84: MON | L84: TUE | M84: WED | N84: THU | O84: FRI | P84: Total | Q84: SAT | R84: Awaiting Payment | S84: Awaiting Payment
E85: COMMISSION - PAY OUT | F85: =F83*F84 -> 0 | G85: $- | H85: =F85/1.12 -> 0 | K85: 0 | L85: 0 | M85: 0 | N85: 0 | O85: 0 | P85: =SUM(K85:O85) -> 0 | Q85: 0 | R85: 0 | S85: 0
E86: EMERGENCY | F86: =Q85 -> 0 | G86: $- | J86: Successful | K86: 0 | L86: 0 | M86: 0 | N86: 0 | O86: 0 | P86: =SUM(K86:O86) -> 0
E87: EMERGENCY - PAY OUT | F87: =F86*0.25 -> 0 | G87: $- | H87: =F87/1.12 -> 0 | J87: Unsuccessful | K87: 0 | L87: 0 | M87: 0 | N87: 0 | O87: 0 | P87: =SUM(K87:O87) -> 0
E88: PREV. WEEK | F88: =I108 -> 898.4 | G88: $- | J88: Success rate | K88: =K86/(K86+K87) -> #DIV/0! | L88: =L86/(L86+L87) -> #DIV/0! | M88: =M86/(M86+M87) -> #DIV/0! | N88: =N86/(N86+N87) -> #DIV/0! | O88: =O86/(O86+O87) -> #DIV/0! | P88: =P86/(P86+P87) -> #DIV/0! | Q88: =Q86/(Q86+Q87) -> #DIV/0!
E89: PREV. WEEK - PAY OUT | F89: =F88*0.05 -> 44.92 | G89: $- | H89: =F89/1.12 -> 40.107143 | J89: Avg sale | K89: =K85/K86 -> #DIV/0! | L89: =L85/L86 -> #DIV/0! | M89: =M85/M86 -> #DIV/0! | N89: =N85/N86 -> #DIV/0! | O89: =O85/O86 -> #DIV/0! | P89: =P85/P86 -> #DIV/0! | Q89: =Q85/Q86 -> #DIV/0!
E90: 5 Star Review | F90: =1*50 -> 50 | H90: =F90/1.12 -> 44.642857
E91: 5 Star Notes | F91: =T80 -> 0 | K91: Managment Summary - SALES ONLY - COLUMN F | R91: WEEKDAY | S91: WEEKEND
K92: MON | L92: TUE | M92: WED | N92: THU | O92: FRI | P92: Total | Q92: SAT | R92: Awaiting Payment | S92: Awaiting Payment
K93: 0 | L93: 0 | M93: 0 | N93: 0 | O93: 0 | P93: =SUM(K93:O93) -> 0 | Q93: 0 | R93: 0 | S93: 0
J94: Successful | K94: =K86 -> 0 | L94: =L86 -> 0 | M94: =M86 -> 0 | N94: =N86 -> 0 | O94: =O86 -> 0 | P94: =P86 -> 0 | Q94: =Q86 -> 0
J95: Unsuccessful | K95: =K87 -> 0 | L95: =L87 -> 0 | M95: =M87 -> 0 | N95: =N87 -> 0 | O95: =O87 -> 0 | P95: =P87 -> 0 | Q95: =Q87 -> 0
J96: Success rate | K96: =K94/(K94+K95) -> #DIV/0! | L96: =L94/(L94+L95) -> #DIV/0! | M96: =M94/(M94+M95) -> #DIV/0! | N96: =N94/(N94+N95) -> #DIV/0! | O96: =O94/(O94+O95) -> #DIV/0! | P96: =P94/(P94+P95) -> #DIV/0! | Q96: =Q94/(Q94+Q95) -> #DIV/0!
J97: Avg sale | K97: =K93/K94 -> #DIV/0! | L97: =L93/L94 -> #DIV/0! | M97: =M93/M94 -> #DIV/0! | N97: =N93/N94 -> #DIV/0! | O97: =O93/O94 -> #DIV/0! | P97: =P93/P94 -> #DIV/0! | Q97: =Q93/Q94 -> #DIV/0!
B100: JOB DETAILS | F100: JOB AMOUNT | K100: PHOTOS | N100: QUOTE | Q100: INVOICE | U100: NOTES
B101: JOB STATUS | C101: DATE | D101: JOB # | E101: SUBURB | F101: AMOUNT EXC. GST | G101: MATERIALS | H101: Merchant Fees | I101: NET PROFIT | J101: PAID | K101: BEFORE | L101: AFTER | M101: RECEIPT | N101: DESCRIPTION | O101: SIGNED | P101: EMAILED | Q101: DESCRIPTION | R101: SIGNED | S101: EMAILED | T101: 5 Star Review | V101: EFTPOS | W101: CASH | X101: Payment Plan
B102: COMPLETED & PAID JOBS
B103: 1 | I103: =F103-G103-H103 -> 0
F104: =SUM(F103:F103) -> 0 | G104: =SUM(G103:G103) -> 0 | H104: =SUM(H103:H103) -> 0 | I104: =SUM(I103:I103) -> 0 | K104: =COUNT(K103:K103) -> 0 | L104: =COUNT(L103:L103) -> 0 | M104: =COUNT(M103:M103) -> 0 | N104: =COUNT(N103:N103) -> 0 | O104: =COUNT(O103:O103) -> 0 | P104: =COUNT(P103:P103) -> 0 | Q104: =COUNT(Q103:Q103) -> 0 | R104: =COUNT(R103:R103) -> 0 | S104: =COUNT(S103:S103) -> 0
K105: =SUM(K103:K103) -> 0 | L105: =SUM(L103:L103) -> 0 | M105: =SUM(M103:M103) -> 0 | N105: =SUM(N103:N103) -> 0 | O105: =SUM(O103:O103) -> 0 | P105: =SUM(P103:P103) -> 0 | Q105: =SUM(Q103:Q103) -> 0 | R105: =SUM(R103:R103) -> 0 | S105: =SUM(S103:S103) -> 0
B107: PREVIOUS JOBS COMPLETED & PAID (COMMISSION) - Modoras Team Please do ADD to THIS SECTION or AMEND/TOUCH
A108: 45887 | B108: 1 | C108: 45884 | D108: 72353 | E108: Dandenong North | F108: 1675 | G108: =450+(126.6)+200 -> 776.6 | I108: =F108-G108-H108 -> 898.4 | J108: Cash | K108: 1 | L108: 1 | M108: 1 | N108: 1 | O108: 1 | P108: 0 | Q108: 1 | R108: 1 | S108: 0 | U108: 18/8-WIP by Rhys
F109: =SUM(F108:F108) -> 1675 | G109: =SUM(G108:G108) -> 776.6 | H109: =SUM(H108:H108) -> 0 | I109: =SUM(I108:I108) -> 898.4
T110: =SUM(T103:T109) -> 0 | V110: =SUM(V103:V109) -> 0 | W110: =SUM(W103:W109) -> 0 | X110: =SUM(X103:X109) -> 0
B113: WEEKLY COMMISSION | F113: WEEK ENDING | G113: 45914
K114: PHOTOS | N114: QUOTE | Q114: INVOICE
B115: BOOKED JOBS | C115: =C116+C117 -> 0 | E115: WEEKLY TARGET | K115: BEFORE | L115: AFTER | M115: RECEIPT | N115: DESCRIPTION | O115: SIGNED | P115: EMAILED | Q115: DESCRIPTION | R115: SIGNED | S115: EMAILED | T115: 5 Star Review
B116: SUCCESSFUL | C116: =P123 -> 0 | E116: Tier 1 | F116: 0.05 | J116: TAKEN | K116: =K142 -> 0 | L116: =L142 -> 0 | M116: =M142 -> 0 | N116: =N142 -> 0 | O116: =O142 -> 0 | P116: =P142 -> 0 | Q116: =Q142 -> 0 | R116: =R142 -> 0 | S116: =S142 -> 0 | T116: =T147 -> 0
...

Sheet Ben - No OT
B3: WEEKLY COMMISSION | F3: WEEK ENDING | G3: 45837
K4: PHOTOS | N4: QUOTE | Q4: INVOICE
B5: BOOKED JOBS | C5: =C6+C7 -> 28 | E5: WEEKLY TARGET | K5: BEFORE | L5: AFTER | M5: RECEIPT | N5: DESCRIPTION | O5: SIGNED | P5: EMAILED | Q5: DESCRIPTION | R5: SIGNED | S5: EMAILED | T5: 5 Star Review
B6: SUCCESSFUL | C6: =P13 -> 15 | E6: Tier 1 | F6: 0.05 | J6: TAKEN | K6: =K39 -> 8 | L6: =L39 -> 7 | M6: =M39 -> 7 | N6: =N39 -> 8 | O6: =O39 -> 8 | P6: =P39 -> 5 | Q6: =Q39 -> 8 | R6: =R39 -> 7 | S6: =S39 -> 6 | T6: =T80 -> 2
B7: UNSUCCESSFUL | C7: =P14 -> 13 | J7: % | K7: =K39/K38 -> 1 | L7: =L39/L38 -> 0.875 | M7: =M39/M38 -> 0.875 | N7: =N39/N38 -> 1 | O7: =O39/O38 -> 1 | P7: =P39/P38 -> 0.625 | Q7: =Q39/Q38 -> 1 | R7: =R39/R38 -> 0.875 | S7: =S39/S38 -> 0.75 | U7: M8 Notes
B8: SUCESSFUL (%) | C8: =P15 -> 0.53571429
F9: ACTUAL | G9: POTENTIAL | H9: Exc. SUPER
B10: AVERAGE SALE | C10: =P16 -> 2164.764 | E10: NET PROFIT | F10: =P12 -> 32471.46 | G10: =I38+I48+I52 -> 32471.46 | K10: DAILY NET PROFIT | R10: WEEKDAY | S10: WEEKEND
E11: UNLOCKED | F11: =F6 -> 0.05 | K11: MON | L11: TUE | M11: WED | N11: THU | O11: FRI | P11: Total | Q11: SAT | R11: Awaiting Payment | S11: Awaiting Payment
E12: COMMISSION - PAY OUT | F12: =(F10+F19-I37-I36-I42-I43-I44-I45-I46-I47-I51)*F11 -> 615.15 | G12: $- | H12: =F12/1.12 -> 549.24107 | K12: =I30+I31+I42 -> 4595.05 | L12: =I43+I32+I44 -> 6204.86 | M12: =I34+I45+I33+I46 -> 9344.35 | N12: =I35+I51 -> 7726.6 | O12: =I36+I37+I47 -> 4600.6 | P12: =SUM(K12:O12) -> 32471.46 | Q12: 0 | R12: =I48+I52 -> 17939.16 | S12: 0
E13: EMERGENCY | F13: =Q12 -> 0 | G13: $- | J13: Successful | K13: 3 | L13: 3 | M13: 4 | N13: 2 | O13: 3 | P13: =SUM(K13:O13) -> 15
E14: EMERGENCY - PAY OUT | F14: =F13*0.25 -> 0 | G14: $- | H14: =F14/1.12 -> 0 | J14: Unsuccessful | K14: 2 | L14: 2 | M14: 1 | N14: 2 | O14: 6 | P14: =SUM(K14:O14) -> 13
E15: PREV. WEEK | G15: $- | J15: Success rate | K15: =K13/(K13+K14) -> 0.6 | L15: =L13/(L13+L14) -> 0.6 | M15: =M13/(M13+M14) -> 0.8 | N15: =N13/(N13+N14) -> 0.5 | O15: =O13/(O13+O14) -> 0.33333333 | P15: =P13/(P13+P14) -> 0.53571429 | Q15: =Q13/(Q13+Q14) -> #DIV/0!
E16: PREV. WEEK - PAY OUT | F16: =F15*0.05 -> 0 | G16: $- | H16: =F16/1.12 -> 0 | J16: Avg sale | K16: =K12/K13 -> 1531.6833 | L16: =L12/L13 -> 2068.2867 | M16: =M12/M13 -> 2336.0875 | N16: =N12/N13 -> 3863.3 | O16: =O12/O13 -> 1533.5333 | P16: =P12/P13 -> 2164.764 | Q16: =Q12/Q13 -> #DIV/0!
E17: 5 Star Review | F17: =1*50 -> 50 | H17: =F17/1.12 -> 44.642857
E18: 5 Star Notes | F18: =T7 -> 0 | K18: Managment Summary - SALES ONLY - COLUMN F | R18: WEEKDAY | S18: WEEKEND
E19: 16 Jun - Water Leak - Job #70792 | F19: =-450 -> -450 | K19: MON | L19: TUE | M19: WED | N19: THU | O19: FRI | P19: Total | Q19: SAT | R19: Awaiting Payment | S19: Awaiting Payment
K20: =F30+F31+F42 -> 7075 | L20: =F43+F32+F44 -> 8608 | M20: =F34+F45+F33+F46 -> 12993 | N20: =F35+F51 -> 12606 | O20: =F36+F37+F47 -> 4680 | P20: =SUM(K20:O20) -> 45962 | Q20: 0 | R20: =F48+F52 -> 26236 | S20: 0
J21: Successful | K21: =K13 -> 3 | L21: =L13 -> 3 | M21: =M13 -> 4 | N21: =N13 -> 2 | O21: =O13 -> 3 | P21: =P13 -> 15 | Q21: =Q13 -> 0
J22: Unsuccessful | K22: =K14 -> 2 | L22: =L14 -> 2 | M22: =M14 -> 1 | N22: =N14 -> 2 | O22: =O14 -> 6 | P22: =P14 -> 13 | Q22: =Q14 -> 0
J23: Success rate | K23: =K21/(K21+K22) -> 0.6 | L23: =L21/(L21+L22) -> 0.6 | M23: =M21/(M21+M22) -> 0.8 | N23: =N21/(N21+N22) -> 0.5 | O23: =O21/(O21+O22) -> 0.33333333 | P23: =P21/(P21+P22) -> 0.53571429 | Q23: =Q21/(Q21+Q22) -> #DIV/0!
J24: Avg sale | K24: =K20/K21 -> 2358.3333 | L24: =L20/L21 -> 2869.3333 | M24: =M20/M21 -> 3248.25 | N24: =N20/N21 -> 6303 | O24: =O20/O21 -> 1560 | P24: =P20/P21 -> 3064.1333 | Q24: =Q20/Q21 -> #DIV/0!
B27: JOB DETAILS | F27: JOB AMOUNT | K27: PHOTOS | N27: QUOTE | Q27: INVOICE | U27: NOTES
B28: JOB STATUS | C28: DATE | D28: JOB # | E28: SUBURB | F28: AMOUNT EXC. GST | G28: MATERIALS | H28: Merchant Fees | I28: NET PROFIT | J28: PAID | K28: BEFORE | L28: AFTER | M28: RECEIPT | N28: DESCRIPTION | O28: SIGNED | P28: EMAILED | Q28: DESCRIPTION | R28: SIGNED | S28: EMAILED | T28: 5 Star Review | V28: EFTPOS | W28: CASH | X28: Payment Plan
B29: COMPLETED & PAID JOBS
B30: 1 | C30: 45831 | D30: 70938/85882114 | E30: Reservoir | F30: 681 | I30: =F30-G30-H30 -> 681 | J30: Card | K30: 1 | L30: 1 | M30: 1 | N30: 1 | O30: 1 | P30: 0 | Q30: 1 | R30: 0 | S30: 1 | U30: 23/06 - WIP&Completed By Tolga , Ben | V30: 749.1
B31: =B30+1 -> 2 | C31: 45831 | D31: 70960 | E31: Coburg | F31: 1261 | G31: 39.7 | I31: =F31-G31-H31 -> 1221.3 | J31: Card | K31: 1 | L31: 1 | M31: 1 | N31: 1 | O31: 1 | P31: 0 | Q31: 1 | R31: 1 | S31: 0 | V31: 1387.1
B32: =B31+1 -> 3 | C32: 45832 | D32: 70985 | E32: North Melbourne | F32: 5814 | G32: =39.7+(1430.19)+250 -> 1719.89 | I32: =F32-G32-H32 -> 4094.11 | J32: Card | K32: 1 | L32: 1 | M32: 1 | N32: 1 | O32: 1 | P32: 1 | Q32: 1 | R32: 1 | S32: 1 | U32: 25/06 - WIP&Completed by Daniel C ; 24/06 - WIP by Daniel C , Ben | V32: =640+5500+255.4 -> 6395.4
B33: =B32+1 -> 4 | C33: 45833 | D33: 70918/858910127 | E33: Doncaster | F33: 7075 | G33: =39.7+(78.67)+(1.6+2365.41+143.43+41.8)+500 -> 3170.61 | I33: =F33-G33-H33 -> 3904.39 | J33: Card | K33: 1 | L33: 1 | M33: 1 | N33: 1 | O33: 1 | P33: 0 | Q33: 1 | R33: 1 | S33: 0 | U33: 26/06 - WIP&Completed by Alex ;25/06 - WIP by Jarrod , Ben ,Alex | V33: =75+674.1+783+6250.4 -> 7782.5
A34: 09/07 CB09/07 | B34: =B33+1 -> 5 | C34: 45833 | D34: 70990/71313 | E34: Mavleod | F34: 2023 | G34: =39.7+(144.4) -> 184.1 | I34: =F34-G34-H34 -> 1838.9 | J34: Card | K34: 1 | L34: 1 | M34: 0 | N34: 1 | O34: 1 | P34: 1 | Q34: 1 | R34: 1 | S34: 1 | U34: 09/07 CB - Attended by Daniel B | V34: =226+1999.3 -> 2225.3
B35: =B34+1 -> 6 | C35: 45834 | D35: 71018 | E35: Preston | F35: 1053 | G35: 39.7 | I35: =F35-G35-H35 -> 1013.3 | J35: Card | K35: 1 | L35: 1 | M35: 1 | N35: 1 | O35: 1 | P35: 1 | Q35: 1 | R35: 1 | S35: 1 | T35: 1 | V35: =119+1039.3 -> 1158.3
B36: =B35+1 -> 7 | C36: 45835 | D36: 71065 | E36: Elsternwick | F36: 681 | I36: =F36-G36-H36 -> 681 | J36: Card | K36: 1 | L36: 1 | M36: 1 | N36: 1 | O36: 1 | P36: 1 | Q36: 1 | R36: 1 | S36: 1 | U36: 27 Jun - Paying 1hr O/T | V36: =75+674.1 -> 749.1
B37: =B36+1 -> 8 | C37: 45835 | D37: 71086/85951516 | E37: Richmond | F37: 1138 | G37: 39.7 | I37: =F37-G37-H37 -> 1098.3 | J37: Card | K37: 1 | L37: 0 | M37: 1 | N37: 1 | O37: 1 | P37: 1 | Q37: 1 | R37: 1 | S37: 1 | U37: 27 Jun - Paying 1.25hrs O/T | V37: 1251.8
F38: =SUM(F30:F37) -> 19726 | G38: =SUM(G30:G37) -> 5193.7 | H38: =SUM(H30:H37) -> 0 | I38: =SUM(I30:I37) -> 14532.3 | K38: =COUNT(K30:K37) -> 8 | L38: =COUNT(L30:L37) -> 8 | M38: =COUNT(M30:M37) -> 8 | N38: =COUNT(N30:N37) -> 8 | O38: =COUNT(O30:O37) -> 8 | P38: =COUNT(P30:P37) -> 8 | Q38: =COUNT(Q30:Q37) -> 8 | R38: =COUNT(R30:R37) -> 8 | S38: =COUNT(S30:S37) -> 8
K39: =SUM(K30:K37) -> 8 | L39: =SUM(L30:L37) -> 7 | M39: =SUM(M30:M37) -> 7 | N39: =SUM(N30:N37) -> 8 | O39: =SUM(O30:O37) -> 8 | P39: =SUM(P30:P37) -> 5 | Q39: =SUM(Q30:Q37) -> 8 | R39: =SUM(R30:R37) -> 7 | S39: =SUM(S30:S37) -> 6
B41: CURRENT JOBS COMPLETED (AWAITING PAYMENT)
A42: 26/06 CB26/06 | B42: 1 | C42: 45831 | D42: 70938/85882653 | E42: Reservoir | F42: 5133 | G42: =39.7+(1906.7+43.85)+250+200 -> 2440.25 | I42: =F42-G42-H42 -> 2692.75 | J42: Card | K42: 1 | L42: 1 | M42: 0 | N42: 1 | O42: 1 | P42: 0 | Q42: 1 | R42: 0 | S42: 1 | U42: 26/06 CB - Attended by Matthew H ISSUE - No water pressure ; 24/06 - WIP&Completed by Tolga; 23/06 - WIP By Tolga , Ben | V42: =565+2500 -> 3065
B43: =B42+1 -> 2 | C43: 45832 | D43: 70976/85898894 | E43: Carlton | F43: =681-681 -> 0 | I43: =F43-G43-H43 -> 0 | K43: 1 | L43: 1 | N43: 1 | O43: 1 | P43: 0 | Q43: 0 | R43: 0 | S43: 0 | U43: Payment update not Available in invoice Tab
B44: =B43+1 -> 3 | C44: 45832 | D44: 70976/85899215 | E44: Carlton | F44: 2794 | G44: =39.7+(46.62+153.12+243.81)+200 -> 683.25 | I44: =F44-G44-H44 -> 2110.75 | J44: Card | K44: 1 | L44: 1 | M44: 1 | N44: 1 | O44: 1 | P44: 0 | Q44: 1 | R44: 1 | S44: 0 | T44: 1 | U44: 24 Jun - Deduct 30mins O/T; 30/06 - WIP&Completed by Tolga ; 25/06 - WIP by Tolga Temp check by monday | V44: =75+674.01+307.5+255.5 -> 1312.01
B45: =B44+1 -> 4 | C45: 45833 | D45: 70918/85908669 | E45: Doncaster | F45: 681 | I45: =F45-G45-H45 -> 681 | K45: 1 | L45: 1 | N45: 1 | O45: 1 | P45: 1 | Q45: 1 | R45: 1 | S45: 1 | U45: 26/06 - WIP&Completed by Alex ; 25/06 - WIP& Completed by Jarrod , Ben , Alex; Payment update not Available in invoice Tab
B46: =B33+1 -> 5 | C46: 45833 | D46: 71021 | E46: Thornbury | F46: 3214 | G46: =39.7+(54.24)+200 -> 293.94 | I46: =F46-G46-H46 -> 2920.06 | J46: Card/PP | K46: 1 | L46: 1 | M46: 0 | N46: 1 | O46: 1 | P46: 1 | Q46: 1 | R46: 1 | S46: 1 | U46: 25 Jun - Deduct 2.5hrs O/T; 25/06 - As per Ben's note - Humm payment approved , no pics uploaded for approved | V46: 354
B47: =B46+1 -> 6 | C47: 45835 | D47: 70987 | E47: Ringwood | F47: 2861 | G47: 39.7 | I47: =F47-G47-H47 -> 2821.3 | J47: Card | K47: 1 | L47: 1 | M47: 1 | N47: 1 | O47: 1 | P47: 0 | Q47: 1 | R47: 1 | S47: 1 | V47: 315
F48: =SUM(F42:F47) -> 14683 | G48: =SUM(G42:G47) -> 3457.14 | H48: =SUM(H42:H47) -> 0 | I48: =SUM(I42:I47) -> 11225.86
B50: CURRENT WORK ORDERS (AWAITING PAYMENT)
A51: 0.05 | B51: 1 | C51: 45834 | D51: 70849/85931834 | E51: Fairfield | F51: 11553 | G51: =39.7+4500+300 -> 4839.7 | I51: =F51-G51-H51 -> 6713.3 | J51: Card | K51: 1 | M51: 1 | N51: 1 | O51: 1 | P51: 0 | U51: 30/06 - Scheduled for Liam | V51: 1270
F52: =SUM(F51:F51) -> 11553 | G52: =SUM(G51:G51) -> 4839.7 | H52: =SUM(H51:H51) -> 0 | I52: =SUM(I51:I51) -> 6713.3
B54: PREVIOUS JOBS COMPLETED (AWAITING PAYMENT) - Modoras Team Please do ADD to THIS SECTION or AMEND/TOUCH
A55: 0.05 | B55: 1 | C55: 45800 | D55: 70335 | E55: Ashwood | F55: 1619 | G55: 39.7 | I55: =F55-G55-H55 -> 1579.3 | J55: Card /EFT | K55: 1 | L55: 1 | M55: 1 | N55: 1 | O55: 1 | P55: 1 | Q55: 1 | R55: 0 | S55: 1 | U55: 23/05- EFT Processed $1780.90
A56: 5% - NGP | B56: =B55+1 -> 2 | C56: 45805 | D56: 70409/85622509 | E56: Maribyrnong | F56: 2999.1 | G56: 39.7 | H56: =F56*0.2 -> 599.82 | I56: =F56-G56-H56 -> 2359.58 | J56: NGP | K56: 1 | L56: 1 | M56: 1 | N56: 1 | O56: 1 | P56: 0 | Q56: 0 | R56: 0 | S56: 0 | U56: NGP 13/06. 28/05- Humm PP Approved
A57: 5% - NGP | B57: =B56+1 -> 3 | C57: 45805 | D57: 70409/85623460 | E57: Maribyrnong | F57: 16214 | G57: =39.7+44+36.26+(33.82+55.44)+(102.43+254.2+84.43+10.82+125.93)+1500 -> 2287.03 | H57: =F57*0.2 -> 3242.8 | I57: =F57-G57-H57 -> 10684.17 | J57: NGP | K57: 1 | M57: 1 | N57: 1 | O57: 1 | P57: 0 | Q57: 1 | R57: 1 | S57: 0 | U57: NGP27/06. NGP 13/06. 02/06-WIP&Completedby Alex,Tolga29/04- WIP by Liam & Ben ; 28/05- Humm PP Approved | X57: 219.33
A58: 0.05 | B58: =B57+1 -> 4 | C58: 45826 | D58: 70849 | E58: Fairfield | F58: 1261 | G58: 39.7 | I58: =F58-G58-H58 -> 1221.3 | J58: Card | K58: 1 | M58: 1 | N58: 1 | O58: 1 | P58: 1 | U58: 20/06 - Unable to add the payment in the invoice tab
F59: =SUM(F55:F58) -> 22093.1 | G59: =SUM(G55:G58) -> 2406.13 | H59: =SUM(H55:H58) -> 3842.62 | I59: =SUM(I55:I58) -> 15844.35
B61: PREVIOUS WORK ORDERS (AWAITING PAYMENT) - Modoras Team Please do ADD to THIS SECTION or AMEND/TOUCH
A62: 0.05 | B62: 1 | C62: 45789 | D62: 70067 | E62: Yarraville | F62: 481 | I62: =F62-G62-H62 -> 481 | K62: 1 | N62: 1 | O62: 1 | P62: 0
F63: =SUM(F62:F62) -> 481 | G63: =SUM(G62:G62) -> 0 | H63: =SUM(H62:H62) -> 0 | I63: =SUM(I62:I62) -> 481
B65: UNSUCCESSFUL JOBS
B66: 1 | C66: 45831 | D66: 70691 | E66: Burnswick | F66: 16214 | G66: 39.7 | I66: =F66-G66-H66 -> 16174.3 | J66: N/A | K66: 1 | N66: 1 | Q66: 1 | R66: 1 | S66: 1
B67: =B66+1 -> 2 | C67: 45831 | D67: 70950 | E67: Fawkner | F67: 28614 | G67: 39.7 | I67: =F67-G67-H67 -> 28574.3 | J67: N/A | K67: 1 | N67: 1 | Q67: 1 | R67: 1 | S67: 1
B68: =B67+1 -> 3 | C68: 45832 | D68: 70965 | E68: Burnswick West | F68: 16214 | G68: 39.7 | I68: =F68-G68-H68 -> 16174.3 | J68: N/A | K68: 1 | N68: 1 | Q68: 1 | R68: 1 | S68: 1 | U68: 24/06 - As per Ben's note - Client cannot get approval through humm due to being a business owner
B69: =B68+1 -> 4 | C69: 45832 | D69: 70973 | E69: Ivanhoe | F69: 4376 | G69: 39.7 | I69: =F69-G69-H69 -> 4336.3 | J69: N/A | K69: 1 | N69: 1 | Q69: 1 | R69: 1 | S69: 1
B70: =B69+1 -> 5 | C70: 45833 | D70: 71023 | E70: Greensborough | F70: 616 | I70: =F70-G70-H70 -> 616 | J70: N/A | K70: 1 | N70: 1 | Q70: 1 | R70: 1 | S70: 1
B71: =B70+1 -> 6 | C71: 45834 | D71: 71019 | E71: South Yarra | F71: 5559 | G71: 39.7 | I71: =F71-G71-H71 -> 5519.3 | J71: N/A | K71: 1 | N71: 1 | Q71: 1 | R71: 1 | S71: 1
B72: =B71+1 -> 7 | C72: 45834 | D72: 71038 | E72: Burnswick West | F72: 596 | I72: =F72-G72-H72 -> 596 | J72: N/A | K72: 1 | N72: 1 | Q72: 1 | R72: 1 | S72: 1
B73: =B72+1 -> 8 | C73: 45835 | D73: 71036 | E73: Burnwood | F73: 2176 | G73: 39.7 | I73: =F73-G73-H73 -> 2136.3 | J73: N/A | K73: 1 | N73: 1 | Q73: 1 | R73: 1 | S73: 1
B74: =B73+1 -> 9 | C74: 45835 | D74: 71015 | E74: Prahran | F74: 681 | I74: =F74-G74-H74 -> 681 | J74: N/A | K74: 1 | N74: 1 | Q74: 1 | R74: 1 | S74: 1
A75: 45847 | B75: =B74+1 -> 10 | C75: 45835 | D75: 71049 | E75: Burnwood East | F75: 4461 | G75: 39.7 | I75: =F75-G75-H75 -> 4421.3 | J75: Card | K75: 1 | M75: 1 | N75: 1 | O75: 1 | U75: 9 Jul - Refund - $491; 27/06 - WIP by Ben Customer Cancelled the job Refund initiated | V75: 491
B76: =B75+1 -> 11 | C76: 45835 | D76: 71050 | E76: Camberwell | F76: 12814 | G76: 39.7 | I76: =F76-G76-H76 -> 12774.3 | J76: N/A | K76: 1 | N76: 1 | Q76: 1 | R76: 1 | S76: 1
B77: =B76+1 -> 12 | C77: 45835 | D77: 71086/85951305 | E77: Richmond | F77: 5592.6 | G77: 39.7 | I77: =F77-G77-H77 -> 5552.9 | J77: N/A | K77: 1 | N77: 1
B78: =B77+1 -> 13 | C78: 45835 | D78: 71066 | E78: Hampton | F78: 0 | I78: =F78-G78-H78 -> 0 | J78: Quote
F79: =SUM(F66:F78) -> 97913.6 | G79: =SUM(G66:G78) -> 357.3 | H79: =SUM(H66:H78) -> 0 | I79: =SUM(I66:I78) -> 97556.3
T80: =SUM(T30:T79) -> 2 | V80: =SUM(V30:V79) -> 28505.61 | W80: =SUM(W30:W79) -> 0 | X80: =SUM(X30:X79) -> 219.33
B84: WEEKLY COMMISSION | F84: WEEK ENDING | G84: 45844
K85: PHOTOS | N85: QUOTE | Q85: INVOICE
B86: BOOKED JOBS | C86: =C87+C88 -> 27 | E86: WEEKLY TARGET | K86: BEFORE | L86: AFTER | M86: RECEIPT | N86: DESCRIPTION | O86: SIGNED | P86: EMAILED | Q86: DESCRIPTION | R86: SIGNED | S86: EMAILED | T86: 5 Star Review
B87: SUCCESSFUL | C87: =P94 -> 15 | E87: Tier 1 | F87: 0.05 | J87: TAKEN | K87: =K123 -> 11 | L87: =L123 -> 10 | M87: =M123 -> 10 | N87: =N123 -> 11 | O87: =O123 -> 10 | P87: =P123 -> 8 | Q87: =Q123 -> 8 | R87: =R123 -> 5 | S87: =S123 -> 8 | T87: =T183 -> 0
B88: UNSUCCESSFUL | C88: =P95 -> 12 | J88: % | K88: =K123/K122 -> 1 | L88: =L123/L122 -> 0.90909091 | M88: =M123/M122 -> 0.90909091 | N88: =N123/N122 -> 1 | O88: =O123/O122 -> 0.90909091 | P88: =P123/P122 -> 0.72727273 | Q88: =Q123/Q122 -> 0.72727273 | R88: =R123/R122 -> 0.45454545 | S88: =S123/S122 -> 0.72727273 | U88: M8 Notes
B89: SUCESSFUL (%) | C89: =P96 -> 0.55555556
F90: ACTUAL | G90: POTENTIAL | H90: Exc. SUPER
B91: AVERAGE SALE | C91: =P97 -> 1959.582 | E91: NET PROFIT | F91: =P93 -> 29393.73 | G91: =I122+I142+I147 -> 29393.73 | K91: DAILY NET PROFIT | R91: WEEKDAY | S91: WEEKEND
E92: UNLOCKED | F92: =F87 -> 0.05 | K92: MON | L92: TUE | M92: WED | N92: THU | O92: FRI | P92: Total | Q92: SAT | R92: Awaiting Payment | S92: Awaiting Payment
E93: COMMISSION - PAY OUT | F93: =(F91-I113-I114-I118-I119-I140-I141-I145-I146)*F92 -> 469.206 | G93: $- | H93: =F93/1.12 -> 418.93393 | K93: =I111+I113+I114+I140+I112 -> 7859.14 | L93: =+I115+I141+I145 -> 4000.6 | M93: =+I116+I117+I146 -> 14266.04 | N93: =I118 -> 898.3 | O93: =I119+I121+I120 -> 2369.65 | P93: =SUM(K93:O93) -> 29393.73 | Q93: =+I126+I127+I128 -> 2903.17 | R93: =I142+I147 -> 16875.34 | S93: =0 -> 0
E94: EMERGENCY | F94: =Q93 -> 2903.17 | G94: $- | I94: O/T = 8.75hrs | J94: Successful | K94: 5 | L94: 3 | M94: 3 | N94: 1 | O94: 3 | P94: =SUM(K94:O94) -> 15 | Q94: 3
E95: EMERGENCY - PAY OUT | F95: =F94*0.25 -> 725.7925 | G95: $- | H95: =F95/1.12 -> 648.02902 | I95: =67.5*8.75 -> 590.625 | J95: Unsuccessful | K95: 2 | L95: 3 | M95: 2 | N95: 2 | O95: 3 | P95: =SUM(K95:O95) -> 12 | Q95: 2
E96: PREV. WEEK | F96: =I137 -> 21273.54 | G96: $- | J96: Success rate | K96: =K94/(K94+K95) -> 0.71428571 | L96: =L94/(L94+L95) -> 0.5 | M96: =M94/(M94+M95) -> 0.6 | N96: =N94/(N94+N95) -> 0.33333333 | O96: =O94/(O94+O95) -> 0.5 | P96: =P94/(P94+P95) -> 0.55555556 | Q96: =Q94/(Q94+Q95) -> 0.6
E97: PREV. WEEK - PAY OUT | F97: =(F96+F100+F101+F102+F103-I133-I134)*0.05 -> 901.0635 | G97: $- | H97: =F97/1.12 -> 804.52098 | J97: Avg sale | K97: =K93/K94 -> 1571.828 | L97: =L93/L94 -> 1333.5333 | M97: =M93/M94 -> 4755.3467 | N97: =N93/N94 -> 898.3 | O97: =O93/O94 -> 789.88333 | P97: =P93/P94 -> 1959.582 | Q97: =Q93/Q94 -> 967.72333
E98: 5 Star Review | H98: =F98/1.12 -> 0
E99: 5 Star Notes | F99: =T88 -> 0 | K99: Managment Summary - SALES ONLY - COLUMN F | R99: WEEKDAY | S99: WEEKEND
E100: 2/7- Reece - 1013955863 - FES83E | F100: -119.56 | K100: MON | L100: TUE | M100: WED | N100: THU | O100: FRI | P100: Total | Q100: SAT | R100: Awaiting Payment | S100: Awaiting Payment
E101: 04/07 Bunnings - 6310/01643619 - Job FES83E | F101: -86.99 | K101: =F111+F113+F114+F140+F112 -> 8233 | L101: =+F115+F141+F145 -> 4080 | M101: =+F116+F117+F146 -> 16035 | N101: =F118 -> 1138 | O101: =F119+F121+F120 -> 2457.05 | P101: =SUM(K101:O101) -> 31943.05 | Q101: =+F140+F141+F120 -> 3206 | R101: =F142+F147 -> 18484 | S101: =0 -> 0
E102: 7 Jul - Bunnings - STOCK ReImb | F102: =-129 -> -129 | J102: Successful | K102: =K94 -> 5 | L102: =L94 -> 3 | M102: =M94 -> 3 | N102: =N94 -> 1 | O102: =O94 -> 3 | P102: =P94 -> 15 | Q102: =Q94 -> 3
E103: 05/07 Reece - 1014063807 - Job 000000 | F103: -124.97 | J103: Unsuccessful | K103: =K95 -> 2 | L103: =L95 -> 3 | M103: =M95 -> 2 | N103: =N95 -> 2 | O103: =O95 -> 3 | P103: =P95 -> 12 | Q103: =Q95 -> 2
J104: Success rate | K104: =K102/(K102+K103) -> 0.71428571 | L104: =L102/(L102+L103) -> 0.5 | M104: =M102/(M102+M103) -> 0.6 | N104: =N102/(N102+N103) -> 0.33333333 | O104: =O102/(O102+O103) -> 0.5 | P104: =P102/(P102+P103) -> 0.55555556 | Q104: =Q102/(Q102+Q103) -> 0.6
J105: Avg sale | K105: =K101/K102 -> 1646.6 | L105: =L101/L102 -> 1360 | M105: =M101/M102 -> 5345 | N105: =N101/N102 -> 1138 | O105: =O101/O102 -> 819.01667 | P105: =P101/P102 -> 2129.5367 | Q105: =Q101/Q102 -> 1068.6667
B108: JOB DETAILS | F108: JOB AMOUNT | K108: PHOTOS | N108: QUOTE | Q108: INVOICE | U108: NOTES
B109: JOB STATUS | C109: DATE | D109: JOB # | E109: SUBURB | F109: AMOUNT EXC. GST | G109: MATERIALS | H109: Merchant Fees | I109: NET PROFIT | J109: PAID | K109: BEFORE | L109: AFTER | M109: RECEIPT | N109: DESCRIPTION | O109: SIGNED | P109: EMAILED | Q109: DESCRIPTION | R109: SIGNED | S109: EMAILED | T109: 5 Star Review | V109: EFTPOS | W109: CASH | X109: Payment Plan
B110: COMPLETED & PAID JOBS
B111: 1 | C111: 45838 | D111: 71076 | E111: Northcote | F111: 814 | G111: =39.7+(14.68) -> 54.38 | I111: =F111-G111-H111 -> 759.62 | J111: Card | K111: 1 | L111: 1 | M111: 1 | N111: 1 | O111: 1 | P111: 1 | Q111: 1 | R111: 0 | S111: 1 | V111: =90+805.4 -> 895.4
B112: =B111+1 -> 2 | C112: 45838 | D112: 71102/85964217 | E112: Jacana | F112: 4261 | G112: 39.7 | I112: =F112-G112-H112 -> 4221.3 | J112: Card/EFT | K112: 1 | L112: 1 | M112: 1 | N112: 1 | O112: 0 | P112: 0 | Q112: 0 | R112: 0 | S112: 0 | U112: 30/06 - WIP byTolga, Ben | V112: =468.71+4218.39 -> 4687.1
A113: Paid Dispute | B113: =B112+1 -> 3 | C113: 45838 | D113: 71095/85966107 | E113: Reservoir | F113: 616 | I113: =F113-G113-H113 -> 616 | J113: Card | K113: 1 | L113: 1 | M113: 0 | N113: 1 | O113: 1 | P113: 1 | Q113: 1 | R113: 0 | S113: 1 | V113: =68+609.6 -> 677.6
A114: Paid Dispute | B114: =B113+1 -> 4 | C114: 45838 | D114: 71095/85966017 | E114: Reservoir | F114: 1281 | G114: =39.7+(200.38) -> 240.08 | I114: =F114-G114-H114 -> 1040.92 | J114: Card | K114: 1 | L114: 1 | M114: 1 | N114: 1 | O114: 1 | P114: 1 | Q114: 1 | R114: 0 | S114: 1 | V114: =140.9+1268.2 -> 1409.1
...

Sheet Bradley
B3: WEEKLY COMMISSION | F3: WEEK ENDING | G3: 45893
K4: PHOTOS | N4: QUOTE | Q4: INVOICE
B5: BOOKED JOBS | C5: =C6+C7 -> 8 | E5: WEEKLY TARGET | K5: BEFORE | L5: AFTER | M5: RECEIPT | N5: DESCRIPTION | O5: SIGNED | P5: EMAILED | Q5: DESCRIPTION | R5: SIGNED | S5: EMAILED | T5: 5 Star Review
B6: SUCCESSFUL | C6: =P13 -> 2 | E6: Tier 1 | F6: 0.05 | J6: TAKEN | K6: =K32 -> 1 | L6: =L32 -> 0 | M6: =M32 -> 1 | N6: =N32 -> 1 | O6: =O32 -> 1 | P6: =P32 -> 1 | Q6: =Q32 -> 1 | R6: =R32 -> 1 | S6: =S32 -> 0 | T6: =T46 -> 0
B7: UNSUCCESSFUL | C7: =P14 -> 6 | J7: % | K7: =K32/K31 -> 1 | L7: =L32/L31 -> 0 | M7: =M32/M31 -> 1 | N7: =N32/N31 -> 1 | O7: =O32/O31 -> 1 | P7: =P32/P31 -> 1 | Q7: =Q32/Q31 -> 1 | R7: =R32/R31 -> 1 | S7: =S32/S31 -> 0 | U7: M8 Notes
B8: SUCESSFUL (%) | C8: =P15 -> 0.25
F9: ACTUAL | G9: POTENTIAL | H9: Exc. SUPER
B10: AVERAGE SALE | C10: =P16 -> 1775.585 | E10: NET PROFIT | F10: =P12 -> 3551.17 | G10: =I31+I36 -> 3551.17 | H10: 27 Aug - 5% will be paid out upon Achieving 5 Star Reviews | K10: DAILY NET PROFIT | R10: WEEKDAY | S10: WEEKEND
E11: UNLOCKED | F11: =F6 -> 0.05 | K11: MON | L11: TUE | M11: WED | N11: THU | O11: FRI | P11: Total | Q11: SAT | R11: Awaiting Payment | S11: Awaiting Payment
E12: COMMISSION - PAY OUT | F12: =(F10-I30-I35)*F11 -> 0 | G12: $- | H12: =F12/1.12 -> 0 | L12: 0 | M12: 0 | N12: =I30+I35 -> 3551.17 | P12: =SUM(K12:O12) -> 3551.17 | Q12: 0 | R12: =I36 -> 2870.17 | S12: 0
E13: EMERGENCY | F13: =Q12 -> 0 | G13: $- | J13: Successful | L13: 0 | M13: 0 | N13: 2 | O13: 0 | P13: =SUM(K13:O13) -> 2
E14: EMERGENCY - PAY OUT | F14: =F13*0.25 -> 0 | G14: $- | H14: =F14/1.12 -> 0 | J14: Unsuccessful | L14: 1 | M14: 3 | N14: 0 | O14: 2 | P14: =SUM(K14:O14) -> 6
E15: PREV. WEEK | G15: $- | J15: Success rate | K15: =K13/(K13+K14) -> #DIV/0! | L15: =L13/(L13+L14) -> 0 | M15: =M13/(M13+M14) -> 0 | N15: =N13/(N13+N14) -> 1 | O15: =O13/(O13+O14) -> 0 | P15: =P13/(P13+P14) -> 0.25 | Q15: =Q13/(Q13+Q14) -> #DIV/0!
E16: PREV. WEEK - PAY OUT | F16: =F15*0.05 -> 0 | G16: $- | H16: =F16/1.12 -> 0 | J16: Avg sale | K16: =K12/K13 -> #DIV/0! | L16: =L12/L13 -> #DIV/0! | M16: =M12/M13 -> #DIV/0! | N16: =N12/N13 -> 1775.585 | O16: =O12/O13 -> #DIV/0! | P16: =P12/P13 -> 1775.585 | Q16: =Q12/Q13 -> #DIV/0!
E17: 5 Star Review | H17: =F17/1.12 -> 0
E18: 5 Star Notes | F18: =T7 -> 0 | K18: Managment Summary - SALES ONLY - COLUMN F | R18: WEEKDAY | S18: WEEKEND
K19: MON | L19: TUE | M19: WED | N19: THU | O19: FRI | P19: Total | Q19: SAT | R19: Awaiting Payment | S19: Awaiting Payment
L20: 0 | M20: 0 | N20: =F30+F35 -> 4793 | P20: =SUM(K20:O20) -> 4793 | Q20: 0 | R20: =F35 -> 4112 | S20: 0
J21: Successful | K21: =K13 -> 0 | L21: =L13 -> 0 | M21: =M13 -> 0 | N21: =N13 -> 2 | O21: =O13 -> 0 | P21: =P13 -> 2 | Q21: =Q13 -> 0
J22: Unsuccessful | K22: =K14 -> 0 | L22: =L14 -> 1 | M22: =M14 -> 3 | N22: =N14 -> 0 | O22: =O14 -> 2 | P22: =P14 -> 6 | Q22: =Q14 -> 0
J23: Success rate | K23: =K21/(K21+K22) -> #DIV/0! | L23: =L21/(L21+L22) -> 0 | M23: =M21/(M21+M22) -> 0 | N23: =N21/(N21+N22) -> 1 | O23: =O21/(O21+O22) -> 0 | P23: =P21/(P21+P22) -> 0.25 | Q23: =Q21/(Q21+Q22) -> #DIV/0!
J24: Avg sale | K24: =K20/K21 -> #DIV/0! | L24: =L20/L21 -> #DIV/0! | M24: =M20/M21 -> #DIV/0! | N24: =N20/N21 -> 2396.5 | O24: =O20/O21 -> #DIV/0! | P24: =P20/P21 -> 2396.5 | Q24: =Q20/Q21 -> #DIV/0!
B27: JOB DETAILS | F27: JOB AMOUNT | K27: PHOTOS | N27: QUOTE | Q27: INVOICE | U27: NOTES
B28: JOB STATUS | C28: DATE | D28: JOB # | E28: SUBURB | F28: AMOUNT EXC. GST | G28: MATERIALS | H28: Merchant Fees | I28: NET PROFIT | J28: PAID | K28: BEFORE | L28: AFTER | M28: RECEIPT | N28: DESCRIPTION | O28: SIGNED | P28: EMAILED | Q28: DESCRIPTION | R28: SIGNED | S28: EMAILED | T28: 5 Star Review | V28: EFTPOS | W28: CASH | X28: Payment Plan
B29: COMPLETED & PAID JOBS
B30: 1 | C30: 45890 | D30: 72507 | E30: Keilor East | F30: 681 | I30: =F30-G30-H30 -> 681 | J30: Card | K30: 1 | L30: 0 | M30: 1 | N30: 1 | O30: 1 | P30: 1 | Q30: 1 | R30: 1 | S30: 0 | U30: 21 Aug - 1hr O/T More Than Comm'ns | V30: 749.1
F31: =SUM(F30) -> 681 | G31: =SUM(G30) -> 0 | H31: =SUM(H30) -> 0 | I31: =SUM(I30) -> 681 | K31: =COUNT(K30:K30) -> 1 | L31: =COUNT(L30:L30) -> 1 | M31: =COUNT(M30:M30) -> 1 | N31: =COUNT(N30:N30) -> 1 | O31: =COUNT(O30:O30) -> 1 | P31: =COUNT(P30:P30) -> 1 | Q31: =COUNT(Q30:Q30) -> 1 | R31: =COUNT(R30:R30) -> 1 | S31: =COUNT(S30:S30) -> 1
K32: =SUM(K30:K30) -> 1 | L32: =SUM(L30:L30) -> 0 | M32: =SUM(M30:M30) -> 1 | N32: =SUM(N30:N30) -> 1 | O32: =SUM(O30:O30) -> 1 | P32: =SUM(P30:P30) -> 1 | Q32: =SUM(Q30:Q30) -> 1 | R32: =SUM(R30:R30) -> 1 | S32: =SUM(S30:S30) -> 0
B34: CURRENT JOBS COMPLETED (AWAITING PAYMENT)
B35: 1 | C35: 45890 | D35: 72546/72507 | E35: Keilor East | F35: 4112 | G35: =39.7+(847.9+27.43+26.8)+300 -> 1241.83 | I35: =F35-G35-H35 -> 2870.17 | J35: Card/EFT | K35: 1 | L35: 0 | M35: 1 | N35: 1 | O35: 1 | P35: 1 | Q35: 1 | R35: 1 | S35: 0 | U35: 21 Aug - Deduct 1hr O/T; 22/8-WIP by Matthew | V35: =450+3000 -> 3450
F36: =SUM(F35) -> 4112 | G36: =SUM(G35) -> 1241.83 | H36: =SUM(H35) -> 0 | I36: =SUM(I35) -> 2870.17
B38: UNSUCCESSFUL JOBS
B39: 1 | C39: 45888 | D39: 72430 | E39: Avondale Heights | F39: 775 | G39: 39.7 | I39: =F39-G39-H39 -> 735.3 | J39: N/A | K39: 1 | N39: 1 | Q39: 1 | R39: 1 | S39: 1
B40: =B39+1 -> 2 | C40: 45889 | D40: 72438 | E40: Cairnlea | F40: 8641 | G40: 39.7 | I40: =F40-G40-H40 -> 8601.3 | J40: N/A | K40: 1 | N40: 1 | Q40: 1 | R40: 1 | S40: 1
B41: =B40+1 -> 3 | C41: 45889 | D41: 72451 | E41: Saint Albans | F41: 7753 | G41: 39.7 | I41: =F41-G41-H41 -> 7713.3 | J41: N/A | K41: 1 | N41: 1 | Q41: 1 | R41: 1 | S41: 1
B42: =B41+1 -> 4 | C42: 45889 | D42: 72437 | E42: Truganina | F42: 7753 | G42: 39.7 | I42: =F42-G42-H42 -> 7713.3 | J42: N/A | K42: 1 | N42: 1 | Q42: 1 | R42: 1 | S42: 1
B43: =B42+1 -> 5 | C43: 45891 | D43: 72538 | E43: Point Cook | F43: 1053 | G43: 39.7 | I43: =F43-G43-H43 -> 1013.3 | J43: N/A | K43: 1 | N43: 1 | Q43: 1 | R43: 1 | S43: 1
B44: =B43+1 -> 6 | C44: 45891 | D44: 72548 | E44: Burwood | F44: 0 | I44: =F44-G44-H44 -> 0 | J44: Quote | U44: 22/08 - As per Bradley's note - "Job was a call back, other toilet is fine." - No initial jobs were found for this same customer
F45: =SUM(F39:F44) -> 25975 | G45: =SUM(G39:G44) -> 198.5 | H45: =SUM(H39:H44) -> 0 | I45: =SUM(I39:I44) -> 25776.5
T46: =SUM(T30:T45) -> 0 | V46: =SUM(V30:V45) -> 4199.1 | W46: =SUM(W30:W45) -> 0 | X46: =SUM(X30:X45) -> 0
B49: WEEKLY COMMISSION | F49: WEEK ENDING | G49: 45900
K50: PHOTOS | N50: QUOTE | Q50: INVOICE
B51: BOOKED JOBS | C51: =C52+C53 -> 28 | E51: WEEKLY TARGET | K51: BEFORE | L51: AFTER | M51: RECEIPT | N51: DESCRIPTION | O51: SIGNED | P51: EMAILED | Q51: DESCRIPTION | R51: SIGNED | S51: EMAILED | T51: 5 Star Review
B52: SUCCESSFUL | C52: =P59 -> 14 | E52: Tier 1 | F52: 0.05 | J52: TAKEN | K52: =K91 -> 14 | L52: =L91 -> 13 | M52: =M91 -> 14 | N52: =N91 -> 14 | O52: =O91 -> 14 | P52: =P91 -> 13 | Q52: =Q91 -> 14 | R52: =R91 -> 14 | S52: =S91 -> 8 | T52: =T113 -> 5
B53: UNSUCCESSFUL | C53: =P60 -> 14 | J53: % | K53: =K91/K90 -> 1 | L53: =L91/L90 -> 0.92857143 | M53: =M91/M90 -> 1 | N53: =N91/N90 -> 1 | O53: =O91/O90 -> 1 | P53: =P91/P90 -> 0.92857143 | Q53: =Q91/Q90 -> 1 | R53: =R91/R90 -> 1 | S53: =S91/S90 -> 0.57142857 | U53: M8 Notes
B54: SUCESSFUL (%) | C54: =P61 -> 0.5
F55: ACTUAL | G55: POTENTIAL | H55: Exc. SUPER
B56: AVERAGE SALE | C56: =P62 -> 1362.9186 | E56: NET PROFIT | F56: =P58 -> 19080.86 | G56: =I90 -> 19080.86 | K56: DAILY NET PROFIT | R56: WEEKDAY | S56: WEEKEND
E57: UNLOCKED | F57: =F52 -> 0.05 | K57: MON | L57: TUE | M57: WED | N57: THU | O57: FRI | P57: Total | Q57: SAT | R57: Awaiting Payment | S57: Awaiting Payment
E58: COMMISSION - PAY OUT | F58: =(F56+F65-I78-I80)*F57 -> 876.8255 | G58: $- | H58: =F58/1.12 -> 782.87991 | K58: =I77+I78+I79+I80+I81+I76 -> 5781.5 | L58: 0 | M58: =I82+I83 -> 3966.4 | N58: =I84+I85+I86+I87 -> 5469.03 | O58: =I88+I89 -> 3863.93 | P58: =SUM(K58:O58) -> 19080.86 | Q58: 0 | R58: 0 | S58: 0
E59: EMERGENCY | F59: =Q58 -> 0 | G59: $- | J59: Successful | K59: 6 | L59: 0 | M59: 2 | N59: 4 | O59: 2 | P59: =SUM(K59:O59) -> 14
E60: EMERGENCY - PAY OUT | F60: =F59*0.25 -> 0 | G60: $- | H60: =F60/1.12 -> 0 | J60: Unsuccessful | K60: 4 | L60: 0 | M60: 4 | N60: 1 | O60: 5 | P60: =SUM(K60:O60) -> 14
E61: PREV. WEEK | G61: $- | J61: Success rate | K61: =K59/(K59+K60) -> 0.6 | L61: =L59/(L59+L60) -> #DIV/0! | M61: =M59/(M59+M60) -> 0.33333333 | N61: =N59/(N59+N60) -> 0.8 | O61: =O59/(O59+O60) -> 0.28571429 | P61: =P59/(P59+P60) -> 0.5 | Q61: =Q59/(Q59+Q60) -> #DIV/0!
E62: PREV. WEEK - PAY OUT | F62: =F61*0.05 -> 0 | G62: $- | H62: =F62/1.12 -> 0 | J62: Avg sale | K62: =K58/K59 -> 963.58333 | L62: =L58/L59 -> #DIV/0! | M62: =M58/M59 -> 1983.2 | N62: =N58/N59 -> 1367.2575 | O62: =O58/O59 -> 1931.965 | P62: =P58/P59 -> 1362.9186 | Q62: =Q58/Q59 -> #DIV/0!
E63: 5 Star Review | F63: =5*50 -> 250 | H63: =F63/1.12 -> 223.21429
E64: 5 Star Notes | F64: =T53 -> 0 | K64: Managment Summary - SALES ONLY - COLUMN F | R64: WEEKDAY | S64: WEEKEND
E65: 27/8 - Bunnings - 6249/01317463 - Job-NA (1112) | F65: -189.05 | K65: MON | L65: TUE | M65: WED | N65: THU | O65: FRI | P65: Total | Q65: SAT | R65: Awaiting Payment | S65: Awaiting Payment
K66: =F77+F78+F79+F80+F81+F76 -> 5980 | L66: 0 | M66: =F82+F83 -> 5814 | N66: =F84+F85+F86+F87 -> 7291.18 | O66: =F88+F89 -> 4042 | P66: =SUM(K66:O66) -> 23127.18 | Q66: 0 | R66: 0 | S66: 0
J67: Successful | K67: =K59 -> 6 | L67: =L59 -> 0 | M67: =M59 -> 2 | N67: =N59 -> 4 | O67: =O59 -> 2 | P67: =P59 -> 14 | Q67: =Q59 -> 0
J68: Unsuccessful | K68: =K60 -> 4 | L68: =L60 -> 0 | M68: =M60 -> 4 | N68: =N60 -> 1 | O68: =O60 -> 5 | P68: =P60 -> 14 | Q68: =Q60 -> 0
J69: Success rate | K69: =K67/(K67+K68) -> 0.6 | L69: =L67/(L67+L68) -> #DIV/0! | M69: =M67/(M67+M68) -> 0.33333333 | N69: =N67/(N67+N68) -> 0.8 | O69: =O67/(O67+O68) -> 0.28571429 | P69: =P67/(P67+P68) -> 0.5 | Q69: =Q67/(Q67+Q68) -> #DIV/0!
J70: Avg sale | K70: =K66/K67 -> 996.66667 | L70: =L66/L67 -> #DIV/0! | M70: =M66/M67 -> 2907 | N70: =N66/N67 -> 1822.795 | O70: =O66/O67 -> 2021 | P70: =P66/P67 -> 1651.9414 | Q70: =Q66/Q67 -> #DIV/0!
B73: JOB DETAILS | F73: JOB AMOUNT | K73: PHOTOS | N73: QUOTE | Q73: INVOICE | U73: NOTES
B74: JOB STATUS | C74: DATE | D74: JOB # | E74: SUBURB | F74: AMOUNT EXC. GST | G74: MATERIALS | H74: Merchant Fees | I74: NET PROFIT | J74: PAID | K74: BEFORE | L74: AFTER | M74: RECEIPT | N74: DESCRIPTION | O74: SIGNED | P74: EMAILED | Q74: DESCRIPTION | R74: SIGNED | S74: EMAILED | T74: 5 Star Review | V74: EFTPOS | W74: CASH | X74: Payment Plan
B75: COMPLETED & PAID JOBS
B76: 1 | C76: 45894 | D76: 72519 | E76: Malvern | F76: 1513 | G76: 39.7 | I76: =F76-G76-H76 -> 1473.3 | J76: EFT | K76: 1 | L76: 1 | M76: 1 | N76: 1 | O76: 1 | P76: 1 | Q76: 1 | R76: 1 | S76: 1 | V76: 1664.3
B77: =B76+1 -> 2 | C77: 45894 | D77: 72582 | E77: Toorak | F77: 1035 | G77: 39.7 | I77: =F77-G77-H77 -> 995.3 | J77: Card | K77: 1 | L77: 1 | M77: 1 | N77: 1 | O77: 1 | P77: 1 | Q77: 1 | R77: 1 | S77: 0 | V77: 1138.5
A78: Paid Dispute | B78: =B77+1 -> 3 | C78: 45894 | D78: 72583 | E78: South Yarra | F78: =814-100 -> 714 | G78: 39.7 | I78: =F78-G78-H78 -> 674.3 | J78: Card | K78: 1 | L78: 1 | M78: 1 | N78: 1 | O78: 1 | P78: 1 | Q78: 1 | R78: 1 | S78: 1 | T78: 1 | V78: 895.4
B79: =B78+1 -> 4 | C79: 45894 | D79: 72615 | E79: Abbotford | F79: 861 | G79: 39.7 | I79: =F79-G79-H79 -> 821.3 | J79: Card | K79: 1 | L79: 1 | M79: 1 | N79: 1 | O79: 1 | P79: 1 | Q79: 1 | R79: 1 | S79: 0 | T79: 1 | U79: 25 Aug - Deduct 1hr O/T | V79: 947.1
B80: =B79+1 -> 5 | C80: 45894 | D80: 72588 | E80: Spotswood | F80: 681 | I80: =F80-G80-H80 -> 681 | J80: Card | K80: 1 | L80: 0 | M80: 1 | N80: 1 | O80: 1 | P80: 1 | Q80: 1 | R80: 1 | S80: 0 | U80: 25 Aug - 1.25hrs O/T More Than Comm'ns | V80: 749.1
B81: =B80+1 -> 6 | C81: 45894 | D81: 72633 | E81: Spotswood | F81: 1176 | G81: 39.7 | I81: =F81-G81-H81 -> 1136.3 | J81: Card | K81: 1 | L81: 1 | M81: 1 | N81: 1 | O81: 1 | P81: 1 | Q81: 1 | R81: 1 | S81: 1 | V81: 1293.6
B82: =B81+1 -> 7 | C82: 45896 | D82: 72669 | E82: Point Cook | F82: 681 | I82: =F82-G82-H82 -> 681 | J82: EFT | K82: 1 | L82: 1 | M82: 1 | N82: 1 | O82: 1 | P82: 1 | Q82: 1 | R82: 1 | S82: 1 | T82: 1 | V82: 749.1
B83: =B82+1 -> 8 | C83: 45896 | D83: 72713/72685/87297551 | E83: Kingsville | F83: 5133 | G83: =39.7+(1807.9) -> 1847.6 | I83: =F83-G83-H83 -> 3285.4 | J83: EFT | K83: 1 | L83: 1 | M83: 1 | N83: 1 | O83: 1 | P83: 0 | Q83: 1 | R83: 1 | S83: 0 | U83: 28/7-Job completed by Tolga by performing temp check;27/8-WIP by Bradley & Mathew H | V83: 5646.3
B84: =B83+1 -> 9 | C84: 45897 | D84: 72736 | E84: West Footscray | F84: 681 | I84: =F84-G84-H84 -> 681 | J84: Card | K84: 1 | L84: 1 | M84: 1 | N84: 1 | O84: 1 | P84: 1 | Q84: 1 | R84: 1 | S84: 1 | V84: 749.1
B85: =B84+1 -> 10 | C85: 45897 | D85: 72744 | E85: Hawthorn | F85: 1681 | G85: =39.7 -> 39.7 | I85: =F85-G85-H85 -> 1641.3 | J85: Card | K85: 1 | L85: 1 | M85: 1 | N85: 1 | O85: 1 | P85: 1 | Q85: 1 | R85: 1 | S85: 0 | V85: 1849.1
B86: =B85+1 -> 11 | C86: 45897 | D86: 72751 | E86: Clifton Hill | F86: 1261 | G86: 39.7 | I86: =F86-G86-H86 -> 1221.3 | J86: EFT | K86: 1 | L86: 1 | M86: 1 | N86: 1 | O86: 1 | P86: 1 | Q86: 1 | R86: 1 | S86: 1 | T86: 1 | U86: 28 Aug - Deduct 15mins O/T | V86: 1387.1
B87: =B86+1 -> 12 | C87: 45897 | D87: 72754 | E87: West Melbourne | F87: 3668.18 | G87: =39.7+(1453.05)+250 -> 1742.75 | I87: =F87-G87-H87 -> 1925.43 | J87: Card | K87: 1 | L87: 1 | M87: 1 | N87: 1 | O87: 1 | P87: 1 | Q87: 1 | R87: 1 | S87: 1 | U87: 28 Aug - Deduct 45mins O/T; 29/8-Customer satisfaction discount of $1564.82 provided-Job completed by Jack M & WIP by Bradley and Riley | V87: =2000+2035 -> 4035
B88: =B87+1 -> 13 | C88: 45898 | D88: 72792 | E88: Burwood | F88: 1513 | G88: =39.7 -> 39.7 | I88: =F88-G88-H88 -> 1473.3 | J88: Card | K88: 1 | L88: 1 | M88: 1 | N88: 1 | O88: 1 | P88: 1 | Q88: 1 | R88: 1 | S88: 1 | V88: 1664.3
B89: =B88+1 -> 14 | C89: 45898 | D89: 72799/72792/87341628 | E89: Burwood | F89: 2529 | G89: =39.7+(98.67) -> 138.37 | I89: =F89-G89-H89 -> 2390.63 | J89: Card | K89: 1 | L89: 1 | M89: 1 | N89: 1 | O89: 1 | P89: 1 | Q89: 1 | R89: 1 | S89: 0 | V89: =300+2481.9 -> 2781.9
F90: =SUM(F76:F89) -> 23127.18 | G90: =SUM(G76:G89) -> 4046.32 | H90: =SUM(H76:H89) -> 0 | I90: =SUM(I76:I89) -> 19080.86 | K90: =COUNT(K76:K89) -> 14 | L90: =COUNT(L76:L89) -> 14 | M90: =COUNT(M76:M89) -> 14 | N90: =COUNT(N76:N89) -> 14 | O90: =COUNT(O76:O89) -> 14 | P90: =COUNT(P76:P89) -> 14 | Q90: =COUNT(Q76:Q89) -> 14 | R90: =COUNT(R76:R89) -> 14 | S90: =COUNT(S76:S89) -> 14
K91: =SUM(K76:K89) -> 14 | L91: =SUM(L76:L89) -> 13 | M91: =SUM(M76:M89) -> 14 | N91: =SUM(N76:N89) -> 14 | O91: =SUM(O76:O89) -> 14 | P91: =SUM(P76:P89) -> 13 | Q91: =SUM(Q76:Q89) -> 14 | R91: =SUM(R76:R89) -> 14 | S91: =SUM(S76:S89) -> 8
B93: PREVIOUS JOBS COMPLETED (AWAITING PAYMENT) - Modoras Team Please do ADD to THIS SECTION or AMEND/TOUCH
B94: 1 | C94: 45890 | D94: 72546/72507 | E94: Keilor East | F94: 4112 | G94: =39.7+(847.9+27.43+26.8)+300 -> 1241.83 | I94: =F94-G94-H94 -> 2870.17 | J94: Card/EFT | K94: 1 | L94: 0 | M94: 1 | N94: 1 | O94: 1 | P94: 1 | Q94: 1 | R94: 1 | S94: 0 | U94: 21 Aug - Deduct 1hr O/T; 22/8-WIP by Matthew
F95: =SUM(F94) -> 4112 | G95: =SUM(G94) -> 1241.83 | H95: =SUM(H94) -> 0 | I95: =SUM(I94) -> 2870.17
B97: UNSUCCESSFUL JOBS
B98: 1 | C98: 45894 | D98: 72586 | E98: Malvern | F98: 4176 | G98: 39.7 | I98: =F98-G98-H98 -> 4136.3 | J98: N/A | K98: 1 | N98: 1 | Q98: 1 | R98: 1 | S98: 1
A99: 45895 | B99: =B98+1 -> 2 | C99: 45894 | D99: 72611 | E99: South Melbourne | F99: 0 | G99: 0 | I99: =F99-G99-H99 -> 0 | J99: Card | K99: 1 | M99: 1 | Q99: 1 | R99: 1 | S99: 1 | U99: 26 Aug - Refund - $203.50 | V99: 203.5
B100: =B99+1 -> 3 | C100: 45894 | D100: 72623/87268732 | E100: West Footscray | F100: 5233 | G100: 39.7 | I100: =F100-G100-H100 -> 5193.3 | J100: N/A | K100: 1 | N100: 1 | Q100: 1 | R100: 1 | S100: 1
B101: =B100+1 -> 4 | C101: 45894 | D101: 72623/87268668 | E101: West Footscray | F101: 6133 | G101: 39.7 | I101: =F101-G101-H101 -> 6093.3 | J101: N/A | K101: 1 | N101: 1 | Q101: 1 | R101: 1 | S101: 1
B102: =B101+1 -> 5 | C102: 45896 | D102: 72655 | E102: Port Melbourne | F102: 1861 | G102: 39.7 | I102: =F102-G102-H102 -> 1821.3 | J102: Card | K102: 1 | M102: 1 | N102: 1 | Q102: 1 | R102: 1 | V102: 93.5
B103: =B102+1 -> 6 | C103: 45896 | D103: 72669/87295090 | E103: Point Cook | F103: 8614 | G103: 39.7 | I103: =F103-G103-H103 -> 8574.3 | J103: N/A | K103: 1 | N103: 1
B104: =B103+1 -> 7 | C104: 45896 | D104: 72670 | E104: Point Cook | F104: 433 | I104: =F104-G104-H104 -> 433 | J104: N/A | K104: 1 | N104: 1 | Q104: 1 | R104: 1 | S104: 1
B105: =B104+1 -> 8 | C105: 45896 | D105: 72685 | E105: Kingsville | F105: 681 | I105: =F105-G105-H105 -> 681 | K105: 1 | O105: 1 | U105: 27/8-WIP by Mathew H & Bradley
B106: =B105+1 -> 9 | C106: 45897 | D106: 72705 | E106: Wyndham Vale | F106: 2176 | G106: 39.7 | I106: =F106-G106-H106 -> 2136.3 | J106: N/A | K106: 1 | N106: 1 | Q106: 1 | R106: 1 | S106: 1
B107: =B106+1 -> 10 | C107: 45898 | D107: 72776 | E107: Toorak | F107: 7393 | G107: 39.7 | I107: =F107-G107-H107 -> 7353.3 | J107: N/A | K107: 1 | N107: 1 | Q107: 1 | R107: 1 | S107: 1
B108: =B107+1 -> 11 | C108: 45898 | D108: 72786 | E108: Malvern East | F108: 5233 | G108: 39.7 | I108: =F108-G108-H108 -> 5193.3 | J108: N/A | K108: 1 | N108: 1
B109: =B108+1 -> 12 | C109: 45898 | D109: 72771 | E109: Burwood | F109: 2814 | G109: =39.7 -> 39.7 | I109: =F109-G109-H109 -> 2774.3 | J109: Card | K109: 1 | M109: 1 | N109: 1 | O109: 1 | P109: 1 | T109: 1 | U109: 1/9-Refunded $235 to customer & retained COF-Customer wants to cancel | V109: =300 -> 300
B110: =B109+1 -> 13 | C110: 45898 | D110: 72760 | E110: Doncaster East | F110: 18161 | G110: 39.7 | I110: =F110-G110-H110 -> 18121.3 | J110: N/A | K110: 1 | N110: 1 | Q110: 1 | R110: 1 | S110: 1
B111: =B110+1 -> 14 | C111: 45898 | D111: 72797 | E111: Doncaster | F111: 1781 | G111: 39.7 | I111: =F111-G111-H111 -> 1741.3 | J111: N/A | K111: 1 | N111: 1 | Q111: 1 | R111: 1 | S111: 1
F112: =SUM(F98:F111) -> 64689 | G112: =SUM(G98:G111) -> 436.7 | H112: =SUM(H98:H111) -> 0 | I112: =SUM(I98:I111) -> 64252.3
...

Sheet Daniel B
B3: WEEKLY COMMISSION | F3: WEEK ENDING | G3: 45970
K4: PHOTOS | N4: QUOTE | Q4: INVOICE
B5: BOOKED JOBS | C5: =C6+C7 -> 0 | E5: WEEKLY TARGET | K5: BEFORE | L5: AFTER | M5: RECEIPT | N5: DESCRIPTION | O5: SIGNED | P5: EMAILED | Q5: DESCRIPTION | R5: SIGNED | S5: EMAILED | T5: 5 Star Review
B6: SUCCESSFUL | C6: =P13 -> 0 | E6: Tier 1 | F6: 0.05 | J6: TAKEN | K6: =K32 -> 0 | L6: =L32 -> 0 | M6: =M32 -> 0 | N6: =N32 -> 0 | O6: =O32 -> 0 | P6: =P32 -> 0 | Q6: =Q32 -> 0 | R6: =R32 -> 0 | S6: =S32 -> 0 | T6: =T33 -> 0
B7: UNSUCCESSFUL | C7: =P14 -> 0 | J7: % | K7: =K32/K31 -> #DIV/0! | L7: =L32/L31 -> #DIV/0! | M7: =M32/M31 -> #DIV/0! | N7: =N32/N31 -> #DIV/0! | O7: =O32/O31 -> #DIV/0! | P7: =P32/P31 -> #DIV/0! | Q7: =Q32/Q31 -> #DIV/0! | R7: =R32/R31 -> #DIV/0! | S7: =S32/S31 -> #DIV/0! | U7: M8 Notes
B8: SUCESSFUL (%) | C8: =P15 -> #DIV/0!
F9: ACTUAL | G9: POTENTIAL | H9: Exc. SUPER
B10: AVERAGE SALE | C10: =P16 -> #DIV/0! | E10: NET PROFIT | F10: =P12 -> 0 | G10: =I31 -> 0 | K10: DAILY NET PROFIT | R10: WEEKDAY | S10: WEEKEND
E11: UNLOCKED | F11: =F6 -> 0.05 | K11: MON | L11: TUE | M11: WED | N11: THU | O11: FRI | P11: Total | Q11: SAT | R11: Awaiting Payment | S11: Awaiting Payment
E12: COMMISSION - PAY OUT | F12: =F10*F11 -> 0 | G12: $- | H12: =F12/1.12 -> 0 | P12: =SUM(K12:O12) -> 0 | Q12: 0 | R12: 0 | S12: 0
E13: EMERGENCY | F13: =Q12 -> 0 | G13: $- | J13: Successful | P13: =SUM(K13:O13) -> 0
E14: EMERGENCY - PAY OUT | F14: =F13*0.25 -> 0 | G14: $- | H14: =F14/1.12 -> 0 | J14: Unsuccessful | P14: =SUM(K14:O14) -> 0
E15: PREV. WEEK | G15: $- | J15: Success rate | K15: =K13/(K13+K14) -> #DIV/0! | L15: =L13/(L13+L14) -> #DIV/0! | M15: =M13/(M13+M14) -> #DIV/0! | N15: =N13/(N13+N14) -> #DIV/0! | O15: =O13/(O13+O14) -> #DIV/0! | P15: =P13/(P13+P14) -> #DIV/0! | Q15: =Q13/(Q13+Q14) -> #DIV/0!
E16: PREV. WEEK - PAY OUT | F16: =F15*0.05 -> 0 | G16: $- | H16: =F16/1.12 -> 0 | J16: Avg sale | K16: =K12/K13 -> #DIV/0! | L16: =L12/L13 -> #DIV/0! | M16: =M12/M13 -> #DIV/0! | N16: =N12/N13 -> #DIV/0! | O16: =O12/O13 -> #DIV/0! | P16: =P12/P13 -> #DIV/0! | Q16: =Q12/Q13 -> #DIV/0!
E17: 5 Star Review | H17: =F17/1.12 -> 0
E18: 5 Star Notes | F18: =T7 -> 0 | K18: Managment Summary - SALES ONLY - COLUMN F | R18: WEEKDAY | S18: WEEKEND
K19: MON | L19: TUE | M19: WED | N19: THU | O19: FRI | P19: Total | Q19: SAT | R19: Awaiting Payment | S19: Awaiting Payment
P20: =SUM(K20:O20) -> 0 | Q20: 0 | R20: 0 | S20: 0
J21: Successful | K21: =K13 -> 0 | L21: =L13 -> 0 | M21: =M13 -> 0 | N21: =N13 -> 0 | O21: =O13 -> 0 | P21: =P13 -> 0 | Q21: =Q13 -> 0
J22: Unsuccessful | K22: =K14 -> 0 | L22: =L14 -> 0 | M22: =M14 -> 0 | N22: =N14 -> 0 | O22: =O14 -> 0 | P22: =P14 -> 0 | Q22: =Q14 -> 0
J23: Success rate | K23: =K21/(K21+K22) -> #DIV/0! | L23: =L21/(L21+L22) -> #DIV/0! | M23: =M21/(M21+M22) -> #DIV/0! | N23: =N21/(N21+N22) -> #DIV/0! | O23: =O21/(O21+O22) -> #DIV/0! | P23: =P21/(P21+P22) -> #DIV/0! | Q23: =Q21/(Q21+Q22) -> #DIV/0!
J24: Avg sale | K24: =K20/K21 -> #DIV/0! | L24: =L20/L21 -> #DIV/0! | M24: =M20/M21 -> #DIV/0! | N24: =N20/N21 -> #DIV/0! | O24: =O20/O21 -> #DIV/0! | P24: =P20/P21 -> #DIV/0! | Q24: =Q20/Q21 -> #DIV/0!
B27: JOB DETAILS | F27: JOB AMOUNT | K27: PHOTOS | N27: QUOTE | Q27: INVOICE | U27: NOTES
B28: JOB STATUS | C28: DATE | D28: JOB # | E28: SUBURB | F28: AMOUNT EXC. GST | G28: MATERIALS | H28: Merchant Fees | I28: NET PROFIT | J28: PAID | K28: BEFORE | L28: AFTER | M28: RECEIPT | N28: DESCRIPTION | O28: SIGNED | P28: EMAILED | Q28: DESCRIPTION | R28: SIGNED | S28: EMAILED | T28: 5 Star Review | V28: EFTPOS | W28: CASH | X28: Payment Plan
B29: COMPLETED & PAID JOBS
B30: 1 | I30: =F30-G30-H30 -> 0
F31: =SUM(F30:F30) -> 0 | G31: =SUM(G30:G30) -> 0 | H31: =SUM(H30:H30) -> 0 | I31: =SUM(I30:I30) -> 0 | K31: =COUNT(K30:K30) -> 0 | L31: =COUNT(L30:L30) -> 0 | M31: =COUNT(M30:M30) -> 0 | N31: =COUNT(N30:N30) -> 0 | O31: =COUNT(O30:O30) -> 0 | P31: =COUNT(P30:P30) -> 0 | Q31: =COUNT(Q30:Q30) -> 0 | R31: =COUNT(R30:R30) -> 0 | S31: =COUNT(S30:S30) -> 0
K32: =SUM(K30:K30) -> 0 | L32: =SUM(L30:L30) -> 0 | M32: =SUM(M30:M30) -> 0 | N32: =SUM(N30:N30) -> 0 | O32: =SUM(O30:O30) -> 0 | P32: =SUM(P30:P30) -> 0 | Q32: =SUM(Q30:Q30) -> 0 | R32: =SUM(R30:R30) -> 0 | S32: =SUM(S30:S30) -> 0
T33: =SUM(T30:T32) -> 0 | V33: =SUM(V30:V32) -> 0 | W33: =SUM(W30:W32) -> 0 | X33: =SUM(X30:X32) -> 0

Sheet Elliot
B2: WEEKLY COMMISSION | F2: WEEK ENDING | G2: 45858
K3: PHOTOS | N3: QUOTE | Q3: INVOICE
B4: BOOKED JOBS | C4: =C5+C6 -> 1 | E4: WEEKLY TARGET | K4: BEFORE | L4: AFTER | M4: RECEIPT | N4: DESCRIPTION | O4: SIGNED | P4: EMAILED | Q4: DESCRIPTION | R4: SIGNED | S4: EMAILED | T4: 5 Star Review
B5: SUCCESSFUL | C5: =P12 -> 1 | E5: Tier 1 | F5: 0.05 | J5: TAKEN | K5: =K31 -> 1 | L5: =L31 -> 1 | M5: =M31 -> 1 | N5: =N31 -> 1 | O5: =O31 -> 1 | P5: =P31 -> 1 | Q5: =Q31 -> 1 | R5: =R31 -> 1 | S5: =S31 -> 1 | T5: =T32 -> 1 | U5: 1X Heath
B6: UNSUCCESSFUL | C6: =P13 -> 0 | J6: % | K6: =K31/K30 -> 1 | L6: =L31/L30 -> 1 | M6: =M31/M30 -> 1 | N6: =N31/N30 -> 1 | O6: =O31/O30 -> 1 | P6: =P31/P30 -> 1 | Q6: =Q31/Q30 -> 1 | R6: =R31/R30 -> 1 | S6: =S31/S30 -> 1 | U6: M8 Notes
B7: SUCESSFUL (%) | C7: =P14 -> 1
F8: ACTUAL | G8: POTENTIAL | H8: Exc. SUPER
B9: AVERAGE SALE | C9: =P15 -> 1221.3 | E9: NET PROFIT | F9: =P11 -> 1221.3 | G9: =I30 -> 1221.3 | K9: DAILY NET PROFIT | R9: WEEKDAY | S9: WEEKEND
E10: UNLOCKED | F10: =F5 -> 0.05 | K10: MON | L10: TUE | M10: WED | N10: THU | O10: FRI | P10: Total | Q10: SAT | R10: Awaiting Payment | S10: Awaiting Payment
E11: COMMISSION - PAY OUT | F11: =F9*F10 -> 61.065 | G11: $- | H11: =F11/1.12 -> 54.522321 | N11: =I29 -> 1221.3 | P11: =SUM(K11:O11) -> 1221.3 | Q11: 0 | R11: =0 -> 0 | S11: 0
E12: EMERGENCY | F12: =Q11 -> 0 | G12: $- | J12: Successful | N12: 1 | P12: =SUM(K12:O12) -> 1
E13: EMERGENCY - PAY OUT | F13: =F12*0.25 -> 0 | G13: $- | H13: =F13/1.12 -> 0 | J13: Unsuccessful | N13: 0 | P13: =SUM(K13:O13) -> 0
E14: PREV. WEEK | G14: $- | J14: Success rate | K14: =K12/(K12+K13) -> #DIV/0! | L14: =L12/(L12+L13) -> #DIV/0! | M14: =M12/(M12+M13) -> #DIV/0! | N14: =N12/(N12+N13) -> 1 | O14: =O12/(O12+O13) -> #DIV/0! | P14: =P12/(P12+P13) -> 1 | Q14: =Q12/(Q12+Q13) -> #DIV/0!
E15: PREV. WEEK - PAY OUT | F15: =F14*0.05 -> 0 | G15: $- | H15: =F15/1.12 -> 0 | J15: Avg sale | K15: =K11/K12 -> #DIV/0! | L15: =L11/L12 -> #DIV/0! | M15: =M11/M12 -> #DIV/0! | N15: =N11/N12 -> 1221.3 | O15: =O11/O12 -> #DIV/0! | P15: =P11/P12 -> 1221.3 | Q15: =Q11/Q12 -> #DIV/0!
E16: 5 Star Review | H16: =F16/1.12 -> 0
E17: 5 Star Notes | F17: =T6 -> 0 | K17: Managment Summary - SALES ONLY - COLUMN F | R17: WEEKDAY | S17: WEEKEND
K18: MON | L18: TUE | M18: WED | N18: THU | O18: FRI | P18: Total | Q18: SAT | R18: Awaiting Payment | S18: Awaiting Payment
N19: =F29 -> 1461 | O19: =Heath!F127 -> 481 | P19: =SUM(K19:O19) -> 1942 | Q19: 0 | R19: =0 -> 0 | S19: 0
J20: Successful | K20: =K12 -> 0 | L20: =L12 -> 0 | M20: =M12 -> 0 | N20: =N12 -> 1 | O20: =O12 -> 0 | P20: =P12 -> 1 | Q20: =Q12 -> 0
J21: Unsuccessful | K21: =K13 -> 0 | L21: =L13 -> 0 | M21: =M13 -> 0 | N21: =N13 -> 0 | O21: =O13 -> 0 | P21: =P13 -> 0 | Q21: =Q13 -> 0
J22: Success rate | K22: =K20/(K20+K21) -> #DIV/0! | L22: =L20/(L20+L21) -> #DIV/0! | M22: =M20/(M20+M21) -> #DIV/0! | N22: =N20/(N20+N21) -> 1 | O22: =O20/(O20+O21) -> #DIV/0! | P22: =P20/(P20+P21) -> 1 | Q22: =Q20/(Q20+Q21) -> #DIV/0!
J23: Avg sale | K23: =K19/K20 -> #DIV/0! | L23: =L19/L20 -> #DIV/0! | M23: =M19/M20 -> #DIV/0! | N23: =N19/N20 -> 1461 | O23: =O19/O20 -> #DIV/0! | P23: =P19/P20 -> 1942 | Q23: =Q19/Q20 -> #DIV/0!
B26: JOB DETAILS | F26: JOB AMOUNT | K26: PHOTOS | N26: QUOTE | Q26: INVOICE | U26: NOTES
B27: JOB STATUS | C27: DATE | D27: JOB # | E27: SUBURB | F27: AMOUNT EXC. GST | G27: MATERIALS | H27: Merchant Fees | I27: NET PROFIT | J27: PAID | K27: BEFORE | L27: AFTER | M27: RECEIPT | N27: DESCRIPTION | O27: SIGNED | P27: EMAILED | Q27: DESCRIPTION | R27: SIGNED | S27: EMAILED | T27: 5 Star Review | V27: EFTPOS | W27: CASH | X27: Payment Plan
B28: COMPLETED & PAID JOBS
B29: 1 | C29: 45855 | D29: 71475 | E29: Elwood | F29: 1461 | G29: =39.7+200 -> 239.7 | I29: =F29-G29-H29 -> 1221.3 | J29: Card | K29: 1 | L29: 1 | M29: 1 | N29: 1 | O29: 1 | P29: 1 | Q29: 1 | R29: 1 | S29: 1 | T29: 1 | U29: 17/07-WIP & Completed by Elliot, Heath | V29: =160.71+1446.39 -> 1607.1
F30: =SUM(F29) -> 1461 | G30: =SUM(G29) -> 239.7 | H30: =SUM(H29) -> 0 | I30: =SUM(I29) -> 1221.3 | K30: =COUNT(K29:K29) -> 1 | L30: =COUNT(L29:L29) -> 1 | M30: =COUNT(M29:M29) -> 1 | N30: =COUNT(N29:N29) -> 1 | O30: =COUNT(O29:O29) -> 1 | P30: =COUNT(P29:P29) -> 1 | Q30: =COUNT(Q29:Q29) -> 1 | R30: =COUNT(R29:R29) -> 1 | S30: =COUNT(S29:S29) -> 1
K31: =SUM(K29:K29) -> 1 | L31: =SUM(L29:L29) -> 1 | M31: =SUM(M29:M29) -> 1 | N31: =SUM(N29:N29) -> 1 | O31: =SUM(O29:O29) -> 1 | P31: =SUM(P29:P29) -> 1 | Q31: =SUM(Q29:Q29) -> 1 | R31: =SUM(R29:R29) -> 1 | S31: =SUM(S29:S29) -> 1
T32: =SUM(T29:T31) -> 1 | V32: =SUM(V29:V31) -> 1607.1 | W32: =SUM(W29:W31) -> 0 | X32: =SUM(X29:X31) -> 0
B35: WEEKLY COMMISSION | F35: WEEK ENDING | G35: 45865
K36: PHOTOS | N36: QUOTE | Q36: INVOICE
B37: BOOKED JOBS | C37: =C38+C39 -> 1 | E37: WEEKLY TARGET | K37: BEFORE | L37: AFTER | M37: RECEIPT | N37: DESCRIPTION | O37: SIGNED | P37: EMAILED | Q37: DESCRIPTION | R37: SIGNED | S37: EMAILED | T37: 5 Star Review
B38: SUCCESSFUL | C38: =P45 -> 1 | E38: Tier 1 | F38: 0.05 | J38: TAKEN | K38: =K64 -> 1 | L38: =L64 -> 1 | M38: =M64 -> 1 | N38: =N64 -> 1 | O38: =O64 -> 1 | P38: =P64 -> 1 | Q38: =Q64 -> 1 | R38: =R64 -> 1 | S38: =S64 -> 1 | T38: =T82 -> 0
B39: UNSUCCESSFUL | C39: =P46 -> 0 | J39: % | K39: =K64/K63 -> 1 | L39: =L64/L63 -> 1 | M39: =M64/M63 -> 1 | N39: =N64/N63 -> 1 | O39: =O64/O63 -> 1 | P39: =P64/P63 -> 1 | Q39: =Q64/Q63 -> 1 | R39: =R64/R63 -> 1 | S39: =S64/S63 -> 1 | U39: M8 Notes
B40: SUCESSFUL (%) | C40: =P47 -> 1
F41: ACTUAL | G41: POTENTIAL | H41: Exc. SUPER
B42: AVERAGE SALE | C42: =P48 -> 774.3 | E42: NET PROFIT | F42: =P44 -> 774.3 | G42: =I63 -> 774.3 | K42: DAILY NET PROFIT | R42: WEEKDAY | S42: WEEKEND
E43: UNLOCKED | F43: =F38 -> 0.05 | K43: MON | L43: TUE | M43: WED | N43: THU | O43: FRI | P43: Total | Q43: SAT | R43: Awaiting Payment | S43: Awaiting Payment
E44: COMMISSION - PAY OUT | F44: =F42*F43 -> 38.715 | G44: $- | H44: =F44/1.12 -> 34.566964 | K44: =I62 -> 774.3 | L44: 0 | M44: 0 | N44: 0 | O44: 0 | P44: =SUM(K44:O44) -> 774.3 | Q44: =I67+I68+I69+I70 -> 3599.6 | R44: 0 | S44: =0 -> 0
E45: EMERGENCY | F45: =Q44 -> 3599.6 | G45: $- | I45: O/T=10.75hrs | J45: Successful | K45: 1 | L45: 0 | M45: 0 | N45: 0 | O45: 0 | P45: =SUM(K45:O45) -> 1 | Q45: 4
E46: EMERGENCY - PAY OUT | F46: =(F45)*0.25 -> 899.9 | G46: $- | H46: =F46/1.12 -> 803.48214 | I46: =67.5*10.75 -> 725.625 | J46: Unsuccessful | K46: 0 | L46: 0 | M46: 0 | N46: 0 | O46: 0 | P46: =SUM(K46:O46) -> 0 | Q46: 7
E47: PREV. WEEK | G47: $- | J47: Success rate | K47: =K45/(K45+K46) -> 1 | L47: =L45/(L45+L46) -> #DIV/0! | M47: =M45/(M45+M46) -> #DIV/0! | N47: =N45/(N45+N46) -> #DIV/0! | O47: =O45/(O45+O46) -> #DIV/0! | P47: =P45/(P45+P46) -> 1 | Q47: =Q45/(Q45+Q46) -> 0.36363636
E48: PREV. WEEK - PAY OUT | F48: =F47*0.05 -> 0 | G48: $- | H48: =F48/1.12 -> 0 | J48: Avg sale | K48: =K44/K45 -> 774.3 | L48: =L44/L45 -> #DIV/0! | M48: =M44/M45 -> #DIV/0! | N48: =N44/N45 -> #DIV/0! | O48: =O44/O45 -> #DIV/0! | P48: =P44/P45 -> 774.3 | Q48: =Q44/Q45 -> 899.9
E49: 5 Star Review | F49: =3*50/2 -> 75 | H49: =F49/1.12 -> 66.964286
E50: 5 Star Notes | F50: =T39 -> 0 | K50: Managment Summary - SALES ONLY - COLUMN F | R50: WEEKDAY | S50: WEEKEND
K51: MON | L51: TUE | M51: WED | N51: THU | O51: FRI | P51: Total | Q51: SAT | R51: Awaiting Payment | S51: Awaiting Payment
K52: =F62 -> 814 | P52: =SUM(K52:O52) -> 814 | Q52: =F67+F68+F69+F70 -> 3679 | R52: 0 | S52: =0 -> 0
J53: Successful | K53: =K45 -> 1 | L53: =L45 -> 0 | M53: =M45 -> 0 | N53: =N45 -> 0 | O53: =O45 -> 0 | P53: =P45 -> 1 | Q53: =Q45 -> 4
J54: Unsuccessful | K54: =K46 -> 0 | L54: =L46 -> 0 | M54: =M46 -> 0 | N54: =N46 -> 0 | O54: =O46 -> 0 | P54: =P46 -> 0 | Q54: =Q46 -> 7
J55: Success rate | K55: =K53/(K53+K54) -> 1 | L55: =L53/(L53+L54) -> #DIV/0! | M55: =M53/(M53+M54) -> #DIV/0! | N55: =N53/(N53+N54) -> #DIV/0! | O55: =O53/(O53+O54) -> #DIV/0! | P55: =P53/(P53+P54) -> 1 | Q55: =Q53/(Q53+Q54) -> 0.36363636
J56: Avg sale | K56: =K52/K53 -> 814 | L56: =L52/L53 -> #DIV/0! | M56: =M52/M53 -> #DIV/0! | N56: =N52/N53 -> #DIV/0! | O56: =O52/O53 -> #DIV/0! | P56: =P52/P53 -> 814 | Q56: =Q52/Q53 -> 919.75
B59: JOB DETAILS | F59: JOB AMOUNT | K59: PHOTOS | N59: QUOTE | Q59: INVOICE | U59: NOTES
B60: JOB STATUS | C60: DATE | D60: JOB # | E60: SUBURB | F60: AMOUNT EXC. GST | G60: MATERIALS | H60: Merchant Fees | I60: NET PROFIT | J60: PAID | K60: BEFORE | L60: AFTER | M60: RECEIPT | N60: DESCRIPTION | O60: SIGNED | P60: EMAILED | Q60: DESCRIPTION | R60: SIGNED | S60: EMAILED | T60: 5 Star Review | V60: EFTPOS | W60: CASH | X60: Payment Plan
B61: COMPLETED & PAID JOBS
B62: 1 | C62: 45859 | D62: 71612 | E62: Avondale Heights | F62: 814 | G62: 39.7 | I62: =F62-G62-H62 -> 774.3 | J62: Card | K62: 1 | L62: 1 | M62: 1 | N62: 1 | O62: 1 | P62: 1 | Q62: 1 | R62: 1 | S62: 1 | U62: 21 Jul - Deduct 30mins O/T | V62: =89.54+805.86 -> 895.4
F63: =SUM(F62:F62) -> 814 | G63: =SUM(G62:G62) -> 39.7 | H63: =SUM(H62:H62) -> 0 | I63: =SUM(I62:I62) -> 774.3 | K63: =COUNT(K62:K62) -> 1 | L63: =COUNT(L62:L62) -> 1 | M63: =COUNT(M62:M62) -> 1 | N63: =COUNT(N62:N62) -> 1 | O63: =COUNT(O62:O62) -> 1 | P63: =COUNT(P62:P62) -> 1 | Q63: =COUNT(Q62:Q62) -> 1 | R63: =COUNT(R62:R62) -> 1 | S63: =COUNT(S62:S62) -> 1
K64: =SUM(K62:K62) -> 1 | L64: =SUM(L62:L62) -> 1 | M64: =SUM(M62:M62) -> 1 | N64: =SUM(N62:N62) -> 1 | O64: =SUM(O62:O62) -> 1 | P64: =SUM(P62:P62) -> 1 | Q64: =SUM(Q62:Q62) -> 1 | R64: =SUM(R62:R62) -> 1 | S64: =SUM(S62:S62) -> 1
B66: WEEKEND COMPLETED & PAID JOBS
B67: 1 | C67: 45864 | D67: 71781/86302383 | E67: Viewbank | F67: 1264 | G67: 39.7 | I67: =F67-G67-H67 -> 1224.3 | J67: Card | K67: 1 | L67: 0 | M67: 1 | N67: 1 | O67: 1 | P67: 1 | Q67: 1 | R67: 1 | S67: 1 | U67: 29/07-Customer wants finding on CCTV | V67: =93.5+129.6+1167.3 -> 1390.4
B68: =B67+1 -> 2 | C68: 45864 | D68: 71781/86305033 | E68: Viewbank | F68: 681 | I68: =F68-G68-H68 -> 681 | J68: Card | K68: 1 | L68: 1 | M68: 1 | N68: 1 | O68: 1 | P68: 1 | Q68: 1 | R68: 1 | S68: 1 | V68: 749.1
B69: =B68+1 -> 3 | C69: 45864 | D69: 71783 | E69: Ferntree Gully | F69: =766-85 -> 681 | I69: =F69-G69-H69 -> 681 | J69: Card | K69: 1 | L69: 1 | M69: 1 | N69: 1 | O69: 1 | P69: 1 | Q69: 1 | R69: 1 | S69: 1 | V69: =93.5+74.91+674.2 -> 842.61
B70: =B69+1 -> 4 | C70: 45864 | D70: 71785/86305840 | E70: Malvern | F70: =1138-85 -> 1053 | G70: 39.7 | I70: =F70-G70-H70 -> 1013.3 | J70: Card | K70: 1 | L70: 1 | M70: 1 | N70: 1 | O70: 1 | P70: 1 | Q70: 1 | R70: 1 | S70: 1 | V70: =93.5+115.83+1042.47 -> 1251.8
F71: =SUM(F67:F70) -> 3679 | G71: =SUM(G67:G70) -> 79.4 | H71: =SUM(H67:H70) -> 0 | I71: =SUM(I67:I70) -> 3599.6
B73: WEEKEND UNSUCCESSFUL JOBS
B74: 1 | C74: 45864 | D74: 71511/86302305 | E74: Canterburry | F74: 1138 | G74: 39.7 | I74: =F74-G74-H74 -> 1098.3 | J74: N/A | K74: 1
B75: =B74+1 -> 2 | C75: 45864 | D75: 71511/86302183 | E75: Canterburry | F75: 814 | G75: 39.7 | I75: =F75-G75-H75 -> 774.3 | J75: N/A | K75: 1
B76: =B75+1 -> 3 | C76: 45864 | D76: 71759 | E76: Pascoe Vale | F76: 814 | G76: 39.7 | I76: =F76-G76-H76 -> 774.3 | J76: N/A | K76: 1
B77: =B76+1 -> 4 | C77: 45864 | D77: 71949/71781/86299286 | E77: Viewbank | F77: 8641 | G77: 39.7 | I77: =F77-G77-H77 -> 8601.3 | J77: N/A | K77: 1
B78: =B77+1 -> 5 | C78: 45864 | D78: 71786 | E78: Eltham | F78: 1138 | G78: 39.7 | I78: =F78-G78-H78 -> 1098.3 | J78: N/A | K78: 1
B79: =B78+1 -> 6 | C79: 45864 | D79: 71783/86305807 | E79: Ferntree Gully | F79: 5814 | G79: 39.7 | I79: =F79-G79-H79 -> 5774.3 | J79: N/A
A80: 45870 | B80: =B79+1 -> 7 | C80: 45864 | D80: 71785/86305874 | E80: Malvern | F80: 12814 | G80: =39.7+1000 -> 1039.7 | I80: =F80-G80-H80 -> 11774.3 | J80: Card | K80: 1 | M80: 1 | N80: 1 | O80: 1 | U80: 1 Aug - Refund - $1,409.50; 26/07-Customer cancelled the job - Refund processed for $1409.5 | V80: 1409.5
F81: =SUM(F74:F80) -> 31173 | G81: =SUM(G74:G80) -> 1277.9 | H81: =SUM(H74:H80) -> 0 | I81: =SUM(I74:I80) -> 29895.1
T82: =SUM(T61:T81) -> 0 | V82: =SUM(V61:V81) -> 6538.81 | W82: =SUM(W61:W81) -> 0 | X82: =SUM(X61:X81) -> 0
B85: WEEKLY COMMISSION | F85: WEEK ENDING | G85: 45872
K86: PHOTOS | N86: QUOTE | Q86: INVOICE
B87: BOOKED JOBS | C87: =C88+C89 -> 3 | E87: WEEKLY TARGET | K87: BEFORE | L87: AFTER | M87: RECEIPT | N87: DESCRIPTION | O87: SIGNED | P87: EMAILED | Q87: DESCRIPTION | R87: SIGNED | S87: EMAILED | T87: 5 Star Review
B88: SUCCESSFUL | C88: =P95 -> 3 | E88: Tier 1 | F88: 0.05 | J88: TAKEN | K88: =K114 -> 0 | L88: =L114 -> 0 | M88: =M114 -> 0 | N88: =N114 -> 0 | O88: =O114 -> 0 | P88: =P114 -> 0 | Q88: =Q114 -> 0 | R88: =R114 -> 0 | S88: =S114 -> 0 | T88: =T121 -> 0
B89: UNSUCCESSFUL | C89: =P96 -> 0 | J89: % | K89: =K114/K113 -> #DIV/0! | L89: =L114/L113 -> #DIV/0! | M89: =M114/M113 -> #DIV/0! | N89: =N114/N113 -> #DIV/0! | O89: =O114/O113 -> #DIV/0! | P89: =P114/P113 -> #DIV/0! | Q89: =Q114/Q113 -> #DIV/0! | R89: =R114/R113 -> #DIV/0! | S89: =S114/S113 -> #DIV/0! | U89: M8 Notes
B90: SUCESSFUL (%) | C90: =P97 -> 1
F91: ACTUAL | G91: POTENTIAL | H91: Exc. SUPER
B92: AVERAGE SALE | C92: =P98 -> 3466.8767 | E92: NET PROFIT | F92: =P94 -> 10400.63 | G92: =I113+I120 -> 10400.63 | K92: DAILY NET PROFIT | R92: WEEKDAY | S92: WEEKEND
E93: UNLOCKED | F93: =F88 -> 0.05 | K93: MON | L93: TUE | M93: WED | N93: THU | O93: FRI | P93: Total | Q93: SAT | R93: Awaiting Payment | S93: Awaiting Payment
E94: COMMISSION - PAY OUT | F94: =(F92-I117-I118-I119)*F93 -> -2.2737368e-14 | G94: $- | H94: =F94/1.12 -> -2.0301221e-14 | O94: =I117+I118+I119 -> 10400.63 | P94: =SUM(K94:O94) -> 10400.63 | Q94: 0 | R94: =+I120 -> 10400.63 | S94: 0
E95: EMERGENCY | F95: =Q94 -> 0 | G95: $- | J95: Successful | O95: 3 | P95: =SUM(K95:O95) -> 3
E96: EMERGENCY - PAY OUT | F96: =F95*0.25 -> 0 | G96: $- | H96: =F96/1.12 -> 0 | J96: Unsuccessful | O96: 0 | P96: =SUM(K96:O96) -> 0
E97: PREV. WEEK | G97: $- | J97: Success rate | K97: =K95/(K95+K96) -> #DIV/0! | L97: =L95/(L95+L96) -> #DIV/0! | M97: =M95/(M95+M96) -> #DIV/0! | N97: =N95/(N95+N96) -> #DIV/0! | O97: =O95/(O95+O96) -> 1 | P97: =P95/(P95+P96) -> 1 | Q97: =Q95/(Q95+Q96) -> #DIV/0!
E98: PREV. WEEK - PAY OUT | F98: =F97*0.05 -> 0 | G98: $- | H98: =F98/1.12 -> 0 | J98: Avg sale | K98: =K94/K95 -> #DIV/0! | L98: =L94/L95 -> #DIV/0! | M98: =M94/M95 -> #DIV/0! | N98: =N94/N95 -> #DIV/0! | O98: =O94/O95 -> 3466.8767 | P98: =P94/P95 -> 3466.8767 | Q98: =Q94/Q95 -> #DIV/0!
E99: 5 Star Review | F99: =5*50/2 -> 125 | H99: =F99/1.12 -> 111.60714
E100: 5 Star Notes | F100: =T89 -> 0 | K100: Managment Summary - SALES ONLY - COLUMN F | R100: WEEKDAY | S100: WEEKEND
E101: 1/8 - Reece - 1014842672 - Job 71949 | F101: -19.84 | K101: MON | L101: TUE | M101: WED | N101: THU | O101: FRI | P101: Total | Q101: SAT | R101: Awaiting Payment | S101: Awaiting Payment
E102: 1/8 - Reece - 1014824226 - Job 71949 | F102: -386.01 | O102: =F117+F118+F119 -> 11383 | P102: =SUM(K102:O102) -> 11383 | Q102: 0 | R102: =+F120 -> 11383 | S102: 0
E103: 1/8 - Reece - CN-52125768- Job 71949 | F103: 235.96 | J103: Successful | K103: =K95 -> 0 | L103: =L95 -> 0 | M103: =M95 -> 0 | N103: =N95 -> 0 | O103: =O95 -> 3 | P103: =P95 -> 3 | Q103: =Q95 -> 0
J104: Unsuccessful | K104: =K96 -> 0 | L104: =L96 -> 0 | M104: =M96 -> 0 | N104: =N96 -> 0 | O104: =O96 -> 0 | P104: =P96 -> 0 | Q104: =Q96 -> 0
J105: Success rate | K105: =K103/(K103+K104) -> #DIV/0! | L105: =L103/(L103+L104) -> #DIV/0! | M105: =M103/(M103+M104) -> #DIV/0! | N105: =N103/(N103+N104) -> #DIV/0! | O105: =O103/(O103+O104) -> 1 | P105: =P103/(P103+P104) -> 1 | Q105: =Q103/(Q103+Q104) -> #DIV/0!
J106: Avg sale | K106: =K102/K103 -> #DIV/0! | L106: =L102/L103 -> #DIV/0! | M106: =M102/M103 -> #DIV/0! | N106: =N102/N103 -> #DIV/0! | O106: =O102/O103 -> 3794.3333 | P106: =P102/P103 -> 3794.3333 | Q106: =Q102/Q103 -> #DIV/0!
B109: JOB DETAILS | F109: JOB AMOUNT | K109: PHOTOS | N109: QUOTE | Q109: INVOICE | U109: NOTES
B110: JOB STATUS | C110: DATE | D110: JOB # | E110: SUBURB | F110: AMOUNT EXC. GST | G110: MATERIALS | H110: Merchant Fees | I110: NET PROFIT | J110: PAID | K110: BEFORE | L110: AFTER | M110: RECEIPT | N110: DESCRIPTION | O110: SIGNED | P110: EMAILED | Q110: DESCRIPTION | R110: SIGNED | S110: EMAILED | T110: 5 Star Review | V110: EFTPOS | W110: CASH | X110: Payment Plan
B111: COMPLETED & PAID JOBS
B112: 1 | I112: =F112-G112-H112 -> 0
F113: =SUM(F112:F112) -> 0 | G113: =SUM(G112:G112) -> 0 | H113: =SUM(H112:H112) -> 0 | I113: =SUM(I112:I112) -> 0 | K113: =COUNT(K112:K112) -> 0 | L113: =COUNT(L112:L112) -> 0 | M113: =COUNT(M112:M112) -> 0 | N113: =COUNT(N112:N112) -> 0 | O113: =COUNT(O112:O112) -> 0 | P113: =COUNT(P112:P112) -> 0 | Q113: =COUNT(Q112:Q112) -> 0 | R113: =COUNT(R112:R112) -> 0 | S113: =COUNT(S112:S112) -> 0
...

Sheet Eric - No OT
B2: WEEKLY COMMISSION | F2: WEEK ENDING | G2: 45970
K3: PHOTOS | N3: QUOTE | Q3: INVOICE
B4: BOOKED JOBS | C4: =C5+C6 -> 0 | E4: WEEKLY TARGET | K4: BEFORE | L4: AFTER | M4: RECEIPT | N4: DESCRIPTION | O4: SIGNED | P4: EMAILED | Q4: DESCRIPTION | R4: SIGNED | S4: EMAILED | T4: 5 Star Review
B5: SUCCESSFUL | C5: =P12 -> 0 | E5: Tier 1 | F5: <$25000 | G5: 0.05 | J5: TAKEN | K5: =K47 -> 0 | L5: =L47 -> 0 | M5: =M47 -> 0 | N5: =N47 -> 0 | O5: =O47 -> 0 | P5: =P47 -> 0 | Q5: =Q47 -> 0 | R5: =R47 -> 0 | S5: =S47 -> 0 | T5: =T144 -> 0
B6: UNSUCCESSFUL | C6: =P13 -> 0 | E6: Tier 2 | F6: >= $25000 | G6: 0.1 | J6: % | K6: =K47/K46 -> #DIV/0! | L6: =L47/L46 -> #DIV/0! | M6: =M47/M46 -> #DIV/0! | N6: =N47/N46 -> #DIV/0! | O6: =O47/O46 -> #DIV/0! | P6: =P47/P46 -> #DIV/0! | Q6: =Q47/Q46 -> #DIV/0! | R6: =R47/R46 -> #DIV/0! | S6: =S47/S46 -> #DIV/0! | U6: M8 Notes
B7: SUCESSFUL (%) | C7: =P14 -> #DIV/0!
F8: ACTUAL | G8: POTENTIAL | H8: Exc. SUPER
B9: AVERAGE SALE | C9: =P15 -> #DIV/0! | E9: NET PROFIT | F9: =P11 -> 0 | G9: =I46+I80+I102 -> 0 | K9: DAILY NET PROFIT | R9: WEEKDAY | S9: WEEKEND
E10: UNLOCKED | F10: =IF(F9>=25000,10%,5%) -> 0.05 | K10: MON | L10: TUE | M10: WED | N10: THU | O10: FRI | P10: Total | Q10: SAT | R10: Awaiting Payment | S10: Awaiting Payment
E11: COMMISSION - PAY OUT | F11: =F9*F10 -> 0 | G11: $- | H11: =F11/1.12 -> 0 | P11: =SUM(K11:O11) -> 0 | Q11: 0 | R11: =I80+I102 -> 0 | S11: =+I91+I113 -> 0
E12: EMERGENCY | F12: =Q11 -> 0 | G12: $- | J12: Successful | P12: =SUM(K12:O12) -> 0
E13: EMERGENCY - PAY OUT | F13: =F12*0.25 -> 0 | G13: $- | H13: =F13/1.12 -> 0 | J13: Unsuccessful | P13: =SUM(K13:O13) -> 0
E14: PREV. WEEK | F14: 0 | G14: $- | J14: Success rate | K14: =K12/(K12+K13) -> #DIV/0! | L14: =L12/(L12+L13) -> #DIV/0! | M14: =M12/(M12+M13) -> #DIV/0! | N14: =N12/(N12+N13) -> #DIV/0! | O14: =O12/(O12+O13) -> #DIV/0! | P14: =P12/(P12+P13) -> #DIV/0! | Q14: =Q12/(Q12+Q13) -> #DIV/0!
E15: PREV. WEEK - PAY OUT | F15: =F14*0.05 -> 0 | G15: $- | H15: =F15/1.12 -> 0 | J15: Avg sale | K15: =K11/K12 -> #DIV/0! | L15: =L11/L12 -> #DIV/0! | M15: =M11/M12 -> #DIV/0! | N15: =N11/N12 -> #DIV/0! | O15: =O11/O12 -> #DIV/0! | P15: =P11/P12 -> #DIV/0! | Q15: =Q11/Q12 -> #DIV/0!
E16: 5 Star Review | H16: =F16/1.12 -> 0
E17: 5 Star Notes | F17: =T6 -> 0 | K17: Managment Summary - SALES ONLY - COLUMN F | R17: WEEKDAY | S17: WEEKEND
K18: MON | L18: TUE | M18: WED | N18: THU | O18: FRI | P18: Total | Q18: SAT | R18: Awaiting Payment | S18: Awaiting Payment
P19: =SUM(K19:O19) -> 0 | Q19: 0 | R19: =F80+F102 -> 0 | S19: =F91+F113 -> 0
J20: Successful | K20: =K12 -> 0 | L20: =L12 -> 0 | M20: =M12 -> 0 | N20: =N12 -> 0 | O20: =O12 -> 0 | P20: =P12 -> 0 | Q20: =Q12 -> 0
J21: Unsuccessful | K21: =K13 -> 0 | L21: =L13 -> 0 | M21: =M13 -> 0 | N21: =N13 -> 0 | O21: =O13 -> 0 | P21: =P13 -> 0 | Q21: =Q13 -> 0
J22: Success rate | K22: =K20/(K20+K21) -> #DIV/0! | L22: =L20/(L20+L21) -> #DIV/0! | M22: =M20/(M20+M21) -> #DIV/0! | N22: =N20/(N20+N21) -> #DIV/0! | O22: =O20/(O20+O21) -> #DIV/0! | P22: =P20/(P20+P21) -> #DIV/0! | Q22: =Q20/(Q20+Q21) -> #DIV/0!
J23: Avg sale | K23: =K19/K20 -> #DIV/0! | L23: =L19/L20 -> #DIV/0! | M23: =M19/M20 -> #DIV/0! | N23: =N19/N20 -> #DIV/0! | O23: =O19/O20 -> #DIV/0! | P23: =P19/P20 -> #DIV/0! | Q23: =Q19/Q20 -> #DIV/0!
B27: JOB DETAILS | F27: JOB AMOUNT | K27: PHOTOS | N27: QUOTE | Q27: INVOICE | U27: NOTES
B28: JOB STATUS | C28: DATE | D28: JOB # | E28: SUBURB | F28: AMOUNT EXC. GST | G28: MATERIALS | H28: Merchant Fees | I28: NET PROFIT | J28: PAID | K28: BEFORE | L28: AFTER | M28: RECEIPT | N28: DESCRIPTION | O28: SIGNED | P28: EMAILED | Q28: DESCRIPTION | R28: SIGNED | S28: EMAILED | T28: 5 Star Review | V28: EFTPOS | W28: CASH | X28: Payment Plan
B29: COMPLETED & PAID JOBS
B30: 1 | I30: =F30-G30-H30 -> 0
B31: =B30+1 -> 2 | I31: =F31-G31-H31 -> 0
B32: =B31+1 -> 3 | I32: =F32-G32-H32 -> 0
B33: =B32+1 -> 4 | I33: =F33-G33-H33 -> 0
B34: =B33+1 -> 5 | I34: =F34-G34-H34 -> 0
B35: =B34+1 -> 6 | I35: =F35-G35-H35 -> 0
B36: =B35+1 -> 7 | I36: =F36-G36-H36 -> 0
B37: =B36+1 -> 8 | I37: =F37-G37-H37 -> 0
B38: =B37+1 -> 9 | I38: =F38-G38-H38 -> 0
B39: =B38+1 -> 10 | I39: =F39-G39-H39 -> 0
B40: =B39+1 -> 11 | I40: =F40-G40-H40 -> 0
B41: =B40+1 -> 12 | I41: =F41-G41-H41 -> 0
B42: =B41+1 -> 13 | I42: =F42-G42-H42 -> 0
... B45: =B44+1 -> 16 | I45: =F45-G45-H45 -> 0
F46: =SUM(F30:F45) -> 0 | G46: =SUM(G30:G45) -> 0 | H46: =SUM(H30:H45) -> 0 | I46: =SUM(I30:I45) -> 0 | K46: =COUNT(K30:K45) -> 0 | L46: =COUNT(L30:L45) -> 0 | M46: =COUNT(M30:M45) -> 0 | N46: =COUNT(N30:N45) -> 0 | O46: =COUNT(O30:O45) -> 0 | P46: =COUNT(P30:P45) -> 0 | Q46: =COUNT(Q30:Q45) -> 0 | R46: =COUNT(R30:R45) -> 0 | S46: =COUNT(S30:S45) -> 0
K47: =SUM(K30:K45) -> 0 | L47: =SUM(L30:L45) -> 0 | M47: =SUM(M30:M45) -> 0 | N47: =SUM(N30:N45) -> 0 | O47: =SUM(O30:O45) -> 0 | P47: =SUM(P30:P45) -> 0 | Q47: =SUM(Q30:Q45) -> 0 | R47: =SUM(R30:R45) -> 0 | S47: =SUM(S30:S45) -> 0
B49: WEEKEND COMPLETED & PAID JOBS
B50: 1 | I50: =F50-G50-H50 -> 0
B51: =B50+1 -> 2 | I51: =F51-G51-H51 -> 0
B52: =B51+1 -> 3 | I52: =F52-G52-H52 -> 0
B53: =B52+1 -> 4 | I53: =F53-G53-H53 -> 0
B54: =B53+1 -> 5 | I54: =F54-G54-H54 -> 0
B55: =B54+1 -> 6 | I55: =F55-G55-H55 -> 0
B56: =B55+1 -> 7 | I56: =F56-G56-H56 -> 0
B57: =B56+1 -> 8 | I57: =F57-G57-H57 -> 0
F58: =SUM(F50:F57) -> 0 | G58: =SUM(G50:G57) -> 0 | H58: =SUM(H50:H57) -> 0 | I58: =SUM(I50:I57) -> 0
B60: PREVIOUS JOBS COMPLETED & PAID (COMMISSION) - Modoras Team Please do ADD to THIS SECTION or AMEND/TOUCH
B61: 1 | I61: =F61-G61-H61 -> 0
B62: =B61+1 -> 2 | I62: =F62-G62-H62 -> 0
B63: =B62+1 -> 3 | I63: =F63-G63-H63 -> 0
B64: =B63+1 -> 4 | I64: =F64-G64-H64 -> 0
B65: =B64+1 -> 5 | I65: =F65-G65-H65 -> 0
B66: =B65+1 -> 6 | I66: =F66-G66-H66 -> 0
B67: =B66+1 -> 7 | I67: =F67-G67-H67 -> 0
B68: =B67+1 -> 8 | I68: =F68-G68-H68 -> 0
F69: =SUM(F61:F68) -> 0 | G69: =SUM(G61:G68) -> 0 | H69: =SUM(H61:H68) -> 0 | I69: =SUM(I61:I68) -> 0
B71: CURRENT JOBS COMPLETED (AWAITING PAYMENT)
B72: 1 | I72: =F72-G72-H72 -> 0
B73: =B72+1 -> 2 | I73: =F73-G73-H73 -> 0
B74: =B73+1 -> 3 | I74: =F74-G74-H74 -> 0
B75: =B74+1 -> 4 | I75: =F75-G75-H75 -> 0
B76: =B75+1 -> 5 | I76: =F76-G76-H76 -> 0
B77: =B76+1 -> 6 | I77: =F77-G77-H77 -> 0
B78: =B77+1 -> 7 | I78: =F78-G78-H78 -> 0
B79: =B78+1 -> 8 | I79: =F79-G79-H79 -> 0
F80: =SUM(F72:F79) -> 0 | G80: =SUM(G72:G79) -> 0 | H80: =SUM(H72:H79) -> 0 | I80: =SUM(I72:I79) -> 0
B82: WEEKEND CURRENT JOBS COMPLETED (AWAITING PAYMENT)
B83: 1 | I83: =F83-G83-H83 -> 0
B84: =B83+1 -> 2 | I84: =F84-G84-H84 -> 0
B85: =B84+1 -> 3 | I85: =F85-G85-H85 -> 0
B86: =B85+1 -> 4 | I86: =F86-G86-H86 -> 0
B87: =B86+1 -> 5 | I87: =F87-G87-H87 -> 0
B88: =B87+1 -> 6 | I88: =F88-G88-H88 -> 0
B89: =B88+1 -> 7 | I89: =F89-G89-H89 -> 0
B90: =B89+1 -> 8 | I90: =F90-G90-H90 -> 0
F91: =SUM(F83:F90) -> 0 | G91: =SUM(G83:G90) -> 0 | H91: =SUM(H83:H90) -> 0 | I91: =SUM(I83:I90) -> 0
B93: CURRENT WORK ORDERS (AWAITING PAYMENT)
B94: 1 | I94: =F94-G94-H94 -> 0
B95: =B94+1 -> 2 | I95: =F95-G95-H95 -> 0
B96: =B95+1 -> 3 | I96: =F96-G96-H96 -> 0
B97: =B96+1 -> 4 | I97: =F97-G97-H97 -> 0
B98: =B97+1 -> 5 | I98: =F98-G98-H98 -> 0
B99: =B98+1 -> 6 | I99: =F99-G99-H99 -> 0
B100: =B99+1 -> 7 | I100: =F100-G100-H100 -> 0
B101: =B100+1 -> 8 | I101: =F101-G101-H101 -> 0
F102: =SUM(F94:F101) -> 0 | G102: =SUM(G94:G101) -> 0 | H102: =SUM(H94:H101) -> 0 | I102: =SUM(I94:I101) -> 0
B104: WEEKEND WORK ORDERS (AWAITING PAYMENT)
B105: 1 | I105: =F105-G105-H105 -> 0
B106: =B105+1 -> 2 | I106: =F106-G106-H106 -> 0
B107: =B106+1 -> 3 | I107: =F107-G107-H107 -> 0
B108: =B107+1 -> 4 | I108: =F108-G108-H108 -> 0
B109: =B108+1 -> 5 | I109: =F109-G109-H109 -> 0
B110: =B109+1 -> 6 | I110: =F110-G110-H110 -> 0
B111: =B110+1 -> 7 | I111: =F111-G111-H111 -> 0
B112: =B111+1 -> 8 | I112: =F112-G112-H112 -> 0
...

Sheet Jack M
B3: WEEKLY COMMISSION | F3: WEEK ENDING | G3: 45837
K4: PHOTOS | N4: QUOTE | Q4: INVOICE
B5: BOOKED JOBS | C5: =C6+C7 -> 40 | E5: WEEKLY TARGET | K5: BEFORE | L5: AFTER | M5: RECEIPT | N5: DESCRIPTION | O5: SIGNED | P5: EMAILED | Q5: DESCRIPTION | R5: SIGNED | S5: EMAILED | T5: 5 Star Review
B6: SUCCESSFUL | C6: =P13 -> 12 | E6: Tier 1 | F6: 0.05 | J6: TAKEN | K6: =K41 -> 10 | L6: =L41 -> 8 | M6: =M41 -> 10 | N6: =N41 -> 10 | O6: =O41 -> 10 | P6: =P41 -> 8 | Q6: =Q41 -> 9 | R6: =R41 -> 9 | S6: =S41 -> 8 | T6: =T92 -> 0
B7: UNSUCCESSFUL | C7: =P14 -> 28 | J7: % | K7: =K41/K40 -> 1 | L7: =L41/L40 -> 0.8 | M7: =M41/M40 -> 1 | N7: =N41/N40 -> 1 | O7: =O41/O40 -> 1 | P7: =P41/P40 -> 0.8 | Q7: =Q41/Q40 -> 0.9 | R7: =R41/R40 -> 0.9 | S7: =S41/S40 -> 0.8 | U7: M8 Notes
B8: SUCESSFUL (%) | C8: =P15 -> 0.3
F9: ACTUAL | G9: POTENTIAL | H9: Exc. SUPER
B10: AVERAGE SALE | C10: =P16 -> 1048.1583 | E10: NET PROFIT | F10: =P12 -> 12577.9 | G10: =I40+I49+I53 -> 12577.9 | K10: DAILY NET PROFIT | R10: WEEKDAY | S10: WEEKEND
E11: UNLOCKED | F11: =F6 -> 0.05 | K11: MON | L11: TUE | M11: WED | N11: THU | O11: FRI | P11: Total | Q11: SAT | R11: Awaiting Payment | S11: Awaiting Payment
E12: COMMISSION - PAY OUT | F12: =(F10-I48-I52)*F11 -> 491.915 | G12: $- | H12: =F12/1.12 -> 439.20982 | K12: =I30+I52 -> 2196.6 | L12: =I31+I32 -> 997 | M12: =I48 -> 1641.3 | N12: =I33+I34+I35 -> 3437.6 | O12: =I37+I36+I38+I39 -> 4305.4 | P12: =SUM(K12:O12) -> 12577.9 | Q12: 0 | R12: =I49+I53 -> 2739.6 | S12: 0
E13: EMERGENCY | F13: =Q12 -> 0 | G13: $- | J13: Successful | K13: 2 | L13: 2 | M13: 1 | N13: 3 | O13: 4 | P13: =SUM(K13:O13) -> 12
E14: EMERGENCY - PAY OUT | F14: =F13*0.25 -> 0 | G14: $- | H14: =F14/1.115 -> 0 | J14: Unsuccessful | K14: 6 | L14: 7 | M14: 4 | N14: 8 | O14: 3 | P14: =SUM(K14:O14) -> 28
E15: PREV. WEEK | G15: $- | J15: Success rate | K15: =K13/(K13+K14) -> 0.25 | L15: =L13/(L13+L14) -> 0.22222222 | M15: =M13/(M13+M14) -> 0.2 | N15: =N13/(N13+N14) -> 0.27272727 | O15: =O13/(O13+O14) -> 0.57142857 | P15: =P13/(P13+P14) -> 0.3 | Q15: =Q13/(Q13+Q14) -> #DIV/0!
E16: PREV. WEEK - PAY OUT | F16: =F15*0.05 -> 0 | G16: $- | H16: =F16/1.115 -> 0 | J16: Avg sale | K16: =K12/K13 -> 1098.3 | L16: =L12/L13 -> 498.5 | M16: =M12/M13 -> 1641.3 | N16: =N12/N13 -> 1145.8667 | O16: =O12/O13 -> 1076.35 | P16: =P12/P13 -> 1048.1583 | Q16: =Q12/Q13 -> #DIV/0!
E17: 5 Star Review | H17: =F17/1.115 -> 0
E18: 5 Star Notes | F18: =T7 -> 0 | K18: Managment Summary - SALES ONLY - COLUMN F | R18: WEEKDAY | S18: WEEKEND
K19: MON | L19: TUE | M19: WED | N19: THU | O19: FRI | P19: Total | Q19: SAT | R19: Awaiting Payment | S19: Awaiting Payment
K20: =F30+F52 -> 2276 | L20: =F31+F32 -> 997 | M20: =F48 -> 1681 | N20: =F33+F34+F35 -> 3517 | O20: =F37+F36+F38+F39 -> 4464 | P20: =SUM(K20:O20) -> 12935 | Q20: 0 | R20: =F49+F53 -> 2819 | S20: 0
J21: Successful | K21: =K13 -> 2 | L21: =L13 -> 2 | M21: =M13 -> 1 | N21: =N13 -> 3 | O21: =O13 -> 4 | P21: =P13 -> 12 | Q21: =Q13 -> 0
J22: Unsuccessful | K22: =K14 -> 6 | L22: =L14 -> 7 | M22: =M14 -> 4 | N22: =N14 -> 8 | O22: =O14 -> 3 | P22: =P14 -> 28 | Q22: =Q14 -> 0
J23: Success rate | K23: =K21/(K21+K22) -> 0.25 | L23: =L21/(L21+L22) -> 0.22222222 | M23: =M21/(M21+M22) -> 0.2 | N23: =N21/(N21+N22) -> 0.27272727 | O23: =O21/(O21+O22) -> 0.57142857 | P23: =P21/(P21+P22) -> 0.3 | Q23: =Q21/(Q21+Q22) -> #DIV/0!
J24: Avg sale | K24: =K20/K21 -> 1138 | L24: =L20/L21 -> 498.5 | M24: =M20/M21 -> 1681 | N24: =N20/N21 -> 1172.3333 | O24: =O20/O21 -> 1116 | P24: =P20/P21 -> 1077.9167 | Q24: =Q20/Q21 -> #DIV/0!
B27: JOB DETAILS | F27: JOB AMOUNT | K27: PHOTOS | N27: QUOTE | Q27: INVOICE | U27: NOTES
B28: JOB STATUS | C28: DATE | D28: JOB # | E28: SUBURB | F28: AMOUNT EXC. GST | G28: MATERIALS | H28: Merchant Fees | I28: NET PROFIT | J28: PAID | K28: BEFORE | L28: AFTER | M28: RECEIPT | N28: DESCRIPTION | O28: SIGNED | P28: EMAILED | Q28: DESCRIPTION | R28: SIGNED | S28: EMAILED | T28: 5 Star Review | V28: EFTPOS | W28: CASH | X28: Payment Plan
B29: COMPLETED & PAID JOBS
B30: 1 | C30: 45831 | D30: 70916 | E30: West Footscray | F30: 1138 | G30: 39.7 | I30: =F30-G30-H30 -> 1098.3 | J30: Card | K30: 1 | L30: 0 | M30: 1 | N30: 1 | O30: 1 | P30: 0 | Q30: 0 | R30: 0 | S30: 0 | V30: 1251.8
B31: =B30+1 -> 2 | C31: 45832 | D31: 70991 | E31: Burnswick | F31: 481 | I31: =F31-G31-H31 -> 481 | J31: EFT | K31: 1 | L31: 1 | M31: 1 | N31: 1 | O31: 1 | P31: 1 | Q31: 1 | R31: 1 | S31: 1 | V31: 529.1
B32: =B31+1 -> 3 | C32: 45832 | D32: 70996 | E32: Burnswick | F32: 516 | I32: =F32-G32-H32 -> 516 | J32: Cash/EFT | K32: 1 | L32: 1 | M32: 1 | N32: 1 | O32: 1 | P32: 1 | Q32: 1 | R32: 1 | S32: 1 | U32: 24/06 - EFT received $10.6 | V32: 10.6 | W32: 557
A33: 45847 | B33: =B32+1 -> 4 | C33: 45834 | D33: 71011 | E33: Mentone | F33: 1138 | G33: 39.7 | I33: =F33-G33-H33 -> 1098.3 | J33: Card | K33: 1 | L33: 1 | M33: 1 | N33: 1 | O33: 1 | P33: 1 | Q33: 1 | R33: 1 | S33: 1 | U33: 9 Jul - Refund - $89 | V33: 1251.8
B34: =B33+1 -> 5 | C34: 45834 | D34: 71029 | E34: Vermont South | F34: 516 | I34: =F34-G34-H34 -> 516 | J34: Card | K34: 1 | L34: 1 | M34: 1 | N34: 1 | O34: 1 | P34: 1 | Q34: 1 | R34: 1 | S34: 1 | V34: 567.6
B35: =B34+1 -> 6 | C35: 45834 | D35: 71031 | E35: Fitzroy | F35: 1863 | G35: 39.7 | I35: =F35-G35-H35 -> 1823.3 | J35: EFT | K35: 1 | L35: 1 | M35: 1 | N35: 1 | O35: 1 | P35: 0 | Q35: 1 | R35: 1 | S35: 0 | U35: 26 Jun - Deduct 1.25hrs O/T | V35: 2049.3
B36: =B35+1 -> 7 | C36: 45835 | D36: 71048 | E36: Essendon | F36: 1264 | G36: 39.7 | I36: =F36-G36-H36 -> 1224.3 | J36: EFT | K36: 1 | L36: 1 | M36: 1 | N36: 1 | O36: 1 | P36: 1 | Q36: 1 | R36: 1 | S36: 1 | U36: 27/06 - EFT Received $1390.40 | V36: 1390.4
B37: =B36+1 -> 8 | C37: 45835 | D37: 71067 | E37: Gladstone Park | F37: 966 | G37: 39.7 | I37: =F37-G37-H37 -> 926.3 | J37: Card | K37: 1 | L37: 1 | M37: 1 | N37: 1 | O37: 1 | P37: 1 | Q37: 1 | R37: 1 | S37: 1 | V37: 1062.6
B38: =B37+1 -> 9 | C38: 45835 | D38: 71061/85948517 | E38: Moonee Ponds | F38: 919 | G38: 39.7 | I38: =F38-G38-H38 -> 879.3 | J38: EFT | K38: 1 | L38: 0 | M38: 1 | N38: 1 | O38: 1 | P38: 1 | Q38: 1 | R38: 1 | S38: 1 | U38: 27/06 - EFT Received $1010.90 | V38: 1010.9
B39: =B38+1 -> 10 | C39: 45835 | D39: 71060 | E39: Ascot Vale | F39: 1315 | G39: 39.5 | I39: =F39-G39-H39 -> 1275.5 | J39: EFT | K39: 1 | L39: 1 | M39: 1 | N39: 1 | O39: 1 | P39: 1 | Q39: 1 | R39: 1 | S39: 1 | U39: 27/06 - EFT Received $1446.50 | V39: 1446.5
F40: =SUM(F30:F39) -> 10116 | G40: =SUM(G30:G39) -> 277.7 | H40: =SUM(H30:H39) -> 0 | I40: =SUM(I30:I39) -> 9838.3 | K40: =COUNT(K30:K39) -> 10 | L40: =COUNT(L30:L39) -> 10 | M40: =COUNT(M30:M39) -> 10 | N40: =COUNT(N30:N39) -> 10 | O40: =COUNT(O30:O39) -> 10 | P40: =COUNT(P30:P39) -> 10 | Q40: =COUNT(Q30:Q39) -> 10 | R40: =COUNT(R30:R39) -> 10 | S40: =COUNT(S30:S39) -> 10
K41: =SUM(K30:K39) -> 10 | L41: =SUM(L30:L39) -> 8 | M41: =SUM(M30:M39) -> 10 | N41: =SUM(N30:N39) -> 10 | O41: =SUM(O30:O39) -> 10 | P41: =SUM(P30:P39) -> 8 | Q41: =SUM(Q30:Q39) -> 9 | R41: =SUM(R30:R39) -> 9 | S41: =SUM(S30:S39) -> 8
B43: PREVIOUS JOBS COMPLETED & PAID (COMMISSION) - Modoras Team Please do ADD to THIS SECTION or AMEND/TOUCH
A44: 5% - 24 Jun | B44: 1 | C44: 45819 | D44: 70680 | E44: Burnswick | F44: 2861 | G44: =39.7+(54.28-11.08) -> 82.9 | I44: =F44-G44-H44 -> 2778.1 | J44: EFT | K44: 1 | L44: 1 | M44: 1 | N44: 1 | O44: 1 | P44: 0 | Q44: 0 | R44: 0 | S44: 0 | U44: 11/06 EFT processed for $3147.10 | V44: =3147.1 -> 3147.1
F45: =SUM(F44:F44) -> 2861 | G45: =SUM(G44:G44) -> 82.9 | H45: =SUM(H44:H44) -> 0 | I45: =SUM(I44:I44) -> 2778.1
B47: CURRENT JOBS COMPLETED (AWAITING PAYMENT)
A48: 0.05 | B48: 1 | C48: 45833 | D48: 71034 | E48: Cremorne | F48: =1866-185 -> 1681 | G48: 39.7 | I48: =F48-G48-H48 -> 1641.3 | J48: Card | K48: 1 | L48: 1 | M48: 1 | N48: 1 | O48: 1 | P48: 1 | Q48: 1 | R48: 0 | S48: 1 | U48: 25 Jun - Deduct 1hr O/T | V48: 203.5
F49: =SUM(F48:F48) -> 1681 | G49: =SUM(G48:G48) -> 39.7 | H49: =SUM(H48:H48) -> 0 | I49: =SUM(I48:I48) -> 1641.3
B51: CURRENT WORK ORDERS (AWAITING PAYMENT)
A52: 0.05 | B52: 1 | C52: 45831 | D52: 70945 | E52: Thornbury | F52: 1138 | G52: 39.7 | I52: =F52-G52-H52 -> 1098.3 | K52: 1 | N52: 1 | O52: 1 | P52: 0 | U52: 23 Jun - Dedcut 45mins O/T
F53: =SUM(F52:F52) -> 1138 | G53: =SUM(G52:G52) -> 39.7 | H53: =SUM(H52:H52) -> 0 | I53: =SUM(I52:I52) -> 1098.3
B55: PREVIOUS JOBS COMPLETED (AWAITING PAYMENT) - Modoras Team Please do ADD to THIS SECTION or AMEND/TOUCH
A56: 0.05 | B56: 1 | C56: 45824 | D56: 70824 | E56: Footscray | F56: =861-185 -> 676 | G56: =39.7 -> 39.7 | I56: =F56-G56-H56 -> 636.3 | J56: Card | K56: 1 | L56: 1 | M56: 1 | N56: 1 | O56: 1 | P56: 1 | Q56: 1 | R56: 1 | S56: 1
A57: 0.05 | B57: =B61+1 -> 2 | C57: 45827 | D57: 70883 | E57: Truganina | F57: 8614 | G57: =39.7+(161.15+1191.42+647.38)+500 -> 2539.65 | I57: =F57-G57-H57 -> 6074.35 | J57: Card | K57: 1 | M57: 1 | N57: 1 | O57: 1 | P57: 0 | Q57: 1 | R57: 1 | S57: 0 | U57: 19 Jun - Deduct 2hrs O/T; 20/06 - WIP by Matthew H
F58: =SUM(F56:F57) -> 9290 | G58: =SUM(G56:G57) -> 2579.35 | H58: =SUM(H56:H57) -> 0 | I58: =SUM(I56:I57) -> 6710.65
B60: PREVIOUS WORK ORDERS (AWAITING PAYMENT) - Modoras Team Please do ADD to THIS SECTION or AMEND/TOUCH
A61: 0.05 | B61: 1 | C61: 45810 | D61: 70518 | E61: Windsor | F61: 26419 | G61: =39.7+203.2+120+64.59+1183.4+149.23+(130.62+177.65+87.1-177.65+57.34)+(128.64+382.27+26.55-93.95+8.58)+(F61*0.2) -> 7771.07 | I61: =F61-G61-H61 -> 18647.93 | K61: 1 | N61: 1 | O61: 1 | P61: 0 | U61: 26/06 - WIP by Daniel B ; 25/06 - WIP by Daniel B, Rhys Clark ; 24/06 - WIP by Alex , Daniel - Received $2500 Card; 23/06 - WIP by Daniel B - Received $10000 EFT; 20/06 - WIP by Tolga , Daniel B; 19/06 - WIP by Tolga ; 18/06 WIP by Tolga , Jack M ; 17/06 WIP by Tolga ; 16/06 - WIP By Tolga, Jarrod Card payment received $2000 ;11/06 - Scheduled for Tolga ;10/06 - WIP by Tolga; 2 Jun - Deduct 1.5hrs O/T; 02/06- WIP by Jack&Tolga | V61: =2500 -> 2500
F62: =SUM(F61:F61) -> 26419 | G62: =SUM(G61:G61) -> 7771.07 | H62: =SUM(H61:H61) -> 0 | I62: =SUM(I61:I61) -> 18647.93
B64: UNSUCCESSFUL JOBS
B65: 1 | C65: 45831 | D65: 70912 | E65: Essendon North | F65: 1861 | G65: 39.7 | I65: =F65-G65-H65 -> 1821.3 | J65: N/A | K65: 1 | N65: 1 | Q65: 1 | R65: 1 | S65: 1
B66: =B65+1 -> 2 | C66: 45831 | D66: 70916/85880436 | E66: West Footscray | F66: 15093.2 | G66: 39.7 | I66: =F66-G66-H66 -> 15053.5 | J66: N/A | K66: 1 | N66: 1
B67: =B66+1 -> 3 | C67: 45831 | D67: 70876/85881669 | E67: Essendon | F67: 6214 | G67: 39.7 | I67: =F67-G67-H67 -> 6174.3 | J67: N/A | K67: 1 | N67: 1 | Q67: 1 | R67: 1 | S67: 1
B68: =B67+1 -> 4 | C68: 45831 | D68: 70876/85882143 | E68: Essendon | F68: 6814 | G68: 39.7 | I68: =F68-G68-H68 -> 6774.3 | J68: N/A | K68: 1 | N68: 1 | Q68: 1 | R68: 1 | S68: 1
B69: =B68+1 -> 5 | C69: 45831 | D69: 70945/85884871 | E69: Thornbury | F69: 12814 | G69: 39.7 | I69: =F69-G69-H69 -> 12774.3 | J69: N/A | K69: 1 | N69: 1 | P69: ='Ben'!P311+'Ben'!P311+'Jack M'!P266+
B70: =B69+1 -> 6 | C70: 45831 | D70: 70931 | E70: Braybrook | F70: 1396 | G70: 39.7 | I70: =F70-G70-H70 -> 1356.3 | J70: N/A | K70: 1 | N70: 1 | Q70: 1 | R70: 1 | S70: 1
B71: =B70+1 -> 7 | C71: 45832 | D71: 70963 | E71: Hoppers Crossing | F71: 1175 | G71: 39.7 | I71: =F71-G71-H71 -> 1135.3 | J71: N/A | K71: 1 | N71: 1 | Q71: 1 | R71: 1 | S71: 1
B72: =B71+1 -> 8 | C72: 45832 | D72: 70975 | E72: Coburg | F72: 1461 | G72: 39.7 | I72: =F72-G72-H72 -> 1421.3 | J72: N/A | K72: 1 | N72: 1 | Q72: 1 | R72: 1 | S72: 1
B73: =B72+1 -> 9 | C73: 45832 | D73: 70977 | E73: Preston | F73: 1461 | G73: 39.7 | I73: =F73-G73-H73 -> 1421.3 | J73: N/A | K73: 1 | N73: 1 | Q73: 1 | R73: 1 | S73: 1
B74: =B73+1 -> 10 | C74: 45832 | D74: 70998 | E74: Blackburn South | F74: 0 | I74: =F74-G74-H74 -> 0 | J74: N/A | N74: 1
B75: =B74+1 -> 11 | C75: 45832 | D75: 70994 | E75: Fairfield | F75: 0 | I75: =F75-G75-H75 -> 0 | J75: Quote | K75: 1 | Q75: 1 | R75: 1 | S75: 1
B76: =B75+1 -> 12 | C76: 45832 | D76: 70989 | E76: Heidelberg | F76: 12814 | G76: 39.7 | I76: =F76-G76-H76 -> 12774.3 | J76: N/A | K76: 1 | N76: 1
B77: =B76+1 -> 13 | C77: 45833 | D77: 70944 | E77: St kilda | F77: 0 | I77: =F77-G77-H77 -> 0 | J77: Quote
B78: =B77+1 -> 14 | C78: 45833 | D78: 71022/85922172 | E78: Saint Kilda East | F78: 2814 | G78: 39.7 | I78: =F78-G78-H78 -> 2774.3 | J78: N/A | K78: 1 | N78: 1 | Q78: 1 | R78: 1 | S78: 1
B79: =B78+1 -> 15 | C79: 45833 | D79: 71022/85922414 | E79: Saint Kilda East | F79: 1138 | G79: 39.7 | I79: =F79-G79-H79 -> 1098.3 | J79: N/A | K79: 1 | N79: 1 | Q79: 1 | R79: 1 | S79: 1
B80: =B79+1 -> 16 | C80: 45833 | D80: 71008 | E80: Maidstone | F80: 0 | I80: =F80-G80-H80 -> 0 | J80: Quote | K80: 1
B81: =B80+1 -> 17 | C81: 45834 | D81: 71007 | E81: Bentleigh East | F81: 1372 | G81: 39.7 | I81: =F81-G81-H81 -> 1332.3 | J81: N/A | K81: 1 | N81: 1 | Q81: 1 | R81: 1 | S81: 1
B82: =B81+1 -> 18 | C82: 45834 | D82: 71014 | E82: Clayton | F82: 0 | I82: =F82-G82-H82 -> 0 | J82: Quote | K82: 1 | Q82: 1 | R82: 1 | S82: 1
B83: =B82+1 -> 19 | C83: 45834 | D83: 71017 | E83: Hamton Park | F83: 0 | I83: =F83-G83-H83 -> 0 | J83: Quote | K83: 1 | Q83: 1 | R83: 1 | S83: 1
B84: =B83+1 -> 20 | C84: 45834 | D84: 71033 | E84: Black Rock | F84: 20417 | G84: 39.7 | I84: =F84-G84-H84 -> 20377.3 | J84: N/A | K84: 1 | N84: 1
B85: =B84+1 -> 21 | C85: 45834 | D85: 71052 | E85: Hamton Park | F85: 749 | I85: =F85-G85-H85 -> 749 | J85: N/A | K85: 1 | N85: 1 | Q85: 1 | R85: 1 | S85: 1
B86: =B85+1 -> 22 | C86: 45834 | D86: 71043/85939171 | E86: Windsor | F86: 5814 | G86: 39.7 | I86: =F86-G86-H86 -> 5774.3 | J86: N/A | K86: 1 | N86: 1 | Q86: 1 | R86: 1 | S86: 1
B87: =B86+1 -> 23 | C87: 45834 | D87: 71043/85938834 | E87: Windsor | F87: 5814 | G87: 39.7 | I87: =F87-G87-H87 -> 5774.3 | J87: N/A | K87: 1 | N87: 1 | Q87: 1 | R87: 1 | S87: 1
B88: =B87+1 -> 24 | C88: 45835 | D88: 71042 | E88: Fitzroy Norh | F88: 6814 | G88: 39.7 | I88: =F88-G88-H88 -> 6774.3 | J88: N/A | K88: 1 | N88: 1 | Q88: 1 | R88: 1 | S88: 1
B89: =B88+1 -> 25 | C89: 45835 | D89: 71057 | E89: Glenroy | F89: 2816 | G89: 39.7 | I89: =F89-G89-H89 -> 2776.3 | J89: N/A | K89: 1 | N89: 1 | Q89: 1 | R89: 1 | S89: 1
B90: =B89+1 -> 26 | C90: 45835 | D90: 71061/85949063 | E90: Moonee Ponds | F90: 5208 | G90: 39.7 | I90: =F90-G90-H90 -> 5168.3 | J90: N/A | K90: 1 | N90: 1
F91: =SUM(F65:F90) -> 114059.2 | G91: =SUM(G65:G90) -> 754.3 | H91: =SUM(H65:H90) -> 0 | I91: =SUM(I65:I90) -> 113304.9
T92: =SUM(T30:T91) -> 0 | V92: =SUM(V30:V91) -> 16421.2 | W92: =SUM(W30:W91) -> 557 | X92: =SUM(X30:X91) -> 0
B96: WEEKLY COMMISSION | F96: WEEK ENDING | G96: 45844
K97: PHOTOS | N97: QUOTE | Q97: INVOICE
B98: BOOKED JOBS | C98: =C99+C100 -> 26 | E98: WEEKLY TARGET | K98: BEFORE | L98: AFTER | M98: RECEIPT | N98: DESCRIPTION | O98: SIGNED | P98: EMAILED | Q98: DESCRIPTION | R98: SIGNED | S98: EMAILED | T98: 5 Star Review
B99: SUCCESSFUL | C99: =P106 -> 12 | E99: Tier 1 | F99: 0.05 | J99: TAKEN | K99: =K131 -> 7 | L99: =L131 -> 6 | M99: =M131 -> 6 | N99: =N131 -> 7 | O99: =O131 -> 7 | P99: =P131 -> 5 | Q99: =Q131 -> 7 | R99: =R131 -> 7 | S99: =S131 -> 6 | T99: =T172 -> 0
B100: UNSUCCESSFUL | C100: =P107 -> 14 | J100: % | K100: =K131/K130 -> 1 | L100: =L131/L130 -> 0.85714286 | M100: =M131/M130 -> 0.85714286 | N100: =N131/N130 -> 1 | O100: =O131/O130 -> 1 | P100: =P131/P130 -> 0.71428571 | Q100: =Q131/Q130 -> 1 | R100: =R131/R130 -> 1 | S100: =S131/S130 -> 0.85714286 | U100: M8 Notes
B101: SUCESSFUL (%) | C101: =P108 -> 0.46153846
F102: ACTUAL | G102: POTENTIAL | H102: Exc. SUPER
B103: AVERAGE SALE | C103: =P109 -> 3436.5158 | E103: NET PROFIT | F103: =P105 -> 41238.19 | G103: =I130+I142+I147 -> 41238.19 | K103: DAILY NET PROFIT | R103: WEEKDAY | S103: WEEKEND
E104: UNLOCKED | F104: =F99 -> 0.05 | K104: MON | L104: TUE | M104: WED | N104: THU | O104: FRI | P104: Total | Q104: SAT | R104: Awaiting Payment | S104: Awaiting Payment
E105: COMMISSION - PAY OUT | F105: =(F103-I126-I139-I140-I141-I145-I146)*F104 -> 433.43 | G105: $- | H105: =F105/1.12 -> 386.99107 | K105: =I125+I123+I124 -> 4069.55 | M105: =+I139+I145+I126 -> 15872.99 | O105: =I127+I128+I129+I140+I146+I141 -> 21295.65 | P105: =SUM(K105:O105) -> 41238.19 | Q105: 0 | R105: =I142+I147 -> 31148.29
E106: EMERGENCY | F106: =Q105 -> 0 | G106: $- | J106: Successful | K106: 3 | M106: 3 | N106: 0 | O106: 6 | P106: =SUM(K106:O106) -> 12
E107: EMERGENCY - PAY OUT | F107: =F106*0.25 -> 0 | G107: $- | H107: =F107/1.12 -> 0 | J107: Unsuccessful | K107: 3 | M107: 4 | N107: 6 | O107: 1 | P107: =SUM(K107:O107) -> 14
E108: PREV. WEEK | F108: =I136 -> 19245.37 | G108: $- | J108: Success rate | K108: =K106/(K106+K107) -> 0.5 | L108: =L106/(L106+L107) -> #DIV/0! | M108: =M106/(M106+M107) -> 0.42857143 | N108: =N106/(N106+N107) -> 0 | O108: =O106/(O106+O107) -> 0.85714286 | P108: =P106/(P106+P107) -> 0.46153846 | Q108: =Q106/(Q106+Q107) -> #DIV/0!
E109: PREV. WEEK - PAY OUT | F109: =(F108+F112)*0.05 -> 957.8185 | G109: $- | H109: =F109/1.12 -> 855.19509 | J109: Avg sale | K109: =K105/K106 -> 1356.5167 | L109: =L105/L106 -> #DIV/0! | M109: =M105/M106 -> 5290.9967 | N109: =N105/N106 -> #DIV/0! | O109: =O105/O106 -> 3549.275 | P109: =P105/P106 -> 3436.5158 | Q109: =Q105/Q106 -> #DIV/0!
E110: 5 Star Review | H110: =F110/1.12 -> 0
E111: 5 Star Notes | F111: =T100 -> 0 | K111: Managment Summary - SALES ONLY - COLUMN F | R111: WEEKDAY | S111: WEEKEND
E112: 9 Jul - Refund - Job 71011 | F112: =-89 -> -89 | K112: MON | L112: TUE | M112: WED | N112: THU | O112: FRI | P112: Total | Q112: SAT | R112: Awaiting Payment | S112: Awaiting Payment
K113: =F125+F123+F124 -> 4952 | M113: =+F139+F145+F126 -> 18356 | O113: =F127+F128+F129+F140+F146+F141 -> 23016 | P113: =SUM(K113:O113) -> 46324 | Q113: 0 | R113: =F142+F147 -> 35171
...

Sheet Jarrod - No OT
B3: WEEKLY COMMISSION | F3: WEEK ENDING | G3: 45837
K4: PHOTOS | N4: QUOTE | Q4: INVOICE
B5: BOOKED JOBS | C5: =C6+C7 -> 0 | E5: WEEKLY TARGET | K5: BEFORE | L5: AFTER | M5: RECEIPT | N5: DESCRIPTION | O5: SIGNED | P5: EMAILED | Q5: DESCRIPTION | R5: SIGNED | S5: EMAILED | T5: 5 Star Review
B6: SUCCESSFUL | C6: =P13 -> 0 | E6: Tier 1 | F6: 0.05 | J6: TAKEN | K6: =K32 -> 0 | L6: =L32 -> 0 | M6: =M32 -> 0 | N6: =N32 -> 0 | O6: =O32 -> 0 | P6: =P32 -> 0 | Q6: =Q32 -> 0 | R6: =R32 -> 0 | S6: =S32 -> 0 | T6: =T37 -> 0
B7: UNSUCCESSFUL | C7: =P14 -> 0 | J7: % | K7: =K32/K31 -> #DIV/0! | L7: =L32/L31 -> #DIV/0! | M7: =M32/M31 -> #DIV/0! | N7: =N32/N31 -> #DIV/0! | O7: =O32/O31 -> #DIV/0! | P7: =P32/P31 -> #DIV/0! | Q7: =Q32/Q31 -> #DIV/0! | R7: =R32/R31 -> #DIV/0! | S7: =S32/S31 -> #DIV/0! | U7: M8 Notes
B8: SUCESSFUL (%) | C8: =P15 -> #DIV/0!
F9: ACTUAL | G9: POTENTIAL | H9: Exc. SUPER
B10: AVERAGE SALE | C10: =P16 -> #DIV/0! | E10: NET PROFIT | F10: =P12 -> 0 | G10: =I31 -> 0 | K10: DAILY NET PROFIT | R10: WEEKDAY | S10: WEEKEND
E11: UNLOCKED | F11: =F6 -> 0.05 | K11: MON | L11: TUE | M11: WED | N11: THU | O11: FRI | P11: Total | Q11: SAT | R11: Awaiting Payment | S11: Awaiting Payment
E12: COMMISSION - PAY OUT | F12: =F10*F11 -> 0 | G12: $- | H12: =F12/1.115 -> 0 | P12: =SUM(K12:O12) -> 0 | Q12: 0 | R12: =0 -> 0 | S12: 0
E13: EMERGENCY | F13: =Q12 -> 0 | G13: $- | J13: Successful | P13: =SUM(K13:O13) -> 0
E14: EMERGENCY - PAY OUT | F14: =F13*0.25 -> 0 | G14: $- | H14: =F14/1.115 -> 0 | J14: Unsuccessful | P14: =SUM(K14:O14) -> 0
E15: PREV. WEEK | G15: $- | J15: Success rate | K15: =K13/(K13+K14) -> #DIV/0! | L15: =L13/(L13+L14) -> #DIV/0! | M15: =M13/(M13+M14) -> #DIV/0! | N15: =N13/(N13+N14) -> #DIV/0! | O15: =O13/(O13+O14) -> #DIV/0! | P15: =P13/(P13+P14) -> #DIV/0! | Q15: =Q13/(Q13+Q14) -> #DIV/0!
E16: PREV. WEEK - PAY OUT | F16: =F15*0.05 -> 0 | G16: $- | H16: =F16/1.115 -> 0 | J16: Avg sale | K16: =K12/K13 -> #DIV/0! | L16: =L12/L13 -> #DIV/0! | M16: =M12/M13 -> #DIV/0! | N16: =N12/N13 -> #DIV/0! | O16: =O12/O13 -> #DIV/0! | P16: =P12/P13 -> #DIV/0! | Q16: =Q12/Q13 -> #DIV/0!
E17: 5 Star Review | H17: =F17/1.115 -> 0
E18: 5 Star Notes | F18: =T7 -> 0 | K18: Managment Summary - SALES ONLY - COLUMN F | R18: WEEKDAY | S18: WEEKEND
E19: 24/06 Reece - 1013735027 - Job 70993 | F19: -189.55 | K19: MON | L19: TUE | M19: WED | N19: THU | O19: FRI | P19: Total | Q19: SAT | R19: Awaiting Payment | S19: Awaiting Payment
Q20: 0 | S20: 0
J21: Successful | K21: =K13 -> 0 | L21: =L13 -> 0 | M21: =M13 -> 0 | N21: =N13 -> 0 | O21: =O13 -> 0 | P21: =P13 -> 0 | Q21: =Q13 -> 0
J22: Unsuccessful | K22: =K14 -> 0 | L22: =L14 -> 0 | M22: =M14 -> 0 | N22: =N14 -> 0 | O22: =O14 -> 0 | P22: =P14 -> 0 | Q22: =Q14 -> 0
J23: Success rate | K23: =K21/(K21+K22) -> #DIV/0! | L23: =L21/(L21+L22) -> #DIV/0! | M23: =M21/(M21+M22) -> #DIV/0! | N23: =N21/(N21+N22) -> #DIV/0! | O23: =O21/(O21+O22) -> #DIV/0! | P23: =P21/(P21+P22) -> #DIV/0! | Q23: =Q21/(Q21+Q22) -> #DIV/0!
J24: Avg sale | K24: =K20/K21 -> #DIV/0! | L24: =L20/L21 -> #DIV/0! | M24: =M20/M21 -> #DIV/0! | N24: =N20/N21 -> #DIV/0! | O24: =O20/O21 -> #DIV/0! | P24: =P20/P21 -> #DIV/0! | Q24: =Q20/Q21 -> #DIV/0!
B27: JOB DETAILS | F27: JOB AMOUNT | K27: PHOTOS | N27: QUOTE | Q27: INVOICE | U27: NOTES
B28: JOB STATUS | C28: DATE | D28: JOB # | E28: SUBURB | F28: AMOUNT EXC. GST | G28: MATERIALS | H28: Merchant Fees | I28: NET PROFIT | J28: PAID | K28: BEFORE | L28: AFTER | M28: RECEIPT | N28: DESCRIPTION | O28: SIGNED | P28: EMAILED | Q28: DESCRIPTION | R28: SIGNED | S28: EMAILED | T28: 5 Star Review | V28: EFTPOS | W28: CASH | X28: Payment Plan
B29: COMPLETED & PAID JOBS
B30: 1 | I30: =F30-G30-H30 -> 0
F31: =SUM(F30:F30) -> 0 | G31: =SUM(G30:G30) -> 0 | H31: =SUM(H30:H30) -> 0 | I31: =SUM(I30:I30) -> 0 | K31: =COUNT(K30:K30) -> 0 | L31: =COUNT(L30:L30) -> 0 | M31: =COUNT(M30:M30) -> 0 | N31: =COUNT(N30:N30) -> 0 | O31: =COUNT(O30:O30) -> 0 | P31: =COUNT(P30:P30) -> 0 | Q31: =COUNT(Q30:Q30) -> 0 | R31: =COUNT(R30:R30) -> 0 | S31: =COUNT(S30:S30) -> 0
K32: =SUM(K30:K30) -> 0 | L32: =SUM(L30:L30) -> 0 | M32: =SUM(M30:M30) -> 0 | N32: =SUM(N30:N30) -> 0 | O32: =SUM(O30:O30) -> 0 | P32: =SUM(P30:P30) -> 0 | Q32: =SUM(Q30:Q30) -> 0 | R32: =SUM(R30:R30) -> 0 | S32: =SUM(S30:S30) -> 0
B34: PREVIOUS JOBS COMPLETED (AWAITING PAYMENT) - Modoras Team Please do ADD to THIS SECTION or AMEND/TOUCH
A35: 0.05 | B35: 1 | C35: 45779 | D35: 55166 | E35: St Kilda | F35: 2024.78 | G35: 39.7 | I35: =F35-G35-H35 -> 1985.08 | K35: 1 | L35: 1 | N35: 1 | O35: 1 | P35: 1 | Q35: 1 | R35: 1 | S35: 1
F36: =SUM(F35:F35) -> 2024.78 | G36: =SUM(G35:G35) -> 39.7 | H36: =SUM(H35:H35) -> 0 | I36: =SUM(I35:I35) -> 1985.08
T37: =SUM(T30:T36) -> 0 | V37: =SUM(V30:V36) -> 0 | W37: =SUM(W30:W36) -> 0 | X37: =SUM(X30:X36) -> 0
B41: WEEKLY COMMISSION | F41: WEEK ENDING | G41: 45851
K42: PHOTOS | N42: QUOTE | Q42: INVOICE
B43: BOOKED JOBS | C43: =C44+C45 -> 22 | E43: WEEKLY TARGET | K43: BEFORE | L43: AFTER | M43: RECEIPT | N43: DESCRIPTION | O43: SIGNED | P43: EMAILED | Q43: DESCRIPTION | R43: SIGNED | S43: EMAILED | T43: 5 Star Review
B44: SUCCESSFUL | C44: =P51 -> 9 | E44: Tier 1 | F44: 0.05 | J44: TAKEN | K44: =K71 -> 2 | L44: =L71 -> 2 | M44: =M71 -> 1 | N44: =N71 -> 2 | O44: =O71 -> 2 | P44: =P71 -> 1 | Q44: =Q71 -> 0 | R44: =R71 -> 0 | S44: =S71 -> 0 | T44: =T106 -> 0
B45: UNSUCCESSFUL | C45: =P52 -> 13 | J45: % | K45: =K71/K70 -> 1 | L45: =L71/L70 -> 1 | M45: =M71/M70 -> 0.5 | N45: =N71/N70 -> 1 | O45: =O71/O70 -> 1 | P45: =P71/P70 -> 0.5 | Q45: =Q71/Q70 -> 0 | R45: =R71/R70 -> 0 | S45: =S71/S70 -> 0 | U45: M8 Notes
B46: SUCESSFUL (%) | C46: =P53 -> 0.40909091
F47: ACTUAL | G47: POTENTIAL | H47: Exc. SUPER
B48: AVERAGE SALE | C48: =P54 -> 5548.7244 | E48: NET PROFIT | F48: =P50 -> 49938.52 | G48: =I70+I82+I88 -> 49938.52 | K48: DAILY NET PROFIT | R48: WEEKDAY | S48: WEEKEND
E49: UNLOCKED | F49: =F44 -> 0.05 | K49: MON | L49: TUE | M49: WED | N49: THU | O49: FRI | P49: Total | Q49: SAT | R49: Awaiting Payment | S49: Awaiting Payment
E50: COMMISSION - PAY OUT | F50: =(F48-I69-I78-I79-I80-I81-I85-I86-I87)*F49 -> -4.5474735e-14 | G50: $- | H50: =F50/1.12 -> -4.0602442e-14 | M50: =I68+I78 -> 11118.99 | N50: =I69+I79+I85 -> 15994.33 | O50: =I80+I81+I86+I87 -> 22825.2 | P50: =SUM(K50:O50) -> 49938.52 | Q50: 0 | R50: =I82+I88 -> 48840.22
E51: EMERGENCY | F51: =Q50 -> 0 | G51: $- | J51: Successful | M51: 2 | N51: 3 | O51: 4 | P51: =SUM(K51:O51) -> 9
E52: EMERGENCY - PAY OUT | F52: =F51*0.25 -> 0 | G52: $- | H52: =F52/1.12 -> 0 | J52: Unsuccessful | M52: 5 | N52: 5 | O52: 3 | P52: =SUM(K52:O52) -> 13
E53: PREV. WEEK | F53: =I75 -> 1985.08 | G53: $- | J53: Success rate | K53: =K51/(K51+K52) -> #DIV/0! | L53: =L51/(L51+L52) -> #DIV/0! | M53: =M51/(M51+M52) -> 0.28571429 | N53: =N51/(N51+N52) -> 0.375 | O53: =O51/(O51+O52) -> 0.57142857 | P53: =P51/(P51+P52) -> 0.40909091 | Q53: =Q51/(Q51+Q52) -> #DIV/0!
E54: PREV. WEEK - PAY OUT | F54: =(F53+F57)*0.05 -> 89.7765 | G54: $- | H54: =F54/1.12 -> 80.157589 | J54: Avg sale | K54: =K50/K51 -> #DIV/0! | L54: =L50/L51 -> #DIV/0! | M54: =M50/M51 -> 5559.495 | N54: =N50/N51 -> 5331.4433 | O54: =O50/O51 -> 5706.3 | P54: =P50/P51 -> 5548.7244 | Q54: =Q50/Q51 -> #DIV/0!
E55: 5 Star Review | H55: =F55/1.12 -> 0
E56: 5 Star Notes | F56: =T45 -> 0 | K56: Managment Summary - SALES ONLY - COLUMN F | R56: WEEKDAY | S56: WEEKEND
E57: 24/06 Reece - 1013735027 - Job 70993 | F57: -189.55 | K57: MON | L57: TUE | M57: WED | N57: THU | O57: FRI | P57: Total | Q57: SAT | R57: Awaiting Payment | S57: Awaiting Payment
M58: =F68+F78 -> 17023 | N58: =F69+F79+F85 -> 18411.6 | O58: =F80+F81+F86+F87 -> 24484 | P58: =SUM(K58:O58) -> 59918.6 | Q58: 0 | R58: =F82+F88 -> 58780.6
J59: Successful | K59: =K51 -> 0 | L59: =L51 -> 0 | M59: =M51 -> 2 | N59: =N51 -> 3 | O59: =O51 -> 4 | P59: =P51 -> 9 | Q59: =Q51 -> 0
J60: Unsuccessful | K60: =K52 -> 0 | L60: =L52 -> 0 | M60: =M52 -> 5 | N60: =N52 -> 5 | O60: =O52 -> 3 | P60: =P52 -> 13 | Q60: =Q52 -> 0
J61: Success rate | K61: =K59/(K59+K60) -> #DIV/0! | L61: =L59/(L59+L60) -> #DIV/0! | M61: =M59/(M59+M60) -> 0.28571429 | N61: =N59/(N59+N60) -> 0.375 | O61: =O59/(O59+O60) -> 0.57142857 | P61: =P59/(P59+P60) -> 0.40909091 | Q61: =Q59/(Q59+Q60) -> #DIV/0!
E62: MODORAS DO NOTE DELETE AS THIS IS THE WORKSHEET FOR W/E 13TH JULY 2025 | J62: Avg sale | K62: =K58/K59 -> #DIV/0! | L62: =L58/L59 -> #DIV/0! | M62: =M58/M59 -> 8511.5 | N62: =N58/N59 -> 6137.2 | O62: =O58/O59 -> 6121 | P62: =P58/P59 -> 6657.6222 | Q62: =Q58/Q59 -> #DIV/0!
B65: JOB DETAILS | F65: JOB AMOUNT | K65: PHOTOS | N65: QUOTE | Q65: INVOICE | U65: NOTES
B66: JOB STATUS | C66: DATE | D66: JOB # | E66: SUBURB | F66: AMOUNT EXC. GST | G66: MATERIALS | H66: Merchant Fees | I66: NET PROFIT | J66: PAID | K66: BEFORE | L66: AFTER | M66: RECEIPT | N66: DESCRIPTION | O66: SIGNED | P66: EMAILED | Q66: DESCRIPTION | R66: SIGNED | S66: EMAILED | T66: 5 Star Review | V66: EFTPOS | W66: CASH | X66: Payment Plan
B67: COMPLETED & PAID JOBS
B68: 1 | C68: 45847 | D68: 71308 | E68: Hampton park | F68: =1138-1138 -> 0 | I68: =F68-G68-H68 -> 0 | J68: Waived | K68: 1 | L68: 1 | M68: 0 | N68: 1 | O68: 1 | P68: 0 | Q68: 0 | R68: 0 | S68: 0 | U68: 09/07 - As per Kris's note - FIRST JOB WAIVED TO WIN DIG.
B69: =B68+1 -> 2 | C69: 45848 | D69: 71383 | E69: Dandenong North | F69: 1138 | G69: =39.7 -> 39.7 | I69: =F69-G69-H69 -> 1098.3 | J69: Card | K69: 1 | L69: 1 | M69: 1 | N69: 1 | O69: 1 | P69: 1 | Q69: 0 | R69: 0 | S69: 0 | U69: 10 Jul - Paying 2hrs O/T | V69: 1251.8
F70: =SUM(F68:F69) -> 1138 | G70: =SUM(G68:G69) -> 39.7 | H70: =SUM(H68:H69) -> 0 | I70: =SUM(I68:I69) -> 1098.3 | K70: =COUNT(K68:K69) -> 2 | L70: =COUNT(L68:L69) -> 2 | M70: =COUNT(M68:M69) -> 2 | N70: =COUNT(N68:N69) -> 2 | O70: =COUNT(O68:O69) -> 2 | P70: =COUNT(P68:P69) -> 2 | Q70: =COUNT(Q68:Q69) -> 2 | R70: =COUNT(R68:R69) -> 2 | S70: =COUNT(S68:S69) -> 2
K71: =SUM(K68:K69) -> 2 | L71: =SUM(L68:L69) -> 2 | M71: =SUM(M68:M69) -> 1 | N71: =SUM(N68:N69) -> 2 | O71: =SUM(O68:O69) -> 2 | P71: =SUM(P68:P69) -> 1 | Q71: =SUM(Q68:Q69) -> 0 | R71: =SUM(R68:R69) -> 0 | S71: =SUM(S68:S69) -> 0
B73: PREVIOUS JOBS COMPLETED & PAID (COMMISSION) - Modoras Team Please do ADD to THIS SECTION or AMEND/TOUCH
A74: 5% - 10 Jul | B74: 1 | C74: 45779 | D74: 55166 | E74: St Kilda | F74: 2024.78 | G74: 39.7 | I74: =F74-G74-H74 -> 1985.08 | J74: EFT | K74: 1 | L74: 1 | M74: 1 | N74: 1 | O74: 1 | P74: 1 | Q74: 1 | R74: 1 | S74: 1 | V74: =2227.26 -> 2227.26
F75: =SUM(F74:F74) -> 2024.78 | G75: =SUM(G74:G74) -> 39.7 | H75: =SUM(H74:H74) -> 0 | I75: =SUM(I74:I74) -> 1985.08
B77: CURRENT JOBS COMPLETED (AWAITING PAYMENT)
A78: 5% - 31/10 CB31/10 | B78: 1 | C78: 45847 | D78: 71349/71308/75003 | E78: Hampton park | F78: 17023 | G78: =39.7+107.63+330+(289.11+195.23)+(37.74)+1500 -> 2499.41 | H78: =F78*0.2 -> 3404.6 | I78: =F78-G78-H78 -> 11118.99 | J78: PP | K78: 1 | L78: 1 | N78: 1 | O78: 1 | P78: 0 | Q78: 1 | R78: 1 | S78: 1 | U78: 31/10-CB by Daniel-CB by reason-Customer had noticed that her drain was not draining away quickly-CB outcome-I Opened up inspection covers , that we had installed prior. Once inspected , I noticed that the water was able to get away . I had a talk with the customer about a tree that was growing over the main run of the sewer drain running to back of her property. I asked the lady if she would like us to look in to it more , She was happy to just wait and see if the drain blocks up again . Jarrod might want to call her and see if he can a up sell.;12/7-Job completed by Alex;11/07 - WIP by Jarrod ; 10/07 - WIP by Daniel B, Rhys ; 09/07 - WIP by Daniel B HUMM app approved
A79: 0.05 | B79: =B78+1 -> 2 | C79: 45848 | D79: 71373 | E79: Mount Eliza | F79: 2681 | G79: =39.7 -> 39.7 | I79: =F79-G79-H79 -> 2641.3 | J79: Card | K79: 1 | L79: 1 | M79: 1 | N79: 1 | O79: 1 | P79: 0 | Q79: 0 | R79: 0 | S79: 0 | V79: 300
A80: 0.05 | B80: =B79+1 -> 3 | C80: 45849 | D80: 71370/86122172 | E80: Dandenong South | F80: =866-85 -> 781 | G80: 39.7 | I80: =F80-G80-H80 -> 741.3 | J80: Card | K80: 1 | L80: 1 | N80: 1 | O80: 1 | P80: 0 | Q80: 1 | R80: 1 | S80: 1 | U80: 14/07 - Uploaded the email to Customer ; 11/07 - POS Receipt for $93.5, $325 not available in SQ portal | V80: =93.5 -> 93.5
A81: 5% - 15 Jul | B81: =B80+1 -> 4 | C81: 45849 | D81: 71370/86122374 | E81: Dandenong South | F81: =2946-85 -> 2861 | G81: 39.7 | I81: =F81-G81-H81 -> 2821.3 | J81: EFT | K81: 1 | L81: 1 | M81: 1 | N81: 1 | O81: 1 | P81: 0 | Q81: 1 | R81: 1 | S81: 1 | U81: 15 Jul - Refund O/Pmt - $177.90 | V81: =3000 -> 3000
F82: =SUM(F78:F81) -> 23346 | G82: =SUM(G78:G81) -> 2618.51 | H82: =SUM(H78:H81) -> 3404.6 | I82: =SUM(I78:I81) -> 17322.89
B84: CURRENT WORK ORDERS (AWAITING PAYMENT)
A85: 0.05 | B85: 1 | C85: 45848 | D85: 71399/71383/86112328 | E85: Dandenong North | F85: 14592.6 | G85: =39.7+306+291+(15.93+73.45+284.68+149.24-76.96)+(254.83)+1000 -> 2337.87 | I85: =F85-G85-H85 -> 12254.73 | J85: Card | K85: 1 | M85: 1 | N85: 1 | O85: 1 | P85: 0 | U85: 14/7-WIP by Tolga & Rhys;13/ 07 WIP by Daniel B ; 11/07 - WIP by Daniel B | V85: =1600+2000 -> 3600
A86: 0.05 | B86: =B85+1 -> 2 | C86: 45849 | D86: 71403/71370/86124652 | E86: Dandenong South | F86: 18161 | G86: =39.7+1500 -> 1539.7 | I86: =F86-G86-H86 -> 16621.3 | K86: 1 | N86: 1 | O86: 1 | P86: 1 | U86: 11/07 Marked as completed no pics available
A87: 0.05 | B87: =B86+1 -> 3 | C87: 45849 | D87: 71276 | E87: Hampton | F87: 2681 | G87: 39.7 | I87: =F87-G87-H87 -> 2641.3 | J87: Card | K87: 1 | M87: 1 | N87: 1 | O87: 1 | P87: 1 | V87: =290 -> 290
F88: =SUM(F85:F87) -> 35434.6 | G88: =SUM(G85:G87) -> 3917.27 | H88: =SUM(H85:H87) -> 0 | I88: =SUM(I85:I87) -> 31517.33
B90: UNSUCCESSFUL JOBS
B91: 1 | C91: 45847 | D91: 71323 | E91: Hampton Park | F91: 1138 | G91: 39.7 | I91: =F91-G91-H91 -> 1098.3 | J91: N/A | K91: 1 | N91: 1 | Q91: 1 | R91: 1 | S91: 1
B92: =B91+1 -> 2 | C92: 45847 | D92: 71319/86090797 | E92: Chelsea | F92: 1281 | G92: 39.7 | I92: =F92-G92-H92 -> 1241.3 | J92: N/A | K92: 1 | N92: 1 | Q92: 1 | R92: 1 | S92: 1
B93: =B92+1 -> 3 | C93: 45847 | D93: 71319/86090804 | E93: Chelsea | F93: 681 | I93: =F93-G93-H93 -> 681 | J93: N/A | K93: 1 | N93: 1 | Q93: 1 | R93: 1 | S93: 1
B94: =B93+1 -> 4 | C94: 45847 | D94: 71319/86091128 | E94: Chelsea | F94: 481 | I94: =F94-G94-H94 -> 481 | J94: N/A | K94: 1 | N94: 1 | Q94: 1 | R94: 1 | S94: 1
B95: =B94+1 -> 5 | C95: 45847 | D95: 71348 | E95: Dandenong North | F95: 6814 | I95: =F95-G95-H95 -> 6814 | J95: N/A | K95: 1 | N95: 1 | Q95: 1 | R95: 1 | S95: 1 | U95: 09/07 Attended by Liam , Jarrod
B96: =B95+1 -> 6 | C96: 45848 | D96: 71333 | E96: Beaumaris | F96: 2861 | G96: =39.7 -> 39.7 | I96: =F96-G96-H96 -> 2821.3 | J96: N/A | K96: 1 | N96: 1 | Q96: 1 | R96: 1 | S96: 1
B97: =B96+1 -> 7 | C97: 45848 | D97: 71355 | E97: Beaumaris | F97: 8214 | G97: =39.7 -> 39.7 | I97: =F97-G97-H97 -> 8174.3 | J97: N/A | K97: 1 | N97: 1
B98: =B97+1 -> 8 | C98: 45848 | D98: 71375 | E98: Mornington | F98: 2681 | G98: 39.7 | I98: =F98-G98-H98 -> 2641.3 | J98: N/A | N98: 1 | Q98: 1 | R98: 1 | S98: 1
B99: =B98+1 -> 9 | C99: 45848 | D99: 71380 | E99: Berwick | F99: 681 | I99: =F99-G99-H99 -> 681 | J99: N/A | K99: 1 | N99: 1 | Q99: 1 | R99: 1 | S99: 1
B100: =B99+1 -> 10 | C100: 45848 | D100: 71341 | E100: Dandenong | F100: 18161 | G100: 39.7 | I100: =F100-G100-H100 -> 18121.3 | J100: N/A | K100: 1 | N100: 1 | Q100: 1 | R100: 1 | S100: 1
B101: =B100+1 -> 11 | C101: 45849 | D101: 71328 | E101: Hughesdale | F101: 1861 | G101: 39.7 | I101: =F101-G101-H101 -> 1821.3 | J101: N/A | K101: 1 | N101: 1 | Q101: 1 | R101: 1 | S101: 1
B102: =B101+1 -> 12 | C102: 45849 | D102: 71396 | E102: Mc Kinnon | F102: 0 | I102: =F102-G102-H102 -> 0 | J102: Quote
B103: =B102+1 -> 13 | C103: 45849 | D103: 71363 | E103: Benleigh | F103: 17861 | G103: 39.7 | I103: =F103-G103-H103 -> 17821.3 | J103: N/A | K103: 1 | N103: 1 | Q103: 1 | R103: 1 | S103: 1
F104: =SUM(F91:F103) -> 62715 | G104: =SUM(G91:G103) -> 317.6 | H104: =SUM(H91:H103) -> 0 | I104: =SUM(I91:I103) -> 62397.4
T106: =SUM(T67:T105) -> 0 | V106: =SUM(V67:V105) -> 10762.56 | W106: =SUM(W67:W105) -> 0 | X106: =SUM(X67:X105) -> 0
B109: WEEKLY COMMISSION | F109: WEEK ENDING | G109: 45858
K110: PHOTOS | N110: QUOTE | Q110: INVOICE
B111: BOOKED JOBS | C111: =C112+C113 -> 36 | E111: WEEKLY TARGET | K111: BEFORE | L111: AFTER | M111: RECEIPT | N111: DESCRIPTION | O111: SIGNED | P111: EMAILED | Q111: DESCRIPTION | R111: SIGNED | S111: EMAILED | T111: 5 Star Review
B112: SUCCESSFUL | C112: =P119 -> 18 | E112: Tier 1 | F112: 0.05 | J112: TAKEN | K112: =K154 -> 17 | L112: =L154 -> 16 | M112: =M154 -> 17 | N112: =N154 -> 16 | O112: =O154 -> 16 | P112: =P154 -> 7 | Q112: =Q154 -> 16 | R112: =R154 -> 11 | S112: =S154 -> 15 | T112: =T199 -> 0
B113: UNSUCCESSFUL | C113: =P120 -> 18 | J113: % | K113: =K154/K153 -> 1 | L113: =L154/L153 -> 0.94117647 | M113: =M154/M153 -> 1 | N113: =N154/N153 -> 0.94117647 | O113: =O154/O153 -> 0.94117647 | P113: =P154/P153 -> 0.41176471 | Q113: =Q154/Q153 -> 0.94117647 | R113: =R154/R153 -> 0.64705882 | S113: =S154/S153 -> 0.88235294 | U113: M8 Notes
B114: SUCESSFUL (%) | C114: =P121 -> 0.5
F115: ACTUAL | G115: POTENTIAL | H115: Exc. SUPER
B116: AVERAGE SALE | C116: =P122 -> 2031.9806 | E116: NET PROFIT | F116: =P118 -> 36575.65 | G116: =I153+I165 -> 36575.65 | K116: DAILY NET PROFIT | R116: WEEKDAY | S116: WEEKEND
E117: UNLOCKED | F117: =F112 -> 0.05 | K117: MON | L117: TUE | M117: WED | N117: THU | O117: FRI | P117: Total | Q117: SAT | R117: Awaiting Payment | S117: Awaiting Payment
...

Sheet Liam
B3: WEEKLY COMMISSION | F3: WEEK ENDING | G3: 45837
K4: PHOTOS | N4: QUOTE | Q4: INVOICE
B5: BOOKED JOBS | C5: =C6+C7 -> 32 | E5: WEEKLY TARGET | K5: BEFORE | L5: AFTER | M5: RECEIPT | N5: DESCRIPTION | O5: SIGNED | P5: EMAILED | Q5: DESCRIPTION | R5: SIGNED | S5: EMAILED | T5: 5 Star Review
B6: SUCCESSFUL | C6: =P13 -> 11 | E6: Tier 1 | F6: 0.05 | J6: TAKEN | K6: =K39 -> 8 | L6: =L39 -> 8 | M6: =M39 -> 8 | N6: =N39 -> 8 | O6: =O39 -> 8 | P6: =P39 -> 0 | Q6: =Q39 -> 6 | R6: =R39 -> 6 | S6: =S39 -> 3 | T6: =T82 -> 0
B7: UNSUCCESSFUL | C7: =P14 -> 21 | J7: % | K7: =K39/K38 -> 1 | L7: =L39/L38 -> 1 | M7: =M39/M38 -> 1 | N7: =N39/N38 -> 1 | O7: =O39/O38 -> 1 | P7: =P39/P38 -> 0 | Q7: =Q39/Q38 -> 0.75 | R7: =R39/R38 -> 0.75 | S7: =S39/S38 -> 0.375 | U7: M8 Notes
B8: SUCESSFUL (%) | C8: =P15 -> 0.34375
F9: ACTUAL | G9: POTENTIAL | H9: Exc. SUPER
B10: AVERAGE SALE | C10: =P16 -> 2564.1836 | E10: NET PROFIT | F10: =P12 -> 28206.02 | G10: =I38+I50 -> 28206.02 | K10: DAILY NET PROFIT | R10: WEEKDAY | S10: WEEKEND
E11: UNLOCKED | F11: =F6 -> 0.05 | K11: MON | L11: TUE | M11: WED | N11: THU | O11: FRI | P11: Total | Q11: SAT | R11: Awaiting Payment | S11: Awaiting Payment
E12: COMMISSION - PAY OUT | F12: =(F10-I31-I32-I36-I47-I48-I49)*F11 -> 288.9695 | G12: $- | H12: =F12/1.12 -> 258.00848 | L12: =I31+I30+I32 -> 1685.12 | M12: =I33+I34 -> 902 | N12: =I35+I36+I47+I48 -> 18336.35 | O12: =I37+I49 -> 7282.55 | P12: =SUM(K12:O12) -> 28206.02 | Q12: 0 | R12: =I50 -> 20948.63 | S12: 0
E13: EMERGENCY | F13: =Q12 -> 0 | G13: $- | J13: Successful | K13: 0 | L13: 3 | M13: 2 | N13: 4 | O13: 2 | P13: =SUM(K13:O13) -> 11
E14: EMERGENCY - PAY OUT | F14: =F13*0.25 -> 0 | G14: $- | H14: =F14/1.12 -> 0 | J14: Unsuccessful | K14: 3 | L14: 6 | M14: 4 | N14: 2 | O14: 6 | P14: =SUM(K14:O14) -> 21
E15: PREV. WEEK | F15: =I44 -> 14904.2 | G15: $- | J15: Success rate | K15: =K13/(K13+K14) -> 0 | L15: =L13/(L13+L14) -> 0.33333333 | M15: =M13/(M13+M14) -> 0.33333333 | N15: =N13/(N13+N14) -> 0.66666667 | O15: =O13/(O13+O14) -> 0.25 | P15: =P13/(P13+P14) -> 0.34375 | Q15: =Q13/(Q13+Q14) -> #DIV/0!
E16: PREV. WEEK - PAY OUT | F16: =(F15+F19+F20-I43)*0.05 -> 715.565 | G16: $- | H16: =F16/1.12 -> 638.89732 | J16: Avg sale | K16: =K12/K13 -> #DIV/0! | L16: =L12/L13 -> 561.70667 | M16: =M12/M13 -> 451 | N16: =N12/N13 -> 4584.0875 | O16: =O12/O13 -> 3641.275 | P16: =P12/P13 -> 2564.1836 | Q16: =Q12/Q13 -> #DIV/0!
E17: 5 Star Review | H17: =F17/1.12 -> 0
E18: 5 Star Notes | F18: =T7 -> 0 | K18: Managment Summary - SALES ONLY - COLUMN F | R18: WEEKDAY | S18: WEEKEND
E19: 26 Jun - Fresh Screens - Job 70764 | F19: =-548.9 -> -548.9 | K19: MON | L19: TUE | M19: WED | N19: THU | O19: FRI | P19: Total | Q19: SAT | R19: Awaiting Payment | S19: Awaiting Payment
E20: 30 Jun - Job 71051 | F20: =-44 -> -44 | L20: =F31+F30+F32 -> 1861.2 | M20: =F33+F34 -> 902 | N20: =F35+F36+F47+F48 -> 21512 | O20: =F37+F49 -> 8628 | P20: =SUM(K20:O20) -> 32903.2 | Q20: 0 | R20: =F50 -> 24584 | S20: 0
J21: Successful | K21: =K13 -> 0 | L21: =L13 -> 3 | M21: =M13 -> 2 | N21: =N13 -> 4 | O21: =O13 -> 2 | P21: =P13 -> 11 | Q21: =Q13 -> 0
J22: Unsuccessful | K22: =K14 -> 3 | L22: =L14 -> 6 | M22: =M14 -> 4 | N22: =N14 -> 2 | O22: =O14 -> 6 | P22: =P14 -> 21 | Q22: =Q14 -> 0
J23: Success rate | K23: =K21/(K21+K22) -> 0 | L23: =L21/(L21+L22) -> 0.33333333 | M23: =M21/(M21+M22) -> 0.33333333 | N23: =N21/(N21+N22) -> 0.66666667 | O23: =O21/(O21+O22) -> 0.25 | P23: =P21/(P21+P22) -> 0.34375 | Q23: =Q21/(Q21+Q22) -> #DIV/0!
J24: Avg sale | K24: =K20/K21 -> #DIV/0! | L24: =L20/L21 -> 620.4 | M24: =M20/M21 -> 451 | N24: =N20/N21 -> 5378 | O24: =O20/O21 -> 4314 | P24: =P20/P21 -> 2991.2 | Q24: =Q20/Q21 -> #DIV/0!
B27: JOB DETAILS | F27: JOB AMOUNT | K27: PHOTOS | N27: QUOTE | Q27: INVOICE | U27: NOTES
B28: JOB STATUS | C28: DATE | D28: JOB # | E28: SUBURB | F28: AMOUNT EXC. GST | G28: MATERIALS | H28: Merchant Fees | I28: NET PROFIT | J28: PAID | K28: BEFORE | L28: AFTER | M28: RECEIPT | N28: DESCRIPTION | O28: SIGNED | P28: EMAILED | Q28: DESCRIPTION | R28: SIGNED | S28: EMAILED | T28: 5 Star Review | V28: EFTPOS | W28: CASH | X28: Payment Plan
B29: COMPLETED & PAID JOBS
B30: 1 | C30: 45832 | D30: 70981 | E30: Mitcham | F30: 864.2 | G30: =39.7+(136.38) -> 176.08 | I30: =F30-G30-H30 -> 688.12 | J30: Card/EFT | K30: 1 | L30: 1 | M30: 1 | N30: 1 | O30: 1 | P30: 0 | Q30: 0 | R30: 0 | S30: 0 | U30: 25/06 - WIP & Completed by Jack M; 24/06 - EFT processed for $400 | V30: =400+550.62 -> 950.62
B31: =B30+1 -> 2 | C31: 45832 | D31: 70983 | E31: Ringwood | F31: 316 | I31: =F31-G31-H31 -> 316 | J31: Card | K31: 1 | L31: 1 | M31: 1 | N31: 1 | O31: 1 | P31: 0 | Q31: 0 | R31: 0 | S31: 0 | U31: 24 Jun - Paying 30mins O/T | V31: 347.6
B32: =B31+1 -> 3 | C32: 45832 | D32: 70978 | E32: Blackburn | F32: 681 | I32: =F32-G32-H32 -> 681 | J32: Card | K32: 1 | L32: 1 | M32: 1 | N32: 1 | O32: 1 | P32: 0 | Q32: 1 | R32: 1 | S32: 1 | U32: 24 Jun - Paying 1.25hr O/T | V32: 749.1
B33: =B32+1 -> 4 | C33: 45833 | D33: 70971 | E33: Mitcham | F33: 421 | I33: =F33-G33-H33 -> 421 | J33: Card | K33: 1 | L33: 1 | M33: 1 | N33: 1 | O33: 1 | P33: 0 | Q33: 1 | R33: 1 | S33: 0 | V33: 463.1
B34: =B33+1 -> 5 | C34: 45833 | D34: 70878 | E34: Burnwood East | F34: 481 | I34: =F34-G34-H34 -> 481 | J34: EFT | K34: 1 | L34: 1 | M34: 1 | N34: 1 | O34: 1 | P34: 0 | Q34: 1 | R34: 1 | S34: 1 | U34: 01/07 - Scheduled to Liam ; 30/06 - Schuduled for Shaun ; 25/06 - EFT Received $529.10 | V34: 529.1
B35: =B34+1 -> 6 | C35: 45834 | D35: 70934 | E35: Melbourne | F35: 2261 | G35: =39.7+33+(34.79)+200 -> 307.49 | I35: =F35-G35-H35 -> 1953.51 | J35: EFT | K35: 1 | L35: 1 | M35: 1 | N35: 1 | O35: 1 | P35: 0 | Q35: 1 | R35: 1 | S35: 1 | U35: 26/06 - WIP&Completed by Liam ,Matthew H, EFT Received $240,$2247.10 | V35: =240+2247.1 -> 2487.1
B36: =B35+1 -> 7 | C36: 45834 | D36: 71040 | E36: Glenroy | F36: 481 | I36: =F36-G36-H36 -> 481 | J36: EFT | K36: 1 | L36: 1 | M36: 1 | N36: 1 | O36: 1 | P36: 0 | Q36: 1 | R36: 1 | S36: 0 | U36: 26 Jun - Paying 30mins O/T; 26/06 - EFT Received $529.10 | V36: 529.1
B37: =B36+1 -> 8 | C37: 45835 | D37: 71045 | E37: Coburg | F37: 2814 | G37: =39.7+(66.06+32.77+239.71)+200 -> 578.24 | I37: =F37-G37-H37 -> 2235.76 | J37: Card/EFT | K37: 1 | L37: 1 | M37: 1 | N37: 1 | O37: 1 | P37: 0 | Q37: 1 | R37: 1 | S37: 0 | U37: 27/06 - WIP&Completed by Liam, Matthew H - EFT processed for $2789.10 | V37: =306+2789.1 -> 3095.1
F38: =SUM(F30:F37) -> 8319.2 | G38: =SUM(G30:G37) -> 1061.81 | H38: =SUM(H30:H37) -> 0 | I38: =SUM(I30:I37) -> 7257.39 | K38: =COUNT(K30:K37) -> 8 | L38: =COUNT(L30:L37) -> 8 | M38: =COUNT(M30:M37) -> 8 | N38: =COUNT(N30:N37) -> 8 | O38: =COUNT(O30:O37) -> 8 | P38: =COUNT(P30:P37) -> 8 | Q38: =COUNT(Q30:Q37) -> 8 | R38: =COUNT(R30:R37) -> 8 | S38: =COUNT(S30:S37) -> 8
K39: =SUM(K30:K37) -> 8 | L39: =SUM(L30:L37) -> 8 | M39: =SUM(M30:M37) -> 8 | N39: =SUM(N30:N37) -> 8 | O39: =SUM(O30:O37) -> 8 | P39: =SUM(P30:P37) -> 0 | Q39: =SUM(Q30:Q37) -> 6 | R39: =SUM(R30:R37) -> 6 | S39: =SUM(S30:S37) -> 3
B41: PREVIOUS JOBS COMPLETED & PAID (COMMISSION) - Modoras Team Please do ADD to THIS SECTION or AMEND/TOUCH
A42: 5% - 24 June | B42: 1 | C42: 45824 | D42: 70798/85819651 | E42: Fairfield | F42: 16840 | G42: =39.7+225.8+(18.96)+(151.34)+1500 -> 1935.8 | I42: =F42-G42-H42 -> 14904.2 | J42: Card/EFT | K42: 1 | L42: 1 | M42: 1 | N42: 1 | O42: 1 | P42: 0 | Q42: 1 | R42: 1 | S42: 0 | U42: 23 Jun - Completed by Jarrod , Liam ; 20/06 - WIP by Jarrod ; 19/06 - WIP by Jarrod, Alex; 18/06 - WIP by Jarrod , Shaun , 17/06 - WIP by Alex ; 16/06 WIP by Alex,Liam | V42: =14344 -> 14344
A43: 5% - 30 Jun - Cancelled | B43: =B42+1 -> 2 | C43: 45828 | D43: 70839/85864870 | E43: Hadfield | F43: =14950-14950 -> 0 | G43: =39.7-39.7 -> 0 | I43: =F43-G43-H43 -> 0 | J43: Cash | K43: 1 | L43: 1 | M43: 1 | N43: 1 | O43: 1 | P43: 0 | Q43: 0 | R43: 0 | S43: 0 | U43: 21/06 - WIP&Completed by Daniel B ; 20/06 - WIP by Alex , Liam
F44: =SUM(F42:F43) -> 16840 | G44: =SUM(G42:G43) -> 1935.8 | H44: =SUM(H42:H43) -> 0 | I44: =SUM(I42:I43) -> 14904.2
B46: CURRENT WORK ORDERS (AWAITING PAYMENT)
A47: 0.05 | B47: 1 | C47: 45834 | D47: 71020/85931776 | E47: Kingsville | F47: 5956 | G47: =39.7+(101.75+99.17+92.52)+(17.71+284.61+439.62)+300 -> 1375.08 | I47: =F47-G47-H47 -> 4580.92 | J47: Card | K47: 1 | L47: 1 | M47: 1 | N47: 1 | O47: 1 | P47: 0 | Q47: 0 | R47: 0 | S47: 0 | U47: 1 Jul - Job Completed by Daniel B; 30/06 - WIP by Daniel B ; 27/06 - Scheduled for Jarrod, Mathew B, Matthew H ; 26/06 - WIP by Tolga , Alex , Liam | V47: =655.16 -> 655.16
A48: 0.05 | B48: =B47+1 -> 2 | C48: 45834 | D48: 71020/85936778 | E48: Kingsville | F48: 12814 | G48: =39.7+(453.38)+1000 -> 1493.08 | I48: =F48-G48-H48 -> 11320.92 | J48: Card | K48: 1 | L48: 1 | M48: 1 | N48: 1 | O48: 1 | P48: 0 | Q48: 0 | R48: 0 | S48: 0 | U48: 1 Jul - Job Completed by Daniel B; 30/06 - WIP by Daniel B ; 27/06 - Scheduled for Jarrod, Mathew B, Matthew H; 26/06 - WIP by Tolga , Alex , Liam | V48: =1999.18 -> 1999.18
A49: 0.05 | B49: =B48+1 -> 3 | C49: 45835 | D49: 71077 | E49: Burnswick | F49: 5814 | G49: =39.7+(727.51) -> 767.21 | I49: =F49-G49-H49 -> 5046.79 | J49: Card/Cash | K49: 1 | M49: 1 | N49: 1 | O49: 1 | P49: 0 | U49: 07/07 - Cash Deposit Receipt uploaded for $600 ; 27 Jun - Deduct 1.25hrs O/T; 30/06 - WIP & Completed by Daniel B , Liam ; 27/06 - WIP by Matthew H ,Liam | V49: 5500 | W49: 600
F50: =SUM(F47:F49) -> 24584 | G50: =SUM(G47:G49) -> 3635.37 | H50: =SUM(H47:H49) -> 0 | I50: =SUM(I47:I49) -> 20948.63
B52: PREVIOUS WORK ORDERS (AWAITING PAYMENT) - Modoras Team Please do ADD to THIS SECTION or AMEND/TOUCH
A53: 0.05 | B53: 1 | C53: 45812 | D53: 70547/85680627 | E53: Brunswick West | F53: 18061 | G53: =39.7+(62.91)+(10.95+18.17+8.58+185.26+145.2+166.5+178.78)+1500 -> 2316.05 | I53: =F53-G53-H53 -> 15744.95 | J53: Card | K53: 1 | M53: 1 | N53: 1 | O53: 1 | P53: 1 | U53: 20/06 - WIP by Alex, Daniel B ; 19/06 - WIP by Daniel B ; 17/06 - WIP by Daniel B; 16/06 - WIP by Daniel B , Alex; 13/06 - WIP by Daniel; 12/06 - WIP by Daniel B. EFT processed for $3000; 11/06 - WIP by Daniel B; 10/06 - WIP by Daniel B, Matthew . EFT Amount recevied $3000; 06/06 - WIP by DanielB, Alex; 05/06 - WIP by Tolga, DanielB , Alex,Liam; 04/06-WIP by Liam,Ben,Jarrod,Tolga,Alex. Card payment recieved $1800
A54: 0.05 | B54: =B53+1 -> 2 | C54: 45813 | D54: 70547/85703766 | E54: Brunswick West | F54: 22614 | G54: =39.7+47.8+356+(396.09)+(145.2-4.72-2.08+8.58-185.26+9.17+5.35+223.39)+2000 -> 3039.22 | I54: =F54-G54-H54 -> 19574.78 | K54: 1 | N54: 1 | O54: 1 | P54: 0 | U54: 20/06 - WIP by Alex, Daniel B ; 19/06 - WIP by Daniel B ; 17/06 - WIP by Daniel B EFT processed for $5000 ; 16/06 - WIP by Daniel B , Alex EFT processed for $3000; 13/06 - WIP by Daniel; 12/06 - WIP by Daniel B; 11/06 - WIP by Daniel B; 10/06 - WIP by Daniel B, Matthew; 06/06 - WIP by DanielB, Alex; 05/06 - WIP by Tolga, DanielB , Alex,Liam
A55: 0.05 | B55: =B54+1 -> 3 | C55: 45820 | D55: 70685/85790827 | E55: Abbotsford | F55: =5553-610 -> 4943 | G55: =39.7+1500 -> 1539.7 | I55: =F55-G55-H55 -> 3403.3 | K55: 1 | N55: 1 | O55: 1 | P55: 0 | U55: 25 Jun Refunded $610. 23/06 - Cash of $2000 Deposited By Liam ; 19/06-Attended by Liam - Received $610 Cash
F56: =SUM(F53:F55) -> 45618 | G56: =SUM(G53:G55) -> 6894.97 | H56: =SUM(H53:H55) -> 0 | I56: =SUM(I53:I55) -> 38723.03
B58: UNSUCCESSFUL JOBS
B59: 1 | C59: 45831 | D59: 70927 | E59: Templestove Lower | F59: 2261 | G59: 39.7 | I59: =F59-G59-H59 -> 2221.3 | J59: N/A | K59: 1 | N59: 1
B60: =B59+1 -> 2 | C60: 45831 | D60: 70939 | E60: Kew | F60: 1138 | G60: 39.7 | I60: =F60-G60-H60 -> 1098.3 | J60: N/A | N60: 1
B61: =B60+1 -> 3 | C61: 45831 | D61: 70935 | E61: Blackburn North | F61: 681 | I61: =F61-G61-H61 -> 681 | J61: N/A | K61: 1 | N61: 1
B62: =B61+1 -> 4 | C62: 45832 | D62: 70954 | E62: South Yarra | F62: 1261 | G62: 39.7 | I62: =F62-G62-H62 -> 1221.3 | J62: Card | K62: 1 | M62: 1 | N62: 1 | U62: 24/06 - COF collected Not avilable in Invoice tab | V62: 93.5
B63: =B62+1 -> 5 | C63: 45832 | D63: 70958 | E63: South Yarra | F63: 6526 | G63: 39.7 | I63: =F63-G63-H63 -> 6486.3 | J63: N/A | K63: 1 | M63: 1 | N63: 1 | V63: 93.5
B64: =B63+1 -> 6 | C64: 45832 | D64: 70969 | E64: South Yarra | F64: 861 | G64: 39.7 | I64: =F64-G64-H64 -> 821.3 | J64: N/A | K64: 1 | N64: 1
B65: =B64+1 -> 7 | C65: 45832 | D65: 70981/85896172 | E65: Mitcham | F65: 2801 | G65: 39.7 | I65: =F65-G65-H65 -> 2761.3 | J65: N/A | K65: 1 | N65: 1
B66: =B65+1 -> 8 | C66: 45832 | D66: 70983/85898866 | E66: Ringwood | F66: 5814 | G66: 39.7 | I66: =F66-G66-H66 -> 5774.3 | J66: N/A | K66: 1 | N66: 1
B67: =B66+1 -> 9 | C67: 45832 | D67: 70986 | E67: Waverley | F67: 681 | I67: =F67-G67-H67 -> 681 | J67: N/A | K67: 1 | N67: 1
B68: =B67+1 -> 10 | C68: 45832 | D68: 70978/85900928 | E68: Blackburn | F68: 5814 | G68: 39.7 | I68: =F68-G68-H68 -> 5774.3 | J68: N/A | K68: 1 | N68: 1
B69: =B68+1 -> 11 | C69: 45833 | D69: 71025 | E69: Glen Huntly | F69: 1261 | G69: 39.7 | I69: =F69-G69-H69 -> 1221.3 | J69: N/A | K69: 1 | N69: 1
B70: =B69+1 -> 12 | C70: 45833 | D70: 71000 | E70: Glen Huntly | F70: 1681 | G70: 39.7 | I70: =F70-G70-H70 -> 1641.3 | J70: N/A | N70: 1
B71: =B70+1 -> 13 | C71: 45833 | D71: 70854 | E71: Elwood | F71: 0 | I71: =F71-G71-H71 -> 0 | J71: Quote
B72: =B71+1 -> 14 | C72: 45833 | D72: 71009 | E72: North Melbourne | F72: 861 | G72: 39.7 | I72: =F72-G72-H72 -> 821.3 | J72: N/A | K72: 1 | N72: 1
B73: =B72+1 -> 15 | C73: 45834 | D73: 71027 | E73: Melbourne | F73: 1681 | G73: 39.7 | I73: =F73-G73-H73 -> 1641.3 | J73: N/A | K73: 1 | N73: 1
B74: =B73+1 -> 16 | C74: 45834 | D74: 71044 | E74: Bundoora | F74: 0 | I74: =F74-G74-H74 -> 0 | J74: Quote | K74: 1
B75: =B74+1 -> 17 | C75: 45835 | D75: 71053 | E75: Mill Park | F75: 2242 | G75: 39.7 | I75: =F75-G75-H75 -> 2202.3 | J75: N/A | K75: 1 | N75: 1
B76: =B75+1 -> 18 | C76: 45835 | D76: 71046/85945280 | E76: Coburg | F76: 1138 | G76: 39.7 | I76: =F76-G76-H76 -> 1098.3 | J76: N/A | N76: 1
B77: =B76+1 -> 19 | C77: 45835 | D77: 71046/85946904 | E77: Coburg | F77: 23426 | G77: 39.7 | I77: =F77-G77-H77 -> 23386.3 | J77: N/A | N77: 1
B78: =B77+1 -> 20 | C78: 45835 | D78: 71072/85947863 | E78: Heidelberg | F78: 0 | J78: N/A | K78: 1 | N78: 1
B79: =B78+1 -> 21 | C79: 45835 | D79: 71072/85948524 | E79: Heidelberg | F79: 1138 | G79: 39.7 | I79: =F79-G79-H79 -> 1098.3 | J79: N/A | K79: 1 | N79: 1
B80: =B79+1 -> 22 | C80: 45835 | D80: 71071 | E80: Pascoe Vale | F80: 1168 | G80: 39.7 | I80: =F80-G80-H80 -> 1128.3 | J80: N/A | N80: 1
F81: =SUM(F59:F80) -> 62434 | G81: =SUM(G59:G80) -> 674.9 | H81: =SUM(H59:H80) -> 0 | I81: =SUM(I59:I80) -> 61759.1
T82: =SUM(T30:T81) -> 0 | V82: =SUM(V30:V81) -> 31836.16 | W82: =SUM(W30:W81) -> 600 | X82: =SUM(X30:X81) -> 0
B86: WEEKLY COMMISSION | F86: WEEK ENDING | G86: 45844
K87: PHOTOS | N87: QUOTE | Q87: INVOICE
B88: BOOKED JOBS | C88: =C89+C90 -> 35 | E88: WEEKLY TARGET | K88: BEFORE | L88: AFTER | M88: RECEIPT | N88: DESCRIPTION | O88: SIGNED | P88: EMAILED | Q88: DESCRIPTION | R88: SIGNED | S88: EMAILED | T88: 5 Star Review
B89: SUCCESSFUL | C89: =P96 -> 14 | E89: Tier 1 | F89: 0.05 | J89: TAKEN | K89: =K125 -> 11 | L89: =L125 -> 11 | M89: =M125 -> 11 | N89: =N125 -> 11 | O89: =O125 -> 11 | P89: =P125 -> 1 | Q89: =Q125 -> 8 | R89: =R125 -> 8 | S89: =S125 -> 4 | T89: =T168 -> 0
B90: UNSUCCESSFUL | C90: =P97 -> 21 | J90: % | K90: =K125/K124 -> 1 | L90: =L125/L124 -> 1 | M90: =M125/M124 -> 1 | N90: =N125/N124 -> 1 | O90: =O125/O124 -> 1 | P90: =P125/P124 -> 0.090909091 | Q90: =Q125/Q124 -> 0.72727273 | R90: =R125/R124 -> 0.72727273 | S90: =S125/S124 -> 0.36363636 | T90: 1 | U90: M8 Notes
B91: SUCESSFUL (%) | C91: =P98 -> 0.4
F92: ACTUAL | G92: POTENTIAL | H92: Exc. SUPER
B93: AVERAGE SALE | C93: =P99 -> 2593.0079 | E93: NET PROFIT | F93: =P95 -> 36302.11 | G93: =I124+I134+I138 -> 36302.11 | K93: DAILY NET PROFIT | R93: WEEKDAY | S93: WEEKEND
E94: UNLOCKED | F94: =F89 -> 0.05 | K94: MON | L94: TUE | M94: WED | N94: THU | O94: FRI | P94: Total | Q94: SAT | R94: Awaiting Payment | S94: Awaiting Payment
E95: COMMISSION - PAY OUT | F95: =(F93-I120-I132-I133-I137)*F94 -> 960.1655 | G95: $- | H95: =F95/1.12 -> 857.29062 | K95: =I113+I114 -> 3754.66 | L95: =+I115+I116 -> 5126.75 | M95: =+I117+I118+I133+I132+I119+I137 -> 20237.1 | N95: =I120 -> 985.3 | O95: =I121+I122+I123 -> 6198.3 | P95: =SUM(K95:O95) -> 36302.11 | Q95: 0 | R95: =I134+I138 -> 16113.5
E96: EMERGENCY | F96: =Q95 -> 0 | G96: $- | J96: Successful | K96: 2 | L96: 2 | M96: 6 | N96: 1 | O96: 3 | P96: =SUM(K96:O96) -> 14
E97: EMERGENCY - PAY OUT | F97: =F96*0.25 -> 0 | G97: $- | H97: =F97/1.12 -> 0 | J97: Unsuccessful | K97: 4 | L97: 4 | M97: 2 | N97: 3 | O97: 8 | P97: =SUM(K97:O97) -> 21
E98: PREV. WEEK | F98: =I128 -> 3403.3 | G98: $- | J98: Success rate | K98: =K96/(K96+K97) -> 0.33333333 | L98: =L96/(L96+L97) -> 0.33333333 | M98: =M96/(M96+M97) -> 0.75 | N98: =N96/(N96+N97) -> 0.25 | O98: =O96/(O96+O97) -> 0.27272727 | P98: =P96/(P96+P97) -> 0.4 | Q98: =Q96/(Q96+Q97) -> #DIV/0!
E99: PREV. WEEK - PAY OUT | F99: =(F98-I128)*0.05 -> 0 | G99: $- | H99: =F99/1.12 -> 0 | J99: Avg sale | K99: =K95/K96 -> 1877.33 | L99: =L95/L96 -> 2563.375 | M99: =M95/M96 -> 3372.85 | N99: =N95/N96 -> 985.3 | O99: =O95/O96 -> 2066.1 | P99: =P95/P96 -> 2593.0079 | Q99: =Q95/Q96 -> #DIV/0!
E100: 5 Star Review | H100: =F100/1.12 -> 0
E101: 5 Star Notes | F101: =T90 -> 1 | K101: Managment Summary - SALES ONLY - COLUMN F | R101: WEEKDAY | S101: WEEKEND
K102: MON | L102: TUE | M102: WED | N102: THU | O102: FRI | P102: Total | Q102: SAT | R102: Awaiting Payment | S102: Awaiting Payment
K103: =F113+F114 -> 4285 | L103: =+F115+F116 -> 5475 | M103: =+F117+F118+F133+F132+F119+F137 -> 21959 | N103: =F120 -> 1025 | O103: =F121+F122+F123 -> 6238 | P103: =SUM(K103:O103) -> 38982 | Q103: 0 | R103: =F134+F138 -> 17756
J104: Successful | K104: =K96 -> 2 | L104: =L96 -> 2 | M104: =M96 -> 6 | N104: =N96 -> 1 | O104: =O96 -> 3 | P104: =P96 -> 14 | Q104: =Q96 -> 0
J105: Unsuccessful | K105: =K97 -> 4 | L105: =L97 -> 4 | M105: =M97 -> 2 | N105: =N97 -> 3 | O105: =O97 -> 8 | P105: =P97 -> 21 | Q105: =Q97 -> 0
J106: Success rate | K106: =K104/(K104+K105) -> 0.33333333 | L106: =L104/(L104+L105) -> 0.33333333 | M106: =M104/(M104+M105) -> 0.75 | N106: =N104/(N104+N105) -> 0.25 | O106: =O104/(O104+O105) -> 0.27272727 | P106: =P104/(P104+P105) -> 0.4 | Q106: =Q104/(Q104+Q105) -> #DIV/0!
J107: Avg sale | K107: =K103/K104 -> 2142.5 | L107: =L103/L104 -> 2737.5 | M107: =M103/M104 -> 3659.8333 | N107: =N103/N104 -> 1025 | O107: =O103/O104 -> 2079.3333 | P107: =P103/P104 -> 2784.4286 | Q107: =Q103/Q104 -> #DIV/0!
B110: JOB DETAILS | F110: JOB AMOUNT | K110: PHOTOS | N110: QUOTE | Q110: INVOICE | U110: NOTES
B111: JOB STATUS | C111: DATE | D111: JOB # | E111: SUBURB | F111: AMOUNT EXC. GST | G111: MATERIALS | H111: Merchant Fees | I111: NET PROFIT | J111: PAID | K111: BEFORE | L111: AFTER | M111: RECEIPT | N111: DESCRIPTION | O111: SIGNED | P111: EMAILED | Q111: DESCRIPTION | R111: SIGNED | S111: EMAILED | T111: 5 Star Review | V111: EFTPOS | W111: CASH | X111: Payment Plan
B112: COMPLETED & PAID JOBS
B113: 1 | C113: 45838 | D113: 71051 | E113: Burnswick | F113: 2604 | G113: =39.7+44+(206.94)+200 -> 490.64 | I113: =F113-G113-H113 -> 2113.36 | J113: Card | K113: 1 | L113: 1 | M113: 1 | N113: 1 | O113: 1 | P113: 0 | Q113: 1 | R113: 1 | S113: 1 | T113: Customer tested and happy job complete didn't have time for a review | U113: 01/07 Reimbursed $44.00 EFT receipt uploaded ; .30/06 - WIP by Tolga , Liam | V113: =280+2584.4 -> 2864.4
...

Sheet Matthew H - No OT
B3: WEEKLY COMMISSION | F3: WEEK ENDING | G3: 45851
K4: PHOTOS | N4: QUOTE | Q4: INVOICE
B5: BOOKED JOBS | C5: =C6+C7 -> 2 | E5: WEEKLY TARGET | K5: BEFORE | L5: AFTER | M5: RECEIPT | N5: DESCRIPTION | O5: SIGNED | P5: EMAILED | Q5: DESCRIPTION | R5: SIGNED | S5: EMAILED | T5: 5 Star Review
B6: SUCCESSFUL | C6: =P13 -> 0 | E6: Tier 1 | F6: 0.05 | J6: TAKEN | K6: =K32 -> 0 | L6: =L32 -> 0 | M6: =M32 -> 0 | N6: =N32 -> 0 | O6: =O32 -> 0 | P6: =P32 -> 0 | Q6: =Q32 -> 0 | R6: =R32 -> 0 | S6: =S32 -> 0 | T6: =T38 -> 0
B7: UNSUCCESSFUL | C7: =P14 -> 2 | J7: % | K7: =K32/K31 -> #DIV/0! | L7: =L32/L31 -> #DIV/0! | M7: =M32/M31 -> #DIV/0! | N7: =N32/N31 -> #DIV/0! | O7: =O32/O31 -> #DIV/0! | P7: =P32/P31 -> #DIV/0! | Q7: =Q32/Q31 -> #DIV/0! | R7: =R32/R31 -> #DIV/0! | S7: =S32/S31 -> #DIV/0! | U7: M8 Notes
B8: SUCESSFUL (%) | C8: =P15 -> 0
F9: ACTUAL | G9: POTENTIAL | H9: Exc. SUPER
B10: AVERAGE SALE | C10: =P16 -> #DIV/0! | E10: NET PROFIT | F10: =P12 -> 0 | G10: =I31 -> 0 | K10: DAILY NET PROFIT | R10: WEEKDAY | S10: WEEKEND
E11: UNLOCKED | F11: =F6 -> 0.05 | K11: MON | L11: TUE | M11: WED | N11: THU | O11: FRI | P11: Total | Q11: SAT | R11: Awaiting Payment | S11: Awaiting Payment
E12: COMMISSION - PAY OUT | F12: =F10*F11 -> 0 | G12: $- | H12: =F12/1.12 -> 0 | P12: =SUM(K12:O12) -> 0 | Q12: 0 | R12: =0 -> 0 | S12: =0 -> 0
E13: EMERGENCY | F13: =Q12 -> 0 | G13: $- | J13: Successful | M13: 0 | P13: =SUM(K13:O13) -> 0
E14: EMERGENCY - PAY OUT | F14: =F13*0.25 -> 0 | G14: $- | H14: =F14/1.12 -> 0 | J14: Unsuccessful | M14: 2 | P14: =SUM(K14:O14) -> 2
E15: PREV. WEEK | G15: $- | J15: Success rate | K15: =K13/(K13+K14) -> #DIV/0! | L15: =L13/(L13+L14) -> #DIV/0! | M15: =M13/(M13+M14) -> 0 | N15: =N13/(N13+N14) -> #DIV/0! | O15: =O13/(O13+O14) -> #DIV/0! | P15: =P13/(P13+P14) -> 0 | Q15: =Q13/(Q13+Q14) -> #DIV/0!
E16: PREV. WEEK - PAY OUT | F16: =F15*0.05 -> 0 | G16: $- | H16: =F16/1.12 -> 0 | J16: Avg sale | K16: =K12/K13 -> #DIV/0! | L16: =L12/L13 -> #DIV/0! | M16: =M12/M13 -> #DIV/0! | N16: =N12/N13 -> #DIV/0! | O16: =O12/O13 -> #DIV/0! | P16: =P12/P13 -> #DIV/0! | Q16: =Q12/Q13 -> #DIV/0!
E17: 5 Star Review | H17: =F17/1.12 -> 0
E18: 5 Star Notes | F18: =T7 -> 0 | K18: Managment Summary - SALES ONLY - COLUMN F | R18: WEEKDAY | S18: WEEKEND
K19: MON | L19: TUE | M19: WED | N19: THU | O19: FRI | P19: Total | Q19: SAT | R19: Awaiting Payment | S19: Awaiting Payment
P20: =SUM(K20:O20) -> 0 | Q20: 0 | R20: =0 -> 0 | S20: =0 -> 0
J21: Successful | K21: =K13 -> 0 | L21: =L13 -> 0 | M21: =M13 -> 0 | N21: =N13 -> 0 | O21: =O13 -> 0 | P21: =P13 -> 0 | Q21: =Q13 -> 0
J22: Unsuccessful | K22: =K14 -> 0 | L22: =L14 -> 0 | M22: =M14 -> 2 | N22: =N14 -> 0 | O22: =O14 -> 0 | P22: =P14 -> 2 | Q22: =Q14 -> 0
J23: Success rate | K23: =K21/(K21+K22) -> #DIV/0! | L23: =L21/(L21+L22) -> #DIV/0! | M23: =M21/(M21+M22) -> 0 | N23: =N21/(N21+N22) -> #DIV/0! | O23: =O21/(O21+O22) -> #DIV/0! | P23: =P21/(P21+P22) -> 0 | Q23: =Q21/(Q21+Q22) -> #DIV/0!
J24: Avg sale | K24: =K20/K21 -> #DIV/0! | L24: =L20/L21 -> #DIV/0! | M24: =M20/M21 -> #DIV/0! | N24: =N20/N21 -> #DIV/0! | O24: =O20/O21 -> #DIV/0! | P24: =P20/P21 -> #DIV/0! | Q24: =Q20/Q21 -> #DIV/0!
B27: JOB DETAILS | F27: JOB AMOUNT | K27: PHOTOS | N27: QUOTE | Q27: INVOICE | U27: NOTES
B28: JOB STATUS | C28: DATE | D28: JOB # | E28: SUBURB | F28: AMOUNT EXC. GST | G28: MATERIALS | H28: Merchant Fees | I28: NET PROFIT | J28: PAID | K28: BEFORE | L28: AFTER | M28: RECEIPT | N28: DESCRIPTION | O28: SIGNED | P28: EMAILED | Q28: DESCRIPTION | R28: SIGNED | S28: EMAILED | T28: 5 Star Review | V28: EFTPOS | W28: CASH | X28: Payment Plan
B29: COMPLETED & PAID JOBS
B30: 1 | I30: =F30-G30-H30 -> 0
F31: =SUM(F30:F30) -> 0 | G31: =SUM(G30:G30) -> 0 | H31: =SUM(H30:H30) -> 0 | I31: =SUM(I30:I30) -> 0 | K31: =COUNT(K30:K30) -> 0 | L31: =COUNT(L30:L30) -> 0 | M31: =COUNT(M30:M30) -> 0 | N31: =COUNT(N30:N30) -> 0 | O31: =COUNT(O30:O30) -> 0 | P31: =COUNT(P30:P30) -> 0 | Q31: =COUNT(Q30:Q30) -> 0 | R31: =COUNT(R30:R30) -> 0 | S31: =COUNT(S30:S30) -> 0
K32: =SUM(K30:K30) -> 0 | L32: =SUM(L30:L30) -> 0 | M32: =SUM(M30:M30) -> 0 | N32: =SUM(N30:N30) -> 0 | O32: =SUM(O30:O30) -> 0 | P32: =SUM(P30:P30) -> 0 | Q32: =SUM(Q30:Q30) -> 0 | R32: =SUM(R30:R30) -> 0 | S32: =SUM(S30:S30) -> 0
B34: UNSUCCESSFUL JOBS
B35: 1 | C35: 45847 | D35: 71353/86092933 | E35: Dandenong North | F35: 681 | I35: =F35-G35-H35 -> 681 | J35: N/A | K35: 1 | N35: 1 | O35: 1 | P35: 1
